Workbook

Sheet 22.5월
B2: 자 금 일 보
J3: 계정과목 | K3: 설명
B4: ※ 자금현황 | G4: 44804 | J4: 복리후생비 | K4: 회식, 식대
B5: 구 분 | C5: 단위 | D5: 전월잔액 | E5: 수 입 | F5: 지 출 | G5: 기준일 기준 잔액 | J5: 여비교통비 | K5: 출장, 대중교통, 대리운전
B6: 신한 #672 | C6: KRW | E6: =sumif(B20:B129,B6,E20:E129) -> 50872576 | F6: =sumif(B20:B172,B6,F20:F172) -> 40470136 | G6: =D6+E6-F6 -> 10402440 | J6: 비품 | K6: 가구, 가전등 개당 단가 150만원이 넘는 용품
B7: WISE USD | C7: USD | E7: =sumif(B20:B172,B7,E20:E129) -> 0 | F7: =sumif(B20:B172,B7,F20:F172) -> 0 | G7: =D7+E7-F7 -> 0 | J7: 소모품비 | K7: 비품(150만원)으로 잡기에는 금액이 작은 비품
B8: WISE SGD | C8: SGD | E8: =sumif(B20:B129,B8,E20:E172) -> 0 | F8: =sumif(B20:B172,B8,F20:F172) -> 0 | G8: =D8+E8-F8 -> 0 | J8: 사무용품비 | K8: 비품, 소모품비를 제외한 업무용 사무용품 구입
B9: WISE KRW | C9: KRW | E9: =sumif(B20:B129,B9,E20:E129) -> 0 | F9: =sumif(B20:B172,B9,F20:F172) -> 0 | G9: =D9+E9-F9 -> 0 | J9: 통신비 | K9: 등기, 퀵 사용비
J10: 접대비 | K10: 외부 미팅
J11: 세금과공과 | K11: 세금 납부시
J12: 지급수수료 | K12: sms 수수료, 송금 수수료, 일반적으로 발생되는 모든 비용
B13: KRW 합 계 | J13: 미수금 | K13: 돌려 받을 예정인 금액 (ex. 부가세 환급금)
B14: USD 합 계 | J14: 용역비 | K14: 외주용역비
J15: 급여 | K15: 직원 급여
B18: ※ 세부내역
B19: 구 분 | C19: 날 짜 | D19: 은 행 적 요 | E19: 수입 | F19: 지출 | G19: 상세메모 | H19: 계정과목
B20: =B6 -> 신한 #672 | C20: 2022.05.25 12:29:55 | D20: 신규 | E20: 0 | F20: 0
B21: =B6 -> 신한 #672 | C21: 2022.05.25 12:51:34 | D21: 대체 | E21: 50000000 | F21: 0 | G21: 주식(사채)납입
B22: =B6 -> 신한 #672 | C22: 2022.05.25 12:55:39 | D22: 대체 | E22: 872557 | F22: 0
B23: =B6 -> 신한 #672 | C23: 2022.05.25 12:56:47 | D23: 대체 | E23: 19 | F23: 0
B24: =B6 -> 신한 #672 | C24: 2022.05.25 14:48:30 | D24: BZ뱅크 | E24: 0 | F24: 4400 | G24: 공동인증수수료 | H24: 지급수수료
B25: =B6 -> 신한 #672 | C25: 2022.05.25 15:22:16 | D25: BZ뱅크 | E25: 0 | F25: 6447167 | G25: 김석준05월급여 | H25: 급여
B26: =B6 -> 신한 #672 | C26: 2022.05.25 15:22:17 | D26: BZ뱅크 | E26: 0 | F26: 6447167 | G26: 전준영05월급여 | H26: 급여
B27: =B6 -> 신한 #672 | C27: 2022.05.25 15:22:17 | D27: BZ뱅크 | E27: 0 | F27: 6447167 | G27: 최고은05월급여 | H27: 급여
B28: =B6 -> 신한 #672 | C28: 2022.05.25 15:22:18 | D28: BZ뱅크 | E28: 0 | F28: 6446667 | G28: 강진석05월급여 | H28: 급여
B29: =B6 -> 신한 #672 | C29: 2022.05.25 15:22:18 | D29: BZ뱅크 | E29: 0 | F29: 2015103 | G29: 고유빈05월급여 | H29: 급여
B30: =B6 -> 신한 #672 | C30: 2022.05.25 15:22:19 | D30: BZ뱅크 | E30: 0 | F30: 1684965 | G30: 이태호05월급여 | H30: 급여
B31: =B6 -> 신한 #672 | C31: 2022.05.25 17:03:15 | D31: BZ뱅크 | E31: 0 | F31: 7832500 | G31: 개발자맥북구매 | H31: 비품
B32: =B6 -> 신한 #672 | C32: 2022.05.31 15:03:54 | D32: BZ뱅크 | E32: 0 | F32: 3089200 | G32: 바트5월개인 | H32: 여비교통비
B33: =B6 -> 신한 #672 | C33: 2022.05.31 15:08:07 | D33: BZ뱅크 | E33: 0 | F33: 55800 | G33: 진04월개인 | H33: 여비교통비

Sheet 22.6월
B2: 자 금 일 보
J3: 계정과목 | K3: 설명
B4: ※ 자금현황 | G4: 44804 | J4: 복리후생비 | K4: 회식, 식대
B5: 구 분 | C5: 단위 | D5: 전월잔액 | E5: 수 입 | F5: 지 출 | G5: 기준일 기준 잔액 | J5: 여비교통비 | K5: 출장, 대중교통, 대리운전
B6: 신한 #672 | C6: KRW | D6: 10402440 | E6: =sumif(B20:B129,B6,E20:E129) -> 128447937 | F6: =sumif(B20:B172,B6,F20:F172) -> 47664363 | G6: =D6+E6-F6 -> 91186014 | J6: 비품 | K6: 가구, 가전등 개당 단가 150만원이 넘는 용품
B7: WISE USD | C7: USD | E7: =sumif(B20:B172,B7,E20:E129) -> 0 | F7: =sumif(B20:B172,B7,F20:F172) -> 0 | G7: =D7+E7-F7 -> 0 | J7: 소모품비 | K7: 비품(150만원)으로 잡기에는 금액이 작은 비품
B8: WISE SGD | C8: SGD | E8: =sumif(B20:B129,B8,E20:E172) -> 0 | F8: =sumif(B20:B172,B8,F20:F172) -> 0 | G8: =D8+E8-F8 -> 0 | J8: 사무용품비 | K8: 비품, 소모품비를 제외한 업무용 사무용품 구입
B9: WISE KRW | C9: KRW | E9: =sumif(B20:B129,B9,E20:E129) -> 0 | F9: =sumif(B20:B172,B9,F20:F172) -> 0 | G9: =D9+E9-F9 -> 0 | J9: 통신비 | K9: 등기, 퀵 사용비
J10: 접대비 | K10: 외부 미팅
J11: 세금과공과 | K11: 세금 납부시
J12: 지급수수료 | K12: sms 수수료, 송금 수수료, 일반적으로 발생되는 모든 비용
B13: KRW 합 계 | J13: 미수금 | K13: 돌려 받을 예정인 금액 (ex. 부가세 환급금)
B14: USD 합 계 | J14: 용역비 | K14: 외주용역비
J15: 급여 | K15: 직원 급여
J16: 이자수익 | K16: 은행이자
J17: 서비스용역매출 | K17: 싱가폴 -> 한국 지사 송금
B18: ※ 세부내역
B19: 구 분 | C19: 날 짜 | D19: 은 행 적 요 | E19: 수입 | F19: 지출 | G19: 상세메모 | H19: 계정과목
B20: =B6 -> 신한 #672 | C20: 2022.06.07 13:53:34 | D20: BZ뱅크 | E20: 0 | F20: 177040 | G20: 05월지방세 | H20: 세금과공과
B21: =B6 -> 신한 #672 | C21: 2022.06.07 13:59:33 | D21: BZ뱅크 | E21: 0 | F21: 1770630 | G21: 05사업소득세 | H21: 세금과공과
B22: =B6 -> 신한 #672 | C22: 2022.06.18 02:11:20 | D22: 이자 | E22: 676 | F22: 0 | G22: 05.25~06.17 | H22: 이자수익
B23: =B6 -> 신한 #672 | C23: 2022.06.21 15:28:50 | D23: BZ뱅크 | E23: 0 | F23: 3916500 | G23: 개발자맥북구매 | H23: 비품
B24: =B6 -> 신한 #672 | C24: 2022.06.22 00:02:06 | D24: 신한체 | E24: 0 | F24: 30000 | G24: 네꼬 | H24: 접대비
B25: =B6 -> 신한 #672 | C25: 2022.06.22 11:00:13 | D25: 타행PC | E25: 128439661 | F25: 0 | G25: Zero X And | H25: 서비스용역매출
B26: =B6 -> 신한 #672 | C26: 2022.06.22 11:57:20 | D26: 신한체 | E26: 0 | F26: 5800 | G26: 로카모빌리티택 | H26: 여비교통비
B27: =B6 -> 신한 #672 | C27: 2022.06.22 16:53:06 | D27: 신한체 | E27: 0 | F27: 10700 | G27: 뚜레쥬르 역삼 | H27: 접대비
B28: =B6 -> 신한 #672 | C28: 2022.06.22 18:44:42 | D28: 신한체 | E28: 0 | F28: 7600 | G28: 카카오택시(선 | H28: 여비교통비
B29: =B6 -> 신한 #672 | C29: 2022.06.22 18:44:43 | D29: 신한체 | E29: 7600 | F29: 0 | G29: 카카오택시(선 | H29: 여비교통비
B30: =B6 -> 신한 #672 | C30: 2022.06.22 18:59:26 | D30: 신한체 | E30: 0 | F30: 3000 | G30: 카카오페이(택 | H30: 여비교통비
B31: =B6 -> 신한 #672 | C31: 2022.06.22 18:59:27 | D31: 신한체 | E31: 0 | F31: 4600 | G31: 카카오페이(택 | H31: 여비교통비
B32: =B6 -> 신한 #672 | C32: 2022.06.22 23:32:05 | D32: 신한체 | E32: 0 | F32: 300000 | G32: 스커트 | H32: 접대비
B33: =B6 -> 신한 #672 | C33: 2022.06.23 03:07:44 | D33: 신한체 | E33: 0 | F33: 22600 | G33: 티머니 법인택 | H33: 여비교통비
B34: =B6 -> 신한 #672 | C34: 2022.06.24 14:14:23 | D34: 신한체 | E34: 0 | F34: 16700 | G34: 카페아란 | H34: 접대비
B35: =B6 -> 신한 #672 | C35: 2022.06.24 14:19:48 | D35: BZ뱅크 | E35: 0 | F35: 5739378 | G35: 06전준영급여 | H35: 급여
B36: =B6 -> 신한 #672 | C36: 2022.06.24 14:37:50 | D36: BZ뱅크 | E36: 0 | F36: 5434828 | G36: 김석준 | H36: 급여
B37: =B6 -> 신한 #672 | C37: 2022.06.24 14:37:50 | D37: BZ뱅크 | E37: 0 | F37: 6061058 | G37: 최고은 | H37: 급여
B38: =B6 -> 신한 #672 | C38: 2022.06.24 14:37:51 | D38: BZ뱅크 | E38: 0 | F38: 5646698 | G38: 강진석 | H38: 급여
B39: =B6 -> 신한 #672 | C39: 2022.06.24 14:37:51 | D39: BZ뱅크 | E39: 0 | F39: 2275450 | G39: 고유빈 | H39: 급여
B40: =B6 -> 신한 #672 | C40: 2022.06.24 14:37:52 | D40: BZ뱅크 | E40: 0 | F40: 4904960 | G40: 이태호 | H40: 급여
B41: =B6 -> 신한 #672 | C41: 2022.06.24 14:37:52 | D41: BZ뱅크 | E41: 0 | F41: 2340480 | G41: 최지현 | H41: 급여
B42: =B6 -> 신한 #672 | C42: 2022.06.24 17:37:39 | D42: BZ뱅크 | E42: 0 | F42: 1777491 | G42: 김석준 | H42: 급여
B43: =B6 -> 신한 #672 | C43: 2022.06.24 17:37:40 | D43: BZ뱅크 | E43: 0 | F43: 3396328 | G43: 전준영 | H43: 급여
B44: =B6 -> 신한 #672 | C44: 2022.06.24 17:37:40 | D44: BZ뱅크 | E44: 0 | F44: 1012000 | G44: 강진석 | H44: 급여
B45: =B6 -> 신한 #672 | C45: 2022.06.26 19:20:02 | D45: 신한체 | E45: 0 | F45: 100000 | G45: 화평동 왕냉면 | H45: 접대비
B46: =B6 -> 신한 #672 | C46: 2022.06.27 18:48:55 | D46: 신한체 | E46: 0 | F46: 43000 | G46: 다채로움 월남 | H46: 접대비
B47: =B6 -> 신한 #672 | C47: 2022.06.27 21:56:39 | D47: 신한체 | E47: 0 | F47: 75000 | G47: 주식회사 드래 | H47: 접대비
B48: =B6 -> 신한 #672 | C48: 2022.06.28 14:14:49 | D48: 신한체 | E48: 0 | F48: 7200 | G48: 뚜레쥬르카페 | H48: 접대비
B49: =B6 -> 신한 #672 | C49: 2022.06.28 14:27:09 | D49: 신한체 | E49: 0 | F49: 8187 | G49: STARBUCKS COFF | H49: 여비교통비
B50: =B6 -> 신한 #672 | C50: 2022.06.28 18:29:06 | D50: 신한체 | E50: 0 | F50: 5600 | G50: 스마트로(비) | H50: 여비교통비
B51: =B6 -> 신한 #672 | C51: 2022.06.28 20:33:52 | D51: 신한체 | E51: 0 | F51: 54816 | G51: BEP NHA LUC TI | H51: 여비교통비
B52: =B6 -> 신한 #672 | C52: 2022.06.28 23:23:33 | D52: 신한체 | E52: 0 | F52: 4251 | G52: MPOS*SEEFAHRER | H52: 여비교통비
B53: =B6 -> 신한 #672 | C53: 2022.06.29 11:44:32 | D53: 신한체 | E53: 0 | F53: 1036073 | G53: HKD THE LUX | H53: 여비교통비
B54: =B6 -> 신한 #672 | C54: 2022.06.29 12:30:52 | D54: BZ뱅크 | E54: 0 | F54: 955300 | G54: 주식회사 웰리(광고대행비) | H54: 용역비
B55: =B6 -> 신한 #672 | C55: 2022.06.29 12:36:58 | D55: 신한체 | E55: 0 | F55: 3981 | G55: STARBUCKS ME L | H55: 여비교통비
B56: =B6 -> 신한 #672 | C56: 2022.06.29 13:36:49 | D56: 신한체 | E56: 0 | F56: 13500 | G56: 투썸플레이스 | H56: 접대비
B57: =B6 -> 신한 #672 | C57: 2022.06.29 16:41:32 | D57: 신한체 | E57: 0 | F57: 24569 | G57: GODMOTHER DONG | H57: 여비교통비
B58: =B6 -> 신한 #672 | C58: 2022.06.29 17:47:02 | D58: 신한체 | E58: 0 | F58: 3641 | G58: CAFE KATINAT | H58: 여비교통비
B59: =B6 -> 신한 #672 | C59: 2022.06.30 12:10:33 | D59: 신한체 | E59: 0 | F59: 29537 | G59: VINMEC SAIGON- | H59: 여비교통비
B60: =B6 -> 신한 #672 | C60: 2022.06.30 12:29:46 | D60: 신한체 | E60: 0 | F60: 7705 | G60: STARBUCKS LAND | H60: 여비교통비
B61: =B6 -> 신한 #672 | C61: 2022.06.30 13:10:16 | D61: 신한체 | E61: 0 | F61: 13412 | G61: ARYA CONSUMER | H61: 여비교통비
B62: =B6 -> 신한 #672 | C62: 2022.06.30 15:19:01 | D62: 신한체 | E62: 0 | F62: 104740 | G62: BORNGA-LANDMAR | H62: 여비교통비
B63: =B6 -> 신한 #672 | C63: 2022.06.30 18:00:05 | D63: 신한체 | E63: 0 | F63: 15000 | G63: 에이든청담호텔 | H63: 접대비
B64: =B6 -> 신한 #672 | C64: 2022.06.30 19:38:41 | D64: 신한체 | E64: 0 | F64: 6571 | G64: CN KUMHO-CTY T | H64: 여비교통비
B65: =B6 -> 신한 #672 | C65: 2022.06.30 20:29:23 | D65: 신한체 | E65: 0 | F65: 169000 | G65: 신칠성집 | H65: 접대비
B66: =B6 -> 신한 #672 | C66: 2022.06.30 22:29:16 | D66: 신한체 | E66: 0 | F66: 47439 | G66: MPOS*MABU KKO | H66: 여비교통비
B67: =B6 -> 신한 #672 | C67: 2022.06.30 23:20:29 | D67: 신한체 | E67: 0 | F67: 82000 | G67: 우미 호타루 | H67: 접대비

Sheet 22.7월
B2: 자 금 일 보
J3: 계정과목 | K3: 설명
B4: ※ 자금현황 | G4: 44804 | J4: 복리후생비 | K4: 회식, 식대
B5: 구 분 | C5: 단위 | D5: 전월잔액 | E5: 수 입 | F5: 지 출 | G5: 기준일 기준 잔액 | J5: 여비교통비 | K5: 출장, 대중교통, 대리운전
B6: 신한 #672 | C6: KRW | D6: 91186014 | E6: =sumif(B20:B154,B6,E20:E154) -> 131027419 | F6: =sumif(B20:B172,B6,F20:F172) -> 92085443 | G6: =D6+E6-F6 -> 130127990 | J6: 비품 | K6: 가구, 가전등 개당 단가 150만원이 넘는 용품
B7: WISE USD | C7: USD | E7: =sumif(B20:B172,B7,E20:E129) -> 0 | F7: =sumif(B20:B172,B7,F20:F172) -> 0 | G7: =D7+E7-F7 -> 0 | J7: 소모품비 | K7: 비품(150만원)으로 잡기에는 금액이 작은 비품
B8: WISE SGD | C8: SGD | E8: =sumif(B20:B129,B8,E20:E172) -> 0 | F8: =sumif(B20:B172,B8,F20:F172) -> 0 | G8: =D8+E8-F8 -> 0 | J8: 사무용품비 | K8: 비품, 소모품비를 제외한 업무용 사무용품 구입
B9: WISE KRW | C9: KRW | E9: =sumif(B20:B129,B9,E20:E129) -> 0 | F9: =sumif(B20:B172,B9,F20:F172) -> 0 | G9: =D9+E9-F9 -> 0 | J9: 통신비 | K9: 등기, 퀵 사용비
J10: 접대비 | K10: 외부 미팅
J11: 세금과공과 | K11: 세금 납부시
J12: 지급수수료 | K12: sms 수수료, 송금 수수료, 일반적으로 발생되는 모든 비용
B13: KRW 합 계 | J13: 미수금 | K13: 돌려 받을 예정인 금액 (ex. 부가세 환급금)
B14: USD 합 계 | J14: 용역비 | K14: 외주용역비
J15: 급여 | K15: 직원 급여
J16: 임차보증금 | K16: 보증금
J17: 서비스용역매출 | K17: 싱가폴 -> 한국 지사 송금
B18: ※ 세부내역
B19: 구 분 | C19: 날 짜 | D19: 은 행 적 요 | E19: 수입 | F19: 지출 | G19: 상세메모 | H19: 계정과목
B20: =B6 -> 신한 #672 | C20: 2022.07.01 00:29:33 | D20: 신한체 | E20: 0 | F20: 100 | G20: 택시_우티택시_ | H20: 여비교통비
B21: =B6 -> 신한 #672 | C21: 2022.07.01 00:29:46 | D21: 신한체 | E21: 100 | F21: 0 | G21: 택시_우티택시_ | H21: 여비교통비
B22: =B6 -> 신한 #672 | C22: 2022.07.01 00:29:49 | D22: 신한체 | E22: 0 | F22: 1000 | G22: 택시_우티택시_ | H22: 여비교통비
B23: =B6 -> 신한 #672 | C23: 2022.07.01 00:36:22 | D23: 신한체 | E23: 1000 | F23: 0 | G23: 택시_우티택시_ | H23: 여비교통비
B24: =B6 -> 신한 #672 | C24: 2022.07.01 00:38:33 | D24: 신한체 | E24: 0 | F24: 19400 | G24: 카카오택시(선 | H24: 여비교통비
B25: =B6 -> 신한 #672 | C25: 2022.07.01 00:38:34 | D25: 신한체 | E25: 19400 | F25: 0 | G25: 카카오택시(선 | H25: 여비교통비
B26: =B6 -> 신한 #672 | C26: 2022.07.01 00:56:14 | D26: 신한체 | E26: 0 | F26: 15400 | G26: 카카오페이(택 | H26: 여비교통비
B27: =B6 -> 신한 #672 | C27: 2022.07.01 00:56:15 | D27: 신한체 | E27: 0 | F27: 3000 | G27: 카카오페이(택 | H27: 여비교통비
B28: =B6 -> 신한 #672 | C28: 2022.07.01 01:24:58 | D28: 신한체 | E28: 0 | F28: 51563 | G28: MPOS*CONCEPT | H28: 여비교통비
B29: =B6 -> 신한 #672 | C29: 2022.07.01 14:19:05 | D29: 신한체 | E29: 0 | F29: 21093 | G29: TASTE OF SAIGO | H29: 여비교통비
B30: =B6 -> 신한 #672 | C30: 2022.07.01 14:24:43 | D30: 신한체 | E30: 0 | F30: 4442 | G30: TCH - 1011815 | H30: 여비교통비
B31: =B6 -> 신한 #672 | C31: 2022.07.01 15:53:27 | D31: 신한체 | E31: 0 | F31: 7416 | G31: ARYA CONSUMER | H31: 여비교통비
B32: =B6 -> 신한 #672 | C32: 2022.07.01 21:52:03 | D32: 신한체 | E32: 0 | F32: 5302 | G32: SASCO-G19D10 | H32: 여비교통비
B33: =B6 -> 신한 #672 | C33: 2022.07.02 08:39:32 | D33: 신한체 | E33: 0 | F33: 45000 | G33: 인천국제공항공 | H33: 여비교통비
B34: =B6 -> 신한 #672 | C34: 2022.07.03 13:13:13 | D34: 신한체 | E34: 0 | F34: 11600 | G34: 카카오택시 선 | H34: 여비교통비
B35: =B6 -> 신한 #672 | C35: 2022.07.03 13:13:14 | D35: 신한체 | E35: 11600 | F35: 0 | G35: 카카오택시 선 | H35: 여비교통비
B36: =B6 -> 신한 #672 | C36: 2022.07.03 13:35:27 | D36: 신한체 | E36: 0 | F36: 10700 | G36: 카카오개인택시 | H36: 여비교통비
B37: =B6 -> 신한 #672 | C37: 2022.07.04 13:50:05 | D37: 신한체 | E37: 0 | F37: 25000 | G37: 소담칼국수 | H37: 접대비
B38: =B6 -> 신한 #672 | C38: 2022.07.04 17:40:02 | D38: BZ공과 | E38: 0 | F38: 2071630 | G38: 국세납부 | H38: 세금과공과
B39: =B6 -> 신한 #672 | C39: 2022.07.04 17:44:54 | D39: BZ공과 | E39: 0 | F39: 207120 | G39: 서울시지방세 | H39: 세금과공과
B40: =B6 -> 신한 #672 | C40: 2022.07.04 18:18:23 | D40: 신한체 | E40: 0 | F40: 6000 | G40: 스마트로(비) | H40: 여비교통비
B41: =B6 -> 신한 #672 | C41: 2022.07.05 12:52:31 | D41: 신한체 | E41: 0 | F41: 10800 | G41: 투썸플레이스( | H41: 접대비
B42: =B6 -> 신한 #672 | C42: 2022.07.05 14:44:46 | D42: 신한체 | E42: 0 | F42: 4000 | G42: 올드타운한양 | H42: 접대비
B43: =B6 -> 신한 #672 | C43: 2022.07.05 17:10:19 | D43: 신한체 | E43: 0 | F43: 12410 | G43: 폴바셋 GFC | H43: 접대비
B44: =B6 -> 신한 #672 | C44: 2022.07.05 18:04:19 | D44: 카드결 | E44: 0 | F44: 291725 | G44: CENTRAL SG RIV | H44: 여비교통비
B45: =B6 -> 신한 #672 | C45: 2022.07.05 21:53:29 | D45: 신한체 | E45: 0 | F45: 884000 | G45: 큰물참치(강남 | H45: 복리후생비
B46: =B6 -> 신한 #672 | C46: 2022.07.06 01:20:31 | D46: 신한체 | E46: 0 | F46: 23300 | G46: 카카오택시(선 | H46: 여비교통비
B47: =B6 -> 신한 #672 | C47: 2022.07.06 01:20:31 | D47: 신한체 | E47: 23300 | F47: 0 | G47: 카카오택시(선 | H47: 여비교통비
B48: =B6 -> 신한 #672 | C48: 2022.07.06 02:42:23 | D48: 신한체 | E48: 0 | F48: 21600 | G48: 카카오택시(선 | H48: 여비교통비
B49: =B6 -> 신한 #672 | C49: 2022.07.06 02:42:24 | D49: 신한체 | E49: 21600 | F49: 0 | G49: 카카오택시(선 | H49: 여비교통비
B50: =B6 -> 신한 #672 | C50: 2022.07.06 03:11:25 | D50: 신한체 | E50: 0 | F50: 24200 | G50: 카카오페이(택 | H50: 여비교통비
B51: =B6 -> 신한 #672 | C51: 2022.07.06 15:23:51 | D51: 신한체 | E51: 0 | F51: 22500 | G51: 유한회사 카페 | H51: 접대비
B52: =B6 -> 신한 #672 | C52: 2022.07.06 16:47:32 | D52: 신한체 | E52: 0 | F52: 9800 | G52: 유한회사 카페 | H52: 접대비
B53: =B6 -> 신한 #672 | C53: 2022.07.06 16:52:47 | D53: 신한체 | E53: 0 | F53: 10500 | G53: KCP-결제 | H53: 소모품비
B54: =B6 -> 신한 #672 | C54: 2022.07.07 15:06:46 | D54: 신한체 | E54: 0 | F54: 238775 | G54: HELLOSIGN YEAR | H54: 지급수수료
B55: =B6 -> 신한 #672 | C55: 2022.07.07 18:58:01 | D55: 신한체 | E55: 0 | F55: 44300 | G55: 폴트버거 판교 | H55: 접대비
B56: =B6 -> 신한 #672 | C56: 2022.07.07 21:31:06 | D56: 신한체 | E56: 0 | F56: 5000 | G56: 카카오 T 주차 | H56: 여비교통비
B57: =B6 -> 신한 #672 | C57: 2022.07.11 07:03:22 | D57: 의보 | E57: 0 | F57: 2649820 | G57: 2206국민건강 | H57: 세금과공과
B58: =B6 -> 신한 #672 | C58: 2022.07.11 07:04:02 | D58: 보험료 | E58: 0 | F58: 506610 | G58: 2206고용보험 | H58: 세금과공과
B59: =B6 -> 신한 #672 | C59: 2022.07.11 07:04:37 | D59: 연금 | E59: 0 | F59: 2573800 | G59: 2206국민연금 | H59: 세금과공과
B60: =B6 -> 신한 #672 | C60: 2022.07.11 07:04:39 | D60: 보험료 | E60: 0 | F60: 207970 | G60: 2206산재보험 | H60: 세금과공과
B61: =B6 -> 신한 #672 | C61: 2022.07.11 16:12:41 | D61: 신한체 | E61: 0 | F61: 13400 | G61: 더보이 | H61: 접대비
B62: =B6 -> 신한 #672 | C62: 2022.07.11 20:29:31 | D62: BZ뱅크 | E62: 0 | F62: 12600000 | G62: 사무실보증금 | H62: 임차보증금
B63: =B6 -> 신한 #672 | C63: 2022.07.12 21:44:11 | D63: 신한체 | E63: 0 | F63: 17500 | G63: 카카오택시 선 | H63: 여비교통비
B64: =B6 -> 신한 #672 | C64: 2022.07.12 21:44:11 | D64: 신한체 | E64: 17500 | F64: 0 | G64: 카카오택시 선 | H64: 여비교통비
B65: =B6 -> 신한 #672 | C65: 2022.07.12 22:04:52 | D65: 신한체 | E65: 0 | F65: 16300 | G65: 카카오법인택시 | H65: 여비교통비
B66: =B6 -> 신한 #672 | C66: 2022.07.13 02:44:13 | D66: 신한체 | E66: 0 | F66: 19400 | G66: 카카오택시 선 | H66: 여비교통비
B67: =B6 -> 신한 #672 | C67: 2022.07.13 02:44:13 | D67: 신한체 | E67: 19400 | F67: 0 | G67: 카카오택시 선 | H67: 여비교통비
B68: =B6 -> 신한 #672 | C68: 2022.07.13 03:16:15 | D68: 신한체 | E68: 0 | F68: 21600 | G68: 카카오법인택시 | H68: 여비교통비
B69: =B6 -> 신한 #672 | C69: 2022.07.13 12:10:25 | D69: 신한체 | E69: 0 | F69: 11000 | G69: 에이씨알 판교 | H69: 접대비
B70: =B6 -> 신한 #672 | C70: 2022.07.13 13:29:31 | D70: 신한체 | E70: 0 | F70: 4000 | G70: 카카오 T 주차 | H70: 여비교통비
B71: =B6 -> 신한 #672 | C71: 2022.07.13 15:39:11 | D71: 신한체 | E71: 0 | F71: 9600 | G71: 에잇이얼스(8Ye | H71: 접대비
B72: =B6 -> 신한 #672 | C72: 2022.07.13 22:31:12 | D72: 신한체 | E72: 0 | F72: 19000 | G72: 카카오T대리 | H72: 여비교통비
B73: =B6 -> 신한 #672 | C73: 2022.07.14 03:49:09 | D73: 신한체 | E73: 0 | F73: 26000 | G73: 카카오T대리 | H73: 여비교통비
B74: =B6 -> 신한 #672 | C74: 2022.07.14 11:00:13 | D74: 타행PC | E74: 129619579 | F74: 0 | G74: Zero X And | H74: 서비스용역매출
B75: =B6 -> 신한 #672 | C75: 2022.07.14 14:09:07 | D75: 신한체 | E75: 0 | F75: 1900 | G75: 데이롱 카페 평 | H75: 접대비
B76: =B6 -> 신한 #672 | C76: 2022.07.14 15:15:39 | D76: 신한체 | E76: 0 | F76: 18100 | G76: 카카오택시 선 | H76: 여비교통비
B77: =B6 -> 신한 #672 | C77: 2022.07.14 15:15:39 | D77: 신한체 | E77: 18100 | F77: 0 | G77: 카카오택시 선 | H77: 여비교통비
B78: =B6 -> 신한 #672 | C78: 2022.07.14 15:35:35 | D78: 신한체 | E78: 0 | F78: 5600 | G78: 로카모빌리티_ | H78: 여비교통비
B79: =B6 -> 신한 #672 | C79: 2022.07.14 15:38:00 | D79: 신한체 | E79: 0 | F79: 17900 | G79: 카카오법인택시 | H79: 여비교통비
B80: =B6 -> 신한 #672 | C80: 2022.07.14 21:12:25 | D80: 신한체 | E80: 0 | F80: 256000 | G80: 디히랑 | H80: 접대비
B81: =B6 -> 신한 #672 | C81: 2022.07.15 15:39:21 | D81: BZ뱅크 | E81: 0 | F81: 325000 | G81: 본점이전등기 | H81: 지급수수료
B82: =B6 -> 신한 #672 | C82: 2022.07.15 16:50:44 | D82: BZ뱅크 | E82: 0 | F82: 2483872 | G82: 패스트파이브07 | H82: 지급수수료
B83: =B6 -> 신한 #672 | C83: 2022.07.18 13:42:14 | D83: 신한체 | E83: 0 | F83: 39000 | G83: 흥부이가 | H83: 접대비
B84: =B6 -> 신한 #672 | C84: 2022.07.18 16:20:22 | D84: 신한체 | E84: 0 | F84: 1012140 | G84: G마켓 | H84: 사무용품비
B85: =B6 -> 신한 #672 | C85: 2022.07.18 16:25:17 | D85: 신한체 | E85: 0 | F85: 178000 | G85: 쿠팡(주) | H85: 사무용품비
B86: =B6 -> 신한 #672 | C86: 2022.07.18 16:49:32 | D86: 신한체 | E86: 0 | F86: 176000 | G86: 네이버파이낸셜 | H86: 사무용품비
B87: =B6 -> 신한 #672 | C87: 2022.07.18 23:24:22 | D87: 신한체 | E87: 0 | F87: 23200 | G87: 카카오택시(선 | H87: 여비교통비
B88: =B6 -> 신한 #672 | C88: 2022.07.18 23:24:22 | D88: 신한체 | E88: 23200 | F88: 0 | G88: 카카오택시(선 | H88: 여비교통비
B89: =B6 -> 신한 #672 | C89: 2022.07.18 23:45:50 | D89: 신한체 | E89: 0 | F89: 18300 | G89: 티머니 법인택 | H89: 여비교통비
B90: =B6 -> 신한 #672 | C90: 2022.07.19 18:37:59 | D90: 신한체 | E90: 0 | F90: 324000 | G90: FUNSHOP | H90: 사무용품비
B91: =B6 -> 신한 #672 | C91: 2022.07.19 20:21:02 | D91: 신한체 | E91: 0 | F91: 156000 | G91: 진대감 | H91: 접대비
B92: =B6 -> 신한 #672 | C92: 2022.07.20 13:18:48 | D92: 신한체 | E92: 0 | F92: 5300 | G92: GS25 강남쌍용 | H92: 여비교통비
B93: =B6 -> 신한 #672 | C93: 2022.07.20 17:15:01 | D93: 신한체 | E93: 0 | F93: 91800 | G93: 쿠팡 | H93: 사무용품비
B94: =B6 -> 신한 #672 | C94: 2022.07.20 18:45:31 | D94: 신한체 | E94: 0 | F94: 123410 | G94: 쿠팡(주) | H94: 사무용품비
B95: =B6 -> 신한 #672 | C95: 2022.07.20 19:00:41 | D95: 신한체 | E95: 0 | F95: 10890 | G95: 쿠팡(주) | H95: 사무용품비
B96: =B6 -> 신한 #672 | C96: 2022.07.21 11:24:12 | D96: 신한체 | E96: 0 | F96: 13500 | G96: 씨유 샛별한양 | H96: 사무용품비
B97: =B6 -> 신한 #672 | C97: 2022.07.21 14:00:06 | D97: 신한체 | E97: 178000 | F97: 0 | G97: 쿠팡(주) | H97: 사무용품비
B98: =B6 -> 신한 #672 | C98: 2022.07.21 16:14:41 | D98: 신한체 | E98: 0 | F98: 6000 | G98: 라츠3 | H98: 접대비
B99: =B6 -> 신한 #672 | C99: 2022.07.21 17:15:26 | D99: BZ뱅크 | E99: 0 | F99: 1000500 | G99: 블록체인위크 | H99: 지급수수료
B100: =B6 -> 신한 #672 | C100: 2022.07.22 11:36:06 | D100: BZ뱅크 | E100: 0 | F100: 42500 | G100: 반품택배비 | H100: 통신비
B101: =B6 -> 신한 #672 | C101: 2022.07.22 12:17:56 | D101: 신한체 | E101: 0 | F101: 7800 | G101: 카카오택시(선 | H101: 여비교통비
...

Sheet 22.8월
B2: 자 금 일 보
J3: 계정과목 | K3: 설명
B4: ※ 자금현황 | G4: 44804 | J4: 복리후생비 | K4: 회식, 식대
B5: 구 분 | C5: 단위 | D5: 전월잔액 | E5: 수 입 | F5: 지 출 | G5: 기준일 기준 잔액 | J5: 여비교통비 | K5: 출장, 대중교통, 대리운전
B6: 신한 #672 | C6: KRW | D6: 130127990 | E6: =sumif(B20:B129,B6,E20:E129) -> 2611400 | F6: =sumif(B20:B172,B6,F20:F172) -> 74432901 | G6: =D6+E6-F6 -> 58306489 | J6: 비품 | K6: 가구, 가전등 개당 단가 150만원이 넘는 용품
B7: WISE USD | C7: USD | D7: 164894.9 | E7: =sumif(B20:B172,B7,E20:E129) -> 0 | F7: =sumif(B20:B172,B7,F20:F172) -> 2123.31 | G7: =D7+E7-F7 -> 162771.59 | J7: 소모품비 | K7: 비품(150만원)으로 잡기에는 금액이 작은 비품
B8: WISE SGD | C8: SGD | D8: 30914.81 | E8: =sumif(B20:B129,B8,E20:E172) -> 0 | F8: =sumif(B20:B172,B8,F20:F172) -> 9070.92 | G8: =D8+E8-F8 -> 21843.89 | J8: 사무용품비 | K8: 비품, 소모품비를 제외한 업무용 사무용품 구입
B9: WISE KRW | C9: KRW | D9: 393788 | E9: =sumif(B20:B129,B9,E20:E129) -> 0 | F9: =sumif(B20:B172,B9,F20:F172) -> 393788 | G9: =D9+E9-F9 -> 0 | J9: 통신비 | K9: 등기, 퀵 사용비
J10: 접대비 | K10: 외부 미팅
J11: 세금과공과 | K11: 세금 납부시
J12: 지급수수료 | K12: sms 수수료, 송금 수수료, 일반적으로 발생되는 모든 비용
B13: KRW 합 계 | J13: 미수금 | K13: 돌려 받을 예정인 금액 (ex. 부가세 환급금)
B14: USD 합 계 | J14: 용역비 | K14: 외주용역비
J15: 급여 | K15: 직원 급여
B18: ※ 세부내역
B19: 구 분 | C19: 날 짜 | D19: 은 행 적 요 | E19: 수입 | F19: 지출 | G19: 상세메모 | H19: 계정과목
B20: 신한 #672 | C20: 2022.08.01 | D20: 황해도찹쌀순대 | E20: 0 | F20: 84000 | G20: 일반음식점 - 황해도찹쌀순대 | H20: 접대비
B21: 신한 #672 | C21: 2022.08.01 | D21: (주)부자되세요 | E21: 0 | F21: 42000 | G21: 일반음식점 - 창고43 강남점 | H21: 접대비
B22: 신한 #672 | C22: 2022.08.01 | D22: 티머니 개인택 | E22: 0 | F22: 6800 | G22: 택시비 | H22: 여비교통비
B23: 신한 #672 | C23: 2022.08.01 | D23: 카카오택시(선 | E23: 0 | F23: 8700 | G23: 택시비 | H23: 여비교통비
B24: 신한 #672 | C24: 2022.08.01 | D24: 카카오택시(선 | E24: 8700 | F24: 0 | G24: 택시비 | H24: 여비교통비
B25: 신한 #672 | C25: 2022.08.01 | D25: 카카오페이(택 | E25: 0 | F25: 8300 | G25: 택시비 | H25: 여비교통비
B26: 신한 #672 | C26: 2022.08.01 | D26: (주)해담채강남 | E26: 0 | F26: 1109100 | G26: 일반음식점 - 해담채강남점 | H26: 복리후생비
B27: 신한 #672 | C27: 2022.08.01 | D27: (주)해담채강남 | E27: 1109100 | F27: 0 | G27: 일반음식점 - 해담채강남점 (할인위해 취소함) | H27: 복리후생비
B28: 신한 #672 | C28: 2022.08.01 | D28: (주)해담채강남 | E28: 0 | F28: 1019000 | G28: 일반음식점 - 해담채강남점 (할인가로 재결제) | H28: 복리후생비
B29: 신한 #672 | C29: 2022.08.01 | D29: 짬뽕지존 역삼 | E29: 0 | F29: 208000 | G29: 일반음식점 - 짬뽕지존 역삼점 | H29: 복리후생비
B30: 신한 #672 | C30: 2022.08.02 | D30: 신동궁감자탕뼈 | E30: 0 | F30: 108000 | G30: 일반음식점 - 신동궁감자탕 | H30: 복리후생비
B31: 신한 #672 | C31: 2022.08.02 | D31: 카카오택시(선 | E31: 51600 | F31: 0 | G31: 택시비 | H31: 여비교통비
... B48: 신한 #672 | C48: 2022.08.05 | D48: 명함제작비 | E48: 0 | F48: 349800 | G48: 명함통- 명함제작비 | H48: 사무용품비
B49: 신한 #672 | C49: 2022.08.08 | D49: 명함제작비 | E49: 0 | F49: 52800 | G49: 명함통 - 명함제작비 (추가금:별색) | H49: 사무용품비 | I49: =F49*1300 -> 68640000
B50: 신한 #672 | C50: 2022.08.08 | D50: 인천->호치민 | E50: 0 | F50: 1002600 | G50: 비행기표 - 인천->호치민 | H50: 여비교통비
B51: 신한 #672 | C51: 2022.08.08 | D51: 호치민->인천 | E51: 0 | F51: 355600 | G51: 비행기표 - 호치민->인천 | H51: 여비교통비
B52: 신한 #672 | C52: 2022.08.08 | D52: 채선당 사계리 | E52: 0 | F52: 54700 | G52: 일반음식점 - 채선당 사계리점 | H52: 접대비
B53: 신한 #672 | C53: 2022.08.09 | D53: 이슬님컴퓨터 | E53: 0 | F53: 1439420 | G53: 신규입사자 컴퓨터 구매 - 이슬님 | H53: 소모품비
B54: 신한 #672 | C54: 2022.08.09 | D54: 한무쇼핑(주)무 | E54: 0 | F54: 19000 | G54: 현대백화점 무역센터점 - 식품관 | H54: 접대비
B55: 신한 #672 | C55: 2022.08.10 | D55: 2207국민건강 | E55: 0 | F55: 3149360 | G55: 202207국민건강 | H55: 세금과공과
B56: 신한 #672 | C56: 2022.08.10 | D56: 2207국민연금 | E56: 0 | F56: 3202000 | G56: 202207국민연금 | H56: 세금과공과
B57: 신한 #672 | C57: 2022.08.10 | D57: 2207고용보험 | E57: 0 | F57: 746470 | G57: 202207고용보험 | H57: 세금과공과
B58: 신한 #672 | C58: 2022.08.10 | D58: 2207산재보험 | E58: 0 | F58: 278420 | G58: 202207산재보험 | H58: 세금과공과
B59: 신한 #672 | C59: 2022.08.10 | D59: 잔고증명영사 | E59: 0 | F59: 309500 | G59: 잔고증명서 영사인증 진행비 (위드문) | H59: 지급수수료
B60: 신한 #672 | C60: 2022.08.10 | D60: 문용준 | E60: 0 | F60: 31400 | G60: 잔고증명서 영사인증 진행비 부가세 (위드문) | H60: 지급수수료
B61: 신한 #672 | C61: 2022.08.10 | D61: 올드타운한양 | E61: 0 | F61: 15000 | G61: 일반음식점 - 올드타운한양 | H61: 접대비
... B127: WISE KRW | C127: 2022.08.09 | D127: Airbnb * Hmzy2m29p3 | E127: 0 | F127: 269708 | G127: 베트남 출장 숙소비 | H127: 여비교통비
B128: WISE SGD | C128: 2022.08.02 | D128: Google | E128: - | F128: 284.29 | G128: Google 사용료 | H128: 지급수수료
B129: WISE SGD | C129: 2022.08.08 | D129: Google Cloud Wdnv9w | E129: 0 | F129: 1000 | G129: Google Cloud 사용료 | H129: 지급수수료
B130: WISE SGD | C130: 2022.08.15 | D130: Google* Cloud Fjj4q8 | E130: 0 | F130: 1000 | G130: Google Cloud 사용료 | H130: 지급수수료
B131: WISE SGD | C131: 2022.08.17 | D131: EBOS SG PTE LTD | E131: 0 | F131: 2790.61 | G131: EBOS 어카운팅 서비스 | H131: 지급수수료
B132: WISE SGD | C132: 2022.08.21 | D132: Google* Cloud 92jszv | E132: 0 | F132: 1000 | G132: Google Cloud 사용료 | H132: 지급수수료
B133: WISE SGD | C133: 2022.08.23 | D133: Grab | E133: 0 | F133: 8.75 | G133: 베트남 택시비 | H133: 여비교통비
B134: WISE SGD | C134: 2022.08.23 | D134: Grab | E134: 0 | F134: 0.6 | G134: 베트남 택시비 | H134: 여비교통비
B135: WISE SGD | C135: 2022.08.24 | D135: Grab | E135: 0 | F135: 6.53 | G135: 베트남 택시비 | H135: 여비교통비
B136: WISE SGD | C136: 2022.08.24 | D136: Grab | E136: 0 | F136: 6.12 | G136: 베트남 택시비 | H136: 여비교통비
B137: WISE SGD | C137: 2022.08.24 | D137: Grab | E137: 0 | F137: 1.91 | G137: 베트남 택시비 | H137: 여비교통비
B138: WISE SGD | C138: 2022.08.25 | D138: Tran Nguyen Ngoc Tam | E138: 0 | F138: 1797.33 | G138: 08월 급여 - 해외직원 - 따미 | H138: 급여
B139: WISE SGD | C139: 2022.08.25 | D139: Tran Nguyen Ngoc Tam | E139: 0 | F139: 70.77 | G139: 08월 개인비용 정산 - 해외직원 - 따미 | H139: 지급수수료
B140: WISE SGD | C140: 2022.08.25 | D140: Grab | E140: 0 | F140: 1.85 | G140: 베트남 택시비 | H140: 여비교통비
... B163: WISE SGD | C163: 2022.08.28 | D163: Google*Cloud N95xl7 | E163: 0 | F163: 1000 | G163: Google Cloud 사용료 | H163: 지급수수료
B164: WISE USD | C164: 2022.08.01 | D164: Slack T02tfdseum8 | E164: - | F164: 158.54 | G164: Slack 사용료 | H164: 지급수수료
B165: WISE USD | C165: 2022.08.01 | D165: Google Gsuite_0xtribe.com | E165: - | F165: 110.72 | G165: Gsuite 사용료 | H165: 지급수수료
B166: WISE USD | C166: 2022.08.03 | D166: Name-Cheap.com*Xfz8k | E166: 0 | F166: 131.96 | G166: 도메인 구입비 | H166: 지급수수료
B167: WISE USD | C167: 2022.08.04 | D167: Notion Labs, Inc | E167: 0 | F167: 129.41 | G167: Notion 사용료 | H167: 지급수수료
B168: WISE USD | C168: 2022.08.09 | D168: Airbnb * Hmzy2m29p3 | E168: 0 | F168: 262.64 | G168: 베트남 출장 숙소비 | H168: 여비교통비
B169: WISE USD | C169: 2022.08.14 | D169: Postmarkapp.com | E169: 0 | F169: 10 | G169: 개발 이메일 딜리버리 서비스 | H169: 지급수수료
B170: WISE USD | C170: 2022.08.16 | D170: Name-Cheap.com*Vmisqn | E170: 0 | F170: 14.16 | G170: 도메인 사용료 | H170: 지급수수료
B171: WISE USD | C171: 2022.08.17 | D171: Nguyen Duc Hieu Thao | E171: 0 | F171: 1003.29 | G171: 베트남 길드 외주용역비 | H171: 용역비
B172: WISE USD | C172: 2022.08.25 | D172: Jezza Mae L. Asencio | E172: 0 | F172: 302.59 | G172: 08월 급여 - 해외직원 - 에이스 | H172: 급여

Sheet 22.9월
B2: 자 금 일 보
J3: 계정과목 | K3: 설명
B4: ※ 자금현황 | G4: 기준일: 2022.09.30 | J4: 복리후생비 | K4: 회식, 식대
B5: 구 분 | C5: 단위 | D5: 전월잔액 | E5: 수 입 | F5: 지 출 | G5: 기준일 기준 잔액 | J5: 여비교통비 | K5: 출장, 대중교통, 대리운전
B6: 신한 #672 | C6: KRW | D6: 58306489 | E6: =sumif(B20:B107,B6,E20:E107) -> 21402 | F6: =sumif(B20:B107,B6,F20:F107) -> 33969133 | G6: =D6+E6-F6 -> 24358758 | J6: 비품 | K6: 가구, 가전등 개당 단가 150만원이 넘는 용품
B7: WISE USD | C7: USD | D7: 162771.59 | E7: =sumif(B20:B107,B7,E20:E107) -> 0 | F7: =sumif(B20:B107,B7,F20:F107) -> 105398.73 | G7: =D7+E7-F7 -> 57372.86 | J7: 소모품비 | K7: 비품(150만원)으로 잡기에는 금액이 작은 비품
B8: WISE SGD | C8: SGD | D8: 21843.89 | E8: =sumif(B20:B107,B8,E20:E107) -> 0 | F8: =sumif(B20:B107,B8,F20:F107) -> 7963.21 | G8: =D8+E8-F8 -> 13880.68 | J8: 사무용품비 | K8: 비품, 소모품비를 제외한 업무용 사무용품 구입
B9: WISE KRW | C9: KRW | D9: 0 | E9: =sumif(B20:B107,B9,E20:E107) -> 0 | F9: =sumif(B20:B107,B9,F20:F107) -> 0 | G9: =D9+E9-F9 -> 0 | J9: 통신비 | K9: 등기, 퀵 사용비
B10: 신한 #543 | C10: USD | D10: 0 | E10: =sumif(B20:B107,B10,E20:E107) -> 199975.6 | F10: =sumif(B20:B107,B10,F20:F107) -> 0 | G10: =D10+E10-F10 -> 199975.6 | J10: 접대비 | K10: 외부 미팅
B11: 하나 #304 | C11: KRW | D11: 0 | E11: =sumif(B20:B107,B11,E20:E107) -> 139598000 | F11: =sumif(B20:B107,B11,F20:F107) -> 52356488 | G11: =D11+E11-F11 -> 87241512 | J11: 세금과공과 | K11: 세금 납부시
B12: 하나 #138 | C12: USD | D12: 0 | E12: =sumif(B20:B107,B12,E20:E107) -> 100000 | F12: =sumif(B20:B107,B12,F20:F107) -> 100000 | G12: =D12+E12-F12 -> 0 | J12: 지급수수료 | K12: sms 수수료, 송금 수수료, 일반적으로 발생되는 모든 비용
B13: KRW 합 계 | J13: 미수금 | K13: 돌려 받을 예정인 금액 (ex. 부가세 환급금)
B14: USD 합 계 | J14: 용역비 | K14: 외주용역비
J15: 급여 | K15: 직원 급여
J16: 서비스용역매출 | K16: 싱가폴 -> 한국 지사 송금
J17: 광고매출 | K17: 타법인 매출
B18: ※ 세부내역 | J18: 보통예금 | K18: 예금간 이체
B19: 구 분 | C19: 날 짜 | D19: 은 행 적 요 | E19: 수입 | F19: 지출 | G19: 상세메모 | H19: 계정과목
B20: 신한 #543 | C20: 2022.09.23 | D20: FTX DIGITAL MA | E20: 199975.6 | F20: 0 | G20: 싱가폴 법인 - 마케팅 대행비 입금 | H20: 서비스용역매출
B21: 신한 #672 | C21: 2022.09.02 | D21: 진심 왕돈까스 | E21: 0 | F21: 31500 | G21: 일반음식점 - 진심 왕돈까스 | H21: 접대비
B22: 신한 #672 | C22: 2022.09.02 | D22: 08개인비용Baht | E22: 0 | F22: 146020 | G22: 2022.08월 바트 개인비용정산 | H22: 지급수수료
B23: 신한 #672 | C23: 2022.09.02 | D23: 08개인비용-Gon | E23: 0 | F23: 29200 | G23: 2022.08월 고니 개인비용정산 | H23: 지급수수료
B24: 신한 #672 | C24: 2022.09.02 | D24: 08개인비용-Jin | E24: 0 | F24: 81000 | G24: 2022.08월 진 개인비용정산 | H24: 지급수수료
B25: 신한 #672 | C25: 2022.09.02 | D25: 08월법률자문료 | E25: 0 | F25: 3025000 | G25: 2022.08월 비앤케이 법률자문료 | H25: 지급수수료
B26: =B6 -> 신한 #672 | C26: 2022.09.02 19:01:51 | D26: 두나무주 | E26: 0 | F26: 600000 | G26: UDC2022 티켓 구매 (2장 - 펠릭스,아이작) | H26: 여비교통비
B27: =B6 -> 신한 #672 | C27: 2022.09.05 12:09:07 | D27: 한국철도공사 ( | E27: 0 | F27: 59800 | G27: UDC2022 출장 - 기차표 | H27: 여비교통비
B28: =B6 -> 신한 #672 | C28: 2022.09.05 12:20:03 | D28: SR | E28: 0 | F28: 52000 | G28: UDC2022출장 - 기차표 | H28: 여비교통비
B29: 신한 #672 | C29: 2022.09.02 | D29: 고유빈 | E29: 0 | F29: 32500 | G29: 2022.08월 코빈 개인비용정산 | H29: 지급수수료
B30: 신한 #672 | C30: 2022.09.06 | D30: 법원행정처 | E30: 0 | F30: 1000 | G30: 법원행정처 | H30: 지급수수료
B31: 신한 #672 | C31: 2022.09.06 | D31: 09소득세 | E31: 0 | F31: 2537830 | G31: 2022.09월 소득세 | H31: 세금과공과
B32: 신한 #672 | C32: 2022.09.06 | D32: 09주민세 | E32: 0 | F32: 253720 | G32: 2022.09월 주민세 | H32: 세금과공과
B33: 신한 #672 | C33: 2022.09.07 | D33: 진_축하금 | E33: 0 | F33: 300000 | G33: 진 배우자 출산 축하금 | H33: 지급수수료
B34: 신한 #672 | C34: 2022.09.13 | D34: 2208국민건강 | E34: 0 | F34: 4086460 | G34: 2022.08 국민건강 | H34: 세금과공과
B35: 신한 #672 | C35: 2022.09.13 | D35: 2208국민연금 | E35: 0 | F35: 4182900 | G35: 2022.08 국민연금 | H35: 세금과공과
B36: 신한 #672 | C36: 2022.09.13 | D36: 2208고용보험 | E36: 0 | F36: 941000 | G36: 2022.08 고용보험 | H36: 세금과공과
B37: 신한 #672 | C37: 2022.09.13 | D37: 2208산재보험 | E37: 0 | F37: 348680 | G37: 2022.08 산재보험 | H37: 세금과공과
B38: 신한 #672 | C38: 2022.09.15 | D38: 코스콤 | E38: 0 | F38: 110000 | G38: 법인 범용 공인인증서 발급 | H38: 지급수수료
B39: 신한 #672 | C39: 2022.09.16 | D39: 노무법인청안 | E39: 0 | F39: 110000 | G39: 노무법인 청안 컨설팅료 | H39: 지급수수료
B40: 신한 #672 | C40: 2022.09.17 | D40: 06.18~09.16 | E40: 21396 | F40: 0 | G40: 은행 이자 | H40: 미수금
... B43: 신한 #672 | C43: 2022.09.21 | D43: PAYPAL PTE | E43: 5 | F43: 0 | G43: PAYPAL PTE | H43: 미수금
B44: =B6 -> 신한 #672 | C44: 2022.09.22 10:34:52 | D44: 출장여비경비 | E44: 0 | F44: 300500 | G44: alma 베트남 출장여비 | H44: 여비교통비
B45: =B6 -> 신한 #672 | C45: 2022.09.22 16:26:31 | D45: 베트남출장여비 | E45: 0 | F45: 100500 | G45: gonnie 싱가폴 출장여비 | H45: 여비교통비
B46: 신한 #672 | C46: 2022.09.21 | D46: PAYPAL PTE | E46: 1 | F46: 0 | G46: PAYPAL PTE | H46: 미수금
B47: 신한 #672 | C47: 2022.09.26 | D47: 노무법인청안 | E47: 0 | F47: 110000 | G47: 노무법인 청안 컨설팅료 | H47: 지급수수료
B48: 신한 #672 | C48: 2022.09.26 | D48: 삼덕회계법인 | E48: 0 | F48: 330000 | G48: 삼덕회계법인 기장비용 | H48: 지급수수료
B49: 신한 #672 | C49: 2022.09.26 | D49: 현대카드(주) | E49: 0 | F49: 2471524 | G49: 현대법인신용카드 | H49: 지급수수료
B50: 신한 #672 | C50: 2022.09.27 | D50: 신규입사자장비 | E50: 0 | F50: 7832500 | G50: 신규입사자 장비 구매(향진,에이든) | H50: 비품
B51: 신한 #672 | C51: 2022.09.30 | D51: 9월사무실임대 | E51: 0 | F51: 5499999 | G51: 9월 패파 사무실 임대료 | H51: 복리후생비
B52: 하나 #138 | C52: 2022.09.22 | D52: 주식회사 제로엑스앤드코리아 | E52: 0 | F52: 100000 | G52: 싱가폴 법인에서 송금된 운영비 원화로 환전 | H52: 보통예금
B53: 하나 #138 | C53: 2022.09.22 | D53: ZERO X AND PTE. LTD. | E53: 100000 | F53: 0 | G53: 싱가폴 법인 - 운영비 입금 (USD) | H53: 서비스용역매출
B54: =B11 -> 하나 #304 | C54: 2022.09.23 | E54: 0 | F54: 49938488 | G54: 2022.09월 급여 | H54: 급여
B55: 하나 #304 | C55: 2022.09.23 | D55: 이이슬 | E55: 0 | F55: 2418000 | G55: 07월프리랜스비용-재무자문료 | H55: 지급수수료
B56: 하나 #304 | C56: 2022.09.22 | D56: 주식회사 제로엑스앤드코리아 | E56: 139598000 | F56: 0 | G56: 싱가폴 법인 - 운영비 환전 | H56: 보통예금
B57: WISE SGD | C57: 2022.09.02 | D57: Google *Cloud 92m3jj | E57: 0 | F57: 591.91 | G57: Google Cloud 사용료 | H57: 지급수수료
B58: WISE SGD | C58: 2022.09.08 | D58: Google*Cloud Fcmpkw | E58: 0 | F58: 1000 | G58: Google Cloud 사용료 | H58: 지급수수료
B59: WISE SGD | C59: 2022.09.12 | D59: Google*Cloud 97bpw6 | E59: 0 | F59: 1000 | G59: Google Cloud 사용료 | H59: 지급수수료
B60: WISE SGD | C60: 2022.09.17 | D60: Google*Cloud Pvmzzk | E60: 0 | F60: 1000 | G60: Google Cloud 사용료 | H60: 지급수수료
B61: WISE SGD | C61: 2022.09.22 | D61: Google*Cloud 393d9p | E61: 0 | F61: 1000 | G61: Google Cloud 사용료 | H61: 지급수수료
B62: WISE SGD | C62: 2022.09.26 | D62: EBOS SG PTE LTD | E62: 0 | F62: 430.61 | G62: 싱가폴법인 회계기장비용 | H62: 지급수수료
B63: WISE SGD | C63: 2022.09.27 | D63: Google*Cloud Whxszc | E63: 0 | F63: 1000 | G63: Google Cloud 사용료 | H63: 지급수수료
B64: WISE USD | C64: 2022.09.01 | D64: Slack T02tfdseum8 | E64: 0 | F64: 218.8 | G64: Slack 사용비 | H64: 지급수수료
B65: WISE USD | C65: 2022.09.01 | D65: Google Gsuite_0xtribe.com | E65: 0 | F65: 143.07 | G65: Google Gsuite 사용료 | H65: 지급수수료
B66: WISE USD | C66: 2022.09.07 | D66: Coinmarketcapproapisub | E66: 0 | F66: 948 | G66: CoinMarketCap 사용료 | H66: 지급수수료
... B68: WISE USD | C68: 2022.09.09 | D68: Name-Cheap.com*Ap518f | E68: 0 | F68: 68.88 | G68: 도메인 사용료 | H68: 지급수수료
B69: =B8 -> WISE SGD | C69: 2022.09.23 | D69: Grab*A-4w664nvgwh32 | E69: 0 | F69: 8.2 | G69: Grab 택시비 | H69: 여비교통비
B70: =B8 -> WISE SGD | C70: 2022.09.23 | D70: Grab*A-4w7n5p6wwfrd | E70: 0 | F70: 1.51 | G70: Grab 택시비 | H70: 여비교통비
B71: =B8 -> WISE SGD | C71: 2022.09.23 | D71: Grab*A-4w82ekdgwir7 | E71: 0 | F71: 2.72 | G71: Grab 택시비 | H71: 여비교통비
B72: =B8 -> WISE SGD | C72: 2022.09.23 | D72: Grab | E72: 0 | F72: 3.08 | G72: Grab 택시비 | H72: 여비교통비
B73: =B8 -> WISE SGD | C73: 2022.09.23 | D73: Grab | E73: 0 | F73: 2.01 | G73: Grab 택시비 | H73: 여비교통비
B74: =B8 -> WISE SGD | C74: 2022.09.24 | D74: Grab | E74: 0 | F74: 1.82 | G74: Grab 택시비 | H74: 여비교통비
B75: =B8 -> WISE SGD | C75: 2022.09.24 | D75: Grab | E75: 0 | F75: 0.85 | G75: Grab 택시비 | H75: 여비교통비
B76: =B8 -> WISE SGD | C76: 2022.09.24 | D76: Grab | E76: 0 | F76: 2.25 | G76: Grab 택시비 | H76: 여비교통비
B77: =B8 -> WISE SGD | C77: 2022.09.24 | D77: Nha Hang Marukame Udon | E77: 0 | F77: 12.08 | G77: Grab 택시비 | H77: 여비교통비
B78: =B8 -> WISE SGD | C78: 2022.09.24 | D78: Grab | E78: 0 | F78: 1.46 | G78: Grab 택시비 | H78: 여비교통비
B79: =B8 -> WISE SGD | C79: 2022.09.25 | D79: Grab | E79: 0 | F79: 1.16 | G79: Grab 택시비 | H79: 여비교통비
B80: =B8 -> WISE SGD | C80: 2022.09.25 | D80: Grab | E80: 0 | F80: 0.85 | G80: Grab 택시비 | H80: 여비교통비
B81: =B8 -> WISE SGD | C81: 2022.09.25 | D81: Grab | E81: 0 | F81: 5.47 | G81: Grab 택시비 | H81: 여비교통비
B82: =B8 -> WISE SGD | C82: 2022.09.26 | D82: Grab | E82: 0 | F82: 7.43 | G82: Grab 택시비 | H82: 여비교통비
B83: =B8 -> WISE SGD | C83: 2022.09.26 | D83: Grab | E83: 0 | F83: 3.1 | G83: Grab 택시비 | H83: 여비교통비
B84: =B8 -> WISE SGD | C84: 2022.09.26 | D84: Grab | E84: 0 | F84: 1.88 | G84: Grab 택시비 | H84: 여비교통비
B85: =B8 -> WISE SGD | C85: 2022.09.26 | D85: Grab | E85: 0 | F85: 4.39 | G85: Grab 택시비 | H85: 여비교통비
B86: WISE USD | C86: 2022.09.14 | D86: Github | E86: 0 | F86: 13.42 | G86: 소프트웨어 사용료 | H86: 지급수수료
B87: =B8 -> WISE SGD | C87: 2022.09.26 | D87: Tran Nguyen Ngoc Tam | E87: 0 | F87: 1831.37 | G87: Tami 급여 | H87: 급여
B88: =B8 -> WISE SGD | C88: 2022.09.26 | D88: Grab | E88: 0 | F88: 1.16 | G88: Grab 택시비 | H88: 여비교통비
B89: =B8 -> WISE SGD | C89: 2022.09.26 | D89: Grab | E89: 0 | F89: 0.86 | G89: Grab 택시비 | H89: 여비교통비
B90: =B8 -> WISE SGD | C90: 2022.09.26 | D90: Grab | E90: 0 | F90: 1.95 | G90: Grab 택시비 | H90: 여비교통비
B91: WISE USD | C91: 2022.09.14 | D91: Postmarkapp.com | E91: 0 | F91: 10 | G91: 이메일 딜리버리 서비스 사용료 | H91: 지급수수료
B92: =B8 -> WISE SGD | C92: 2022.09.27 | D92: Grab | E92: 0 | F92: 5.3 | G92: Grab 택시비 | H92: 여비교통비
B93: =B8 -> WISE SGD | C93: 2022.09.27 | D93: Grab | E93: 0 | F93: 0.86 | G93: Grab 택시비 | H93: 여비교통비
B94: =B8 -> WISE SGD | C94: 2022.09.27 | D94: Grab | E94: 0 | F94: 0.86 | G94: Grab 택시비 | H94: 여비교통비
B95: =B8 -> WISE SGD | C95: 2022.09.27 | D95: Grab | E95: 0 | F95: 1.34 | G95: Grab 택시비 | H95: 여비교통비
B96: WISE USD | C96: 2022.09.21 | D96: Zero X And Korea Inc. | E96: 0 | F96: 100014.39 | G96: 한국 법인 운영비 | H96: 용역비
B97: WISE USD | C97: 2022.09.27 | D97: Mileston Business Group, LLC. | E97: 0 | F97: 398.39 | G97: Chris 개인비용 정산 | H97: 지급수수료
B98: WISE USD | C98: 2022.09.27 | D98: Nguyen Duc Hiue Thao | E98: 0 | F98: 3334.39 | G98: 베트남 서비스 마케팅 및 운영비 | H98: 용역비
B99: =B8 -> WISE SGD | C99: 2022.09.28 | D99: Grab | E99: 0 | F99: 7.48 | G99: Grab 택시비 | H99: 여비교통비
B100: =B8 -> WISE SGD | C100: 2022.09.28 | D100: Grab | E100: 0 | F100: 0.62 | G100: Grab 택시비 | H100: 여비교통비
B101: =B8 -> WISE SGD | C101: 2022.09.30 | D101: Grab | E101: 0 | F101: 11.18 | G101: Grab 택시비 | H101: 여비교통비
B102: =B8 -> WISE SGD | C102: 2022.09.30 | D102: Grab | E102: 0 | F102: 0.55 | G102: Grab 택시비 | H102: 여비교통비
B103: =B8 -> WISE SGD | C103: 2022.09.30 | D103: Grab | E103: 0 | F103: 3.02 | G103: Grab 택시비 | H103: 여비교통비
B104: =B8 -> WISE SGD | C104: 2022.09.30 | D104: Grab | E104: 0 | F104: 0.85 | G104: Grab 택시비 | H104: 여비교통비
...

Sheet 22.10월
B2: 자 금 일 보
J3: 계정과목 | K3: 설명
B4: ※ 자금현황 | G4: 기준일: 2022.10.31 | J4: 복리후생비 | K4: 회식, 식대
B5: 구 분 | C5: 단위 | D5: 전월잔액 | E5: 수 입 | F5: 지 출 | G5: 기준일 기준 잔액 | J5: 여비교통비 | K5: 출장, 대중교통, 대리운전
B6: 신한 #672 | C6: KRW | D6: ='22.9월'!G6 -> 24358758 | E6: =sumif(B20:B61,B6,E20:E61) -> 143690000 | F6: =sumif(B20:B61,B6,F20:F61) -> 32442224 | G6: =D6+E6-F6 -> 135606534 | J6: 비품 | K6: 가구, 가전등 개당 단가 150만원이 넘는 용품
B7: WISE USD | C7: USD | D7: ='22.9월'!G7 -> 57372.86 | E7: =sumif(B20:B61,B7,E20:E61) -> 0 | F7: =sumif(B20:B61,B7,F20:F61) -> 10094.39 | G7: =D7+E7-F7 -> 47278.47 | J7: 소모품비 | K7: 비품(150만원)으로 잡기에는 금액이 작은 비품
B8: WISE SGD | C8: SGD | D8: ='22.9월'!G8 -> 13880.68 | E8: =sumif(B20:B61,B8,E20:E61) -> 0 | F8: =sumif(B20:B61,B8,F20:F61) -> 9203.93 | G8: =D8+E8-F8 -> 4676.75 | J8: 사무용품비 | K8: 비품, 소모품비를 제외한 업무용 사무용품 구입
B9: WISE KRW | C9: KRW | D9: ='22.9월'!G9 -> 0 | E9: =sumif(B20:B61,B9,E20:E61) -> 0 | F9: =sumif(B20:B61,B9,F20:F61) -> 0 | G9: =D9+E9-F9 -> 0 | J9: 통신비 | K9: 등기, 퀵 사용비
B10: 신한 #543 | C10: USD | D10: ='22.9월'!G10 -> 199975.6 | E10: =sumif(B20:B61,B10,E20:E61) -> 0 | F10: =sumif(B20:B61,B10,F20:F61) -> 100000 | G10: =D10+E10-F10 -> 99975.6 | J10: 접대비 | K10: 외부 미팅
B11: 하나 #304 | C11: KRW | D11: ='22.9월'!G11 -> 87241512 | E11: =sumif(B20:B61,B11,E20:E61) -> 0 | F11: =sumif(B20:B61,B11,F20:F61) -> 57494593 | G11: =D11+E11-F11 -> 29746919 | J11: 세금과공과 | K11: 세금 납부시
B12: 하나 #138 | C12: USD | D12: ='22.9월'!G12 -> 0 | E12: =sumif(B20:B61,B12,E20:E61) -> 0 | F12: =sumif(B20:B61,B12,F20:F61) -> 0 | G12: =D12+E12-F12 -> 0 | J12: 지급수수료 | K12: sms 수수료, 송금 수수료, 일반적으로 발생되는 모든 비용
B13: KRW 합 계 | D13: =D6+D9+D11 -> 111600270 | E13: =E6+E9+E11 -> 143690000 | F13: =F6+F9+F11 -> 89936817 | G13: =G6+G9+G11 -> 165353453 | J13: 미수금 | K13: 돌려 받을 예정인 금액 (ex. 부가세 환급금)
B14: USD 합 계 | D14: =D7+D10+D12 -> 257348.46 | E14: =E7+E10+E12 -> 0 | F14: =F7+F10+F12 -> 110094.39 | G14: =G7+G10+G12 -> 147254.07 | H14: =rounddown(G14*1420.9,0) -> 209233308 | J14: 용역비 | K14: 외주용역비
B15: SGD 합 계 | D15: =D8 -> 13880.68 | E15: =E8 -> 0 | F15: =F8 -> 9203.93 | G15: =G8 -> 4676.75 | J15: 급여 | K15: 직원 급여
J16: 서비스용역매출 | K16: 싱가폴 -> 한국 지사 송금
J17: 광고매출 | K17: 타법인 매출
B18: ※ 세부내역 | J18: 보통예금 | K18: 예금간 이체
B19: 구 분 | C19: 날 짜 | D19: 은 행 적 요 | E19: 수입 | F19: 지출 | G19: 상세메모 | H19: 계정과목
B20: 신한 #543 | C20: 2022.10.24 | D20: 환전 | E20: 0 | F20: 100000 | G20: 싱가폴 법인 - 운영비 환전 | H20: 보통예금
B21: 신한 #672 | C21: 2022.10.06 | D21: 법률사무소 비앤케이 | E21: 0 | F21: 825000 | G21: 09월법률자문료 | H21: 지급수수료
B22: 신한 #672 | C22: 2022.10.06 | D22: 09근로소득세 | E22: 0 | F22: 3598860 | G22: 09근로소득세 | H22: 세금과공과 | K22: 135606534
B23: 신한 #672 | C23: 2022.10.06 | D23: 09사업소득세 | E23: 0 | F23: 75000 | G23: 09사업소득세 | H23: 세금과공과 | K23: 47278.47
B24: 신한 #672 | C24: 2022.10.06 | D24: 09지방소득세 | E24: 0 | F24: 367320 | G24: 09지방소득세 | H24: 세금과공과 | K24: 4676.75
B25: 신한 #672 | C25: 2022.10.11 | D25: 2022.10.11 07:03:03 | E25: 0 | F25: 4406280 | G25: 2209국민건강 | H25: 세금과공과 | K25: 0
B26: 신한 #672 | C26: 2022.10.11 | D26: 2209국민연금 | E26: 0 | F26: 4511360 | G26: 2209국민연금 | H26: 세금과공과 | K26: 99975.6
B27: 신한 #672 | C27: 2022.10.11 | D27: 2209고용보험 | E27: 0 | F27: 1069990 | G27: 2209고용보험 | H27: 세금과공과 | K27: 29746919
B28: 신한 #672 | C28: 2022.10.11 | D28: 2209산재보험 | E28: 0 | F28: 396500 | G28: 2209산재보험 | H28: 세금과공과 | K28: 0
B29: 신한 #672 | C29: 2022.10.13 | D29: 번역공증수수료 | E29: 0 | F29: 34000 | G29: 번역공증수수료 | H29: 지급수수료
B30: 신한 #672 | C30: 2022.10.20 | D30: 이니시스-정기 | E30: 0 | F30: 440 | G30: 사무실 프린트 비용 | H30: 사무용품비
B31: 신한 #672 | C31: 2022.10.20 | D31: OTP수수료 | E31: 0 | F31: 5000 | G31: OTP 추가발급 수수료 | H31: 지급수수료
B32: 신한 #672 | C32: 2022.10.20 | D32: 이니시스-정기 | E32: 0 | F32: 550 | G32: 사무실 프린트 비용 | H32: 사무용품비
B33: 신한 #672 | C33: 2022.10.24 | D33: 공동인증수수료 | E33: 0 | F33: 4400 | G33: 카드,OTP 인증 은행 수수료 | H33: 지급수수료
B34: 신한 #672 | C34: 2022.10.24 | D34: 코오롱엘에스아 | E34: 0 | F34: 1100500 | G34: 부산 출장 숙소비 | H34: 여비교통비
B35: 신한 #672 | C35: 2022.10.24 | D35: 환전 | E35: 143690000 | F35: 0 | G35: 싱가폴 법인 - 운영비 환전 | H35: 보통예금
B36: 신한 #672 | C36: 2022.10.25 | D36: 노무법인청안 | E36: 0 | F36: 110000 | G36: 노무 컨설팅 비용 | H36: 지급수수료
B37: 신한 #672 | C37: 2022.10.25 | D37: 삼덕회계법인 | E37: 0 | F37: 330000 | G37: 회계 기장 대리 비용 | H37: 지급수수료
B38: 신한 #672 | C38: 2022.10.25 | D38: 현대카드(주) | E38: 0 | F38: 7098922 | G38: 현대카드10월사용분 | H38: 지급수수료
B39: 신한 #672 | C39: 2022.10.27 | D39: 비대면바우처_1 | E39: 0 | F39: 800000 | G39: 케이바우처 - GPRO | H39: 지급수수료
B40: 신한 #672 | C40: 2022.10.28 | D40: Risa-개인비용 | E40: 0 | F40: 369600 | G40: Risa 개인비용 정산 | H40: 여비교통비
... B61: WISE USD | C61: 2022.10.26 | D61: Github | E61: 0 | F61: 148 | G61: 인터넷 호스팅 서비스 및 소프트웨어 개발 | H61: 지급수수료

Sheet 22.11월
B1: 자 금 일 보
K2: 계정과목 | L2: 설명
B3: ※ 자금현황 | G3: 기준일: 2022.11.30 | K3: 복리후생비 | L3: 회식, 식대
B4: 구 분 | C4: 단위 | D4: 전월잔액 | E4: 수 입 | F4: 지 출 | G4: 기준일 기준 잔액 | K4: 여비교통비 | L4: 출장, 대중교통, 대리운전
B5: 신한 #672 | C5: KRW | D5: 135606534 | E5: =sumif(B21:B128,B5,E21:E128) -> 136965758 | F5: =sumif(B21:B171,B5,F21:F171) -> 171929206 | G5: =D5+E5-F5 -> 100643086 | K5: 비품 | L5: 가구, 가전등 개당 단가 150만원이 넘는 용품
B6: 신한 #543 | C6: USD | D6: 99975.6 | E6: =sumif(B21:B130,B6,E21:E130) -> 0 | F6: =sumif(B21:B171,B6,F21:F171) -> 99975.6 | G6: =D6+E6-F6 -> 0 | K6: 소모품비 | L6: 비품(150만원)으로 잡기에는 금액이 작은 비품
B7: 하나 #304 | C7: KRW | D7: 29746919 | E7: =sumif(B21:B130,B7,E21:E130) -> 0 | F7: =sumif(B21:B171,B7,F21:F171) -> 2315185 | G7: =D7+E7-F7 -> 27431734 | K7: 사무용품비 | L7: 비품, 소모품비를 제외한 업무용 사무용품 구입
B8: 하나 #138 | C8: USD | D8: 0 | E8: =sumif(B21:B130,B8,E21:E130) -> 0 | F8: =sumif(B21:B171,B8,F21:F171) -> 0 | G8: =D8+E8-F8 -> 0 | K8: 통신비 | L8: 등기, 퀵 사용비
B9: WISE USD | C9: USD | D9: 47278.47 | E9: =sumif(B21:B171,B9,E21:E128) -> 0 | F9: =sumif(B21:B171,B9,F21:F171) -> 14456.91 | G9: =D9+E9-F9 -> 32821.56 | K9: 접대비 | L9: 외부 미팅
B10: WISE SGD | C10: SGD | D10: 4676.75 | E10: =sumif(B21:B128,B10,E21:E171) -> 0 | F10: =sumif(B21:B171,B10,F21:F171) -> 4676.75 | G10: =D10+E10-F10 -> 0 | K10: 세금과공과 | L10: 세금 납부시
B11: WISE KRW | C11: KRW | D11: 0 | E11: =sumif(B21:B130,B11,E21:E130) -> 0 | F11: =sumif(B21:B171,B11,F21:F171) -> 0 | G11: =D11+E11-F11 -> 0 | K11: 지급수수료 | L11: sms 수수료, 송금 수수료, 일반적으로 발생되는 모든 비용
B12: OCBC USD | C12: USD | D12: 7121.24 | E12: =sumif(B21:B130,B12,E21:E130) -> 0 | F12: =sumif(B21:B170,B12,F21:F170) -> 0 | G12: =D12+E12-F12 -> 7121.24 | K12: 미수금 | L12: 돌려 받을 예정인 금액 (ex. 부가세 환급금)
B13: OCBC SGD | C13: SGD | D13: 930 | E13: =sumif(B21:B130,B13,E21:E130) -> 0 | F13: =sumif(B21:B170,B13,F21:F170) -> 20 | G13: =D13+E13-F13 -> 910 | K13: 용역비 | L13: 외주용역비
B15: KRW 합 계 | D15: =D5+D7+D11 -> 165353453 | E15: =E5+E7+E11 -> 136965758 | F15: =F5+F7+F11 -> 174244391 | G15: =G5+G11+G7 -> 128074820 | H15: =G15 -> 128074820 | K15: 급여 | L15: 직원 급여
B16: USD 합 계 | D16: =D6+D8+D9+D12 -> 154375.31 | E16: =E6+E8+E9+E12 -> 0 | F16: =F6+F8+F9+F12 -> 114432.51 | G16: =G9+G6+G8+G12 -> 39942.8 | H16: =rounddown(G16*1335.9,0) -> 53359586 | K16: 서비스용역매출 | L16: 싱가폴 -> 한국 지사 송금
B17: SGD 합 계 | D17: =D10+D13 -> 5606.75 | E17: =E10+E13 -> 0 | F17: =F10+F13 -> 4696.75 | G17: =G10+G13 -> 910 | H17: =rounddown(G17*970.9,0) -> 883519 | K17: 광고매출 | L17: 타법인 매출
H18: =SUM(H15:H17) -> 182317925 | K18: 보통예금 | L18: 예금간 이체
B19: ※ 세부내역
B20: 구 분 | C20: 날 짜 | D20: 은 행 적 요 | E20: 수입 | F20: 지출 | G20: 상세메모 | H20: 계정과목
B21: 신한 #543 | C21: 2022.11.14 | D21: (주)제로엑스앤드코리아 | E21: 0 | F21: 99975.6 | G21: 환전 | H21: 보통예금
B22: 신한 #672 | C22: 2022.11.01 | D22: 김재욱(법률사 | E22: 0 | F22: 825000 | G22: 비앤케이 10월 법률자문료 | H22: 지급수수료
B23: 신한 #672 | C23: 2022.11.02 | D23: 알마validator | E23: 0 | F23: 1013092 | G23: 알마 경비 정산 | H23: 지급수수료
B24: 신한 #672 | C24: 2022.11.01 | D24: 신한체크카드 | E24: 0 | F24: 110 | G24: 컬러 프린트 비용 | H24: 지급수수료
B25: 신한 #672 | C25: 2022.11.07 | D25: 신한카드10월카 | E25: 0 | F25: 200 | G25: 신한카드 10월카드사용알림서비스 이용료 | H25: 지급수수료
B26: 신한 #672 | C26: 2022.11.08 | D26: 10월소득세 | E26: 0 | F26: 4043620 | G26: 10월 소득세 납부 | H26: 세금과공과
B27: 신한 #672 | C27: 2022.11.08 | D27: 10월주민세 | E27: 0 | F27: 404290 | G27: 10월 주민세 납부 | H27: 세금과공과
B28: 신한 #672 | C28: 2022.11.09 | D28: 국세 | E28: 4163130 | F28: 0 | G28: 환급금 | H28: 미수금
B29: 신한 #672 | C29: 2022.11.10 | D29: 의보 | E29: 0 | F29: 4406280 | G29: 2210국민건강 | H29: 세금과공과
B30: 신한 #672 | C30: 2022.11.10 | D30: 연금 | E30: 0 | F30: 4605900 | G30: 2210국민연금 | H30: 세금과공과
B31: 신한 #672 | C31: 2022.11.10 | D31: 보험료 | E31: 0 | F31: 1157270 | G31: 2210고용보험 | H31: 세금과공과
B32: 신한 #672 | C32: 2022.11.10 | D32: 보험료 | E32: 0 | F32: 428860 | G32: 2210산재보험 | H32: 세금과공과
B33: 신한 #672 | C33: 2022.11.10 | D33: BZ뱅크 | E33: 0 | F33: 10000500 | G33: 사무실계약금 | H33: 지급수수료
B34: 신한 #672 | C34: 2022.11.14 | D34: 환전 | E34: 132637628 | G34: 환전 입금 | H34: 보통예금
B35: 신한 #672 | C35: 2022.11.14 | D35: 공증문서번역비 | E35: 0 | F35: 330500 | G35: 공증문서번역비 | H35: 지급수수료 | K35: =F15-SUM(F33,F35,F43,F46,F63,F64,F65) -> 84736891 | L35: 1회성 제외
B36: 신한 #672 | C36: 2022.11.14 | D36: 신한체크 | E36: 0 | F36: 110 | G36: 프린트비 | H36: 지급수수료 | K36: =K35-SUM(F62,F66) -> 78760310 | L36: 법카 제외 금액
B37: 신한 #672 | C37: 2022.11.14 | D37: 신한체크 | E37: 0 | F37: 110 | G37: 프린트비 | H37: 지급수수료 | K37: =SUM(F69:F82)*1300 -> 24873758 | L37: 인프라 비용, Chris
B38: 신한 #672 | C38: 2022.11.14 | D38: 신한체크 | E38: 0 | F38: 110 | G38: 프린트비 | H38: 지급수수료 | K38: =SUM(K36:K37) -> 103634068
B39: 신한 #672 | C39: 2022.11.14 | D39: 신한체크 | E39: 0 | F39: 550 | G39: 프린트비 | H39: 지급수수료
B40: 신한 #672 | C40: 2022.11.15 | D40: 명함 제작비 | E40: 0 | F40: 17000 | G40: 명함 제작비 - 케빈 | H40: 지급수수료
B41: 신한 #672 | C41: 2022.11.16 | D41: 명함 배송비 | E41: 0 | F41: 9000 | G41: 명함 배송비 | H41: 지급수수료
B42: 신한 #672 | C42: 2022.11.16 | D42: 서초번역 | E42: 165000 | F42: 0 | G42: 공증번역 할인비 | H42: 미수금
B43: 신한 #672 | C43: 2022.11.22 | D43: 그림바우빌딩 | E43: 0 | F43: 70000500 | G43: 사무실임대보증금(잔금) | H43: 지급수수료
B44: 신한 #672 | C44: 2022.11.23 | D44: 연법무사 | E44: 0 | F44: 325500 | G44: 등기이전 | H44: 지급수수료
B45: 신한 #672 | C45: 2022.11.23 | D45: (주)안양신도판매 | E45: 0 | F45: 300500 | G45: 복합기보증금 | H45: 지급수수료
B46: 신한 #672 | C46: 2022.11.23 | D46: 신태양부동산 | E46: 0 | F46: 4752500 | G46: 부동산중개수수료 | H46: 지급수수료
B47: 신한 #672 | C47: 2022.11.23 | D47: 에스원 | E47: 0 | F47: 100000 | G47: 세콤 보증금 | H47: 지급수수료
B48: 신한 #672 | C48: 2022.11.25 | D48: 11월급여 | E48: 0 | F48: 5726328 | G48: 11월급여-Baht | H48: 급여
B49: 신한 #672 | C49: 2022.11.25 | D49: 11월급여 | E49: 0 | F49: 5415408 | G49: 11월급여-alma | H49: 급여
B50: 신한 #672 | C50: 2022.11.25 | D50: 11월급여 | E50: 0 | F50: 5412708 | G50: 11월급여-Gon | H50: 급여
... B77: WISE USD | C77: 2022.11.14 | D77: Postmarkapp.com | E77: 0 | F77: 10 | G77: 개발 관련 서비스 | H77: 지급수수료
B78: WISE USD | C78: 2022.11.21 | D78: Google Cloud Jhfcwc | E78: 0 | F78: 707.66 | G78: Google Cloud 사용료 | H78: 지급수수료 | K78: 102719586
B79: WISE USD | C79: 2022.11.15 | D79: Nguyen Duc Hiue Thao | E79: 0 | F79: 1003.29 | G79: 해튼길드 투자 | H79: 지급수수료 | K79: 0
B80: WISE USD | C80: 2022.11.25 | D80: Tran Nguyen Ngoc Tam | E80: 0 | F80: 1219.53 | G80: 11월급여-Tami | H80: 급여 | K80: 27431734
B81: WISE USD | C81: 2022.11.25 | D81: Google Cloud Jz4d3b | E81: 0 | F81: 730.31 | G81: Google Cloud 사용료 | H81: 지급수수료 | K81: 0
B82: WISE USD | C82: 2022.11.29 | D82: Google Cloud Vdz2bw | E82: 0 | F82: 731.73 | G82: Google Cloud 사용료 | H82: 지급수수료 | K82: 32821.56
K83: 0
K84: 0
K85: 7121.24
K86: 920

Sheet 22.12월
B1: 자 금 일 보
I2: Currency | J2: KRW | L2: 계정과목 | M2: 설명
B3: ※ 자금현황 | G3: 기준일: 2022.12.31 | I3: USD | J3: 1267.3 | L3: 광고매출 | M3: 타법인 매출
B4: 구 분 | C4: 단위 | D4: 전월잔액 | E4: 수 입 | F4: 지 출 | G4: 기준일 기준 잔액 | I4: SGD | J4: 943.11 | L4: 급여 | M4: 직원 급여
B5: 신한 #672 | C5: KRW | D5: 100640086 | E5: =sumif(B22:B129,B5,E22:E129) -> 12619203 | F5: =sumif(B22:B172,B5,F22:F172) -> 56596015 | G5: =D5+E5-F5 -> 56663274 | L5: 미수금 | M5: 돌려 받을 예정인 금액 (ex. 부가세 환급금)
B6: 신한 #543 | C6: USD | D6: 0 | E6: =sumif(B22:B131,B6,E22:E131) -> 2.31 | F6: =sumif(B22:B172,B6,F22:F172) -> 0 | G6: =D6+E6-F6 -> 2.31 | L6: 보증금 | M6: 보증금 (사무실 임대, 장비 리스 등)
B7: 하나 #304 | C7: KRW | D7: 27431734 | E7: =sumif(B22:B131,B7,E22:E131) -> 130078647 | F7: =sumif(B22:B172,B7,F22:F172) -> 72241082 | G7: =D7+E7-F7 -> 85269299 | L7: 보통예금 | M7: 예금간 이체
B8: 하나 #138 | C8: USD | D8: 0 | E8: =sumif(B22:B131,B8,E22:E131) -> 100000.02 | F8: =sumif(B22:B172,B8,F22:F172) -> 100000 | G8: =D8+E8-F8 -> 0.02 | L8: 복리후생비 | M8: 회식, 식대
B9: WISE USD | C9: USD | D9: 32821.56 | E9: =sumif(B22:B172,B9,E22:E129) -> 115721.12 | F9: =sumif(B22:B172,B9,F22:F172) -> 118357.96 | G9: =D9+E9-F9 -> 30184.72 | L9: 비품 | M9: 가구, 가전등 개당 단가 150만원이 넘는 용품
B10: WISE SGD | C10: SGD | D10: 0 | E10: =sumif(B22:B129,B10,E22:E172) -> 0 | F10: =sumif(B22:B172,B10,F22:F172) -> 0 | G10: =D10+E10-F10 -> 0 | L10: 사무용품비 | M10: 비품, 소모품비를 제외한 업무용 사무용품 구입
B11: WISE KRW | C11: KRW | D11: 0 | E11: =sumif(B22:B131,B11,E22:E131) -> 0 | F11: =sumif(B22:B172,B11,F22:F172) -> 0 | G11: =D11+E11-F11 -> 0 | L11: 서비스용역매출 | M11: 싱가폴 -> 한국 지사 송금
B12: OCBC USD | C12: USD | D12: 7121.24 | E12: =sumif(B22:B131,B12,E22:E131) -> 0 | F12: =sumif(B22:B171,B12,F22:F171) -> 0 | G12: =D12+E12-F12 -> 7121.24 | L12: 세금과공과 | M12: 세금 납부시
B13: OCBC SGD | C13: SGD | D13: 905 | E13: =sumif(B22:B131,B13,E22:E131) -> 0 | F13: =sumif(B22:B171,B13,F22:F171) -> 25 | G13: =D13+E13-F13 -> 880 | L13: 소모품비 | M13: 비품(150만원)으로 잡기에는 금액이 작은 비품
B15: KRW 합 계 | D15: =D5+D7+D11 -> 128071820 | E15: =E5+E7+E11 -> 142697850 | F15: =F5+F7+F11 -> 128837097 | G15: =G5+G11+G7 -> 141932573 | H15: =G15 -> 141932573 | L15: 여비교통비 | M15: 출장, 대중교통, 대리운전
B16: USD 합 계 | D16: =D6+D8+D9+D12 -> 39942.8 | E16: =E6+E8+E9+E12 -> 215723.45 | F16: =F6+F8+F9+F12 -> 218357.96 | G16: =G9+G6+G8+G12 -> 37308.29 | H16: =rounddown(G16*$J$3,0) -> 47280795 | L16: 용역비 | M16: 외주용역비
B17: SGD 합 계 | D17: =D10+D13 -> 905 | E17: =E10+E13 -> 0 | F17: =F10+F13 -> 25 | G17: =G10+G13 -> 880 | H17: =rounddown(G17*$J$4,0) -> 829936 | L17: 접대비 | M17: 외부 미팅
H18: =SUM(H15:H17) -> 190043304 | L18: 지급수수료 | M18: sms 수수료, 송금 수수료, 일반적으로 발생되는 모든 비용
L19: 이자수익 | M19: 은행이자
B20: ※ 세부내역 | L20: 통신비 | M20: 등기, 퀵 사용비
B21: 구 분 | C21: 날 짜 | D21: 은 행 적 요 | E21: 수입 | F21: 지출 | G21: 상세메모 | H21: 계정과목
B22: 신한 #672 | C22: 2022.12.01 | D22: 쇼파 배송비 | E22: 0 | F22: 225500 | G22: 언주 신규 사무실 쇼파 배송료 | H22: 지급수수료
B23: 신한 #672 | C23: 2022.12.05 | D23: Jay 축하금 | E23: 0 | F23: 300500 | G23: 황정원 본인결혼 축하금 | H23: 복리후생비
B24: 신한 #672 | C24: 2022.12.06 | D24: 게임기획외주 | E24: 0 | F24: 2901500 | G24: 게임기획프리랜스비용 (김용애) | H24: 용역비
B25: 신한 #672 | C25: 2022.12.06 | D25: 진 개인비용 | E25: 0 | F25: 23000 | G25: 강진석 11월 개인비용 정산 | H25: 지급수수료
B26: 신한 #672 | C26: 2022.12.06 | D26: 찰스 개인비용 | E26: 0 | F26: 152474 | G26: 권우철 11월 개인비용 정산 | H26: 지급수수료
B27: 신한 #672 | C27: 2022.12.07 | D27: 소득세 | E27: 0 | F27: 4229330 | G27: 11월 소득세 | H27: 세금과공과
B28: 신한 #672 | C28: 2022.12.07 | D28: 사업소득세 | E28: 0 | F28: 90000 | G28: 11월 사업소득세 | H28: 세금과공과
B29: 신한 #672 | C29: 2022.12.07 | D29: 주민세 | E29: 0 | F29: 431860 | G29: 11월주민세 | H29: 세금과공과
B30: 신한 #672 | C30: 2022.12.07 | D30: 11월법률자문료 | E30: 0 | F30: 3025000 | G30: 11월 법률자문료 | H30: 지급수수료
B31: 신한 #672 | C31: 2022.12.07 | D31: 패스트파이브 | E31: 12600000 | F31: 0 | G31: 보증금 환급 | H31: 보증금
B32: 신한 #672 | C32: 2022.12.12 | D32: 의보 | E32: 0 | F32: 5371520 | G32: 건강보험료 | H32: 세금과공과
B33: 신한 #672 | C33: 2022.12.12 | D33: 보험료 | E33: 0 | F33: 1298340 | G33: 고용보험료 | H33: 세금과공과
B34: 신한 #672 | C34: 2022.12.12 | D34: 연금 | E34: 0 | F34: 5544600 | G34: 국민연금 | H34: 세금과공과 | J34: 56663274
B35: 신한 #672 | C35: 2022.12.12 | D35: 보험료 | E35: 0 | F35: 481160 | G35: 산재보험료 | H35: 세금과공과 | J35: 0
B36: 신한 #672 | C36: 2022.12.12 | D36: 서비스 | E36: 0 | F36: 440000 | G36: 세콤 이용료 | H36: 지급수수료 | J36: 85269299
B37: OCBC SGD | C37: 2022.12.05 | D37: Bank monthly fee | E37: 0 | F37: 10 | G37: Bank monthly fee | H37: 지급수수료 | J37: 100000
B38: WISE USD | C38: 2022.12.01 | D38: Milestone Business Group | E38: 0 | F38: 9936.39 | G38: Chris 12월급여 | H38: 급여 | J38: 30184.72
B39: WISE USD | C39: 2022.12.02 | D39: Google Cloud 84l94z | E39: 0 | F39: 492.46 | G39: Google Cloud 사용료 | H39: 지급수수료 | J39: 0
B40: WISE USD | C40: 2022.12.04 | D40: Name-Cheap.com* F7m0xg | E40: 0 | F40: 64.98 | G40: 도메인 사용료 | H40: 지급수수료 | J40: 0
B41: WISE USD | C41: 2022.12.05 | D41: Google Cloud Wczw3l | E41: 0 | F41: 744.71 | G41: Google Cloud 사용료 | H41: 지급수수료 | J41: 7121.24
B42: WISE USD | C42: 2022.12.07 | D42: PRESTO INVESTMENT (BVI) LTD. | E42: 995.86 | F42: 0 | G42: LINK 코인 환전 (BITFRONT > Presto > WISE) | H42: 서비스용역매출 | J42: 880
B43: WISE USD | C43: 2022.12.08 | D43: PRESTO INVESTMENT (BVI) LTD. | E43: 114725.26 | F43: 0 | G43: LINK 코인 환전 (BITFRONT > Presto > WISE) | H43: 서비스용역매출
B44: WISE USD | C44: 2022.12.09 | D44: Google*Cloud F9r3q5 | E44: 0 | F44: 743.93 | G44: Google Cloud 사용료 | H44: 지급수수료
B45: WISE USD | C45: 2022.12.14 | D45: EBOS Advisory Pte Ltd | E45: 0 | F45: 74.62 | G45: E-certificate of incorporation 발급비용 | H45: 지급수수료
B46: =B9 -> WISE USD | C46: 2022.12.14 | D46: Zero X And Korea Inc. | E46: 0 | F46: 100014.39 | G46: 싱가폴 -> 한국지사 송금 | H46: 서비스용역매출
B47: =B9 -> WISE USD | C47: 2022.12.14 | D47: Postmarkapp.com | E47: 0 | F47: 10 | G47: emailing service | H47: 지급수수료
B48: =B8 -> 하나 #138 | C48: 2022.12.15 | D48: ZERO X AND PTE. LTD | E48: 100000 | F48: 0 | G48: 싱가폴 -> 한국지사 송금 | H48: 보통예금
B49: =B5 -> 신한 #672 | C49: 2022.12.15 | D49: BZ뱅크 | E49: 0 | F49: 2921255 | G49: 메가존 - 연간 이용료 | H49: 지급수수료
B50: =B5 -> 신한 #672 | C50: 2022.12.17 | D50: 이자 | E50: 19203 | F50: 0 | G50: 09.17~12.16 은행이자 | H50: 이자수익
B51: =B7 -> 하나 #304 | C51: 2022.12.16 | D51: 주식회사제로엑스앤드 | E51: 130068000 | F51: 0 | G51: 달러 환전 | H51: 보통예금
B52: =B7 -> 하나 #304 | C52: 2022.12.17 | D52: 예금이자 | E52: 10647 | F52: 0 | G52: 예금이자 | H52: 이자수익
B53: =B9 -> WISE USD | C53: 2022.12.15 | D53: EBOS Advisory Pte Ltd | E53: 0 | F53: 3980.82 | G53: 투자 계약서 준비 및 싱가포르 정부 신고 진행비 | H53: 지급수수료
B54: =B5 -> 신한 #672 | C54: 2022.12.22 | D54: 사무실인테리어 | E54: 0 | F54: 23980500 | G54: 사무실 인테리어 비용 | H54: 지급수수료
B55: =B9 -> WISE USD | C55: 2022.12.21 | D55: EBOS Advisory Pte Ltd | E55: 0 | F55: 2295.66 | G55: 2022.11~2023.01 Nominee Director fee + Cloud Accounting package | H55: 지급수수료
B56: =B5 -> 신한 #672 | C56: 2022.12.26 | D56: 노무법인청안 | E56: 0 | F56: 110000 | G56: 노무 컨설팅 비용 | H56: 지급수수료
B57: =B5 -> 신한 #672 | C57: 2022.12.26 | D57: 삼덕회계법인 | E57: 0 | F57: 330000 | G57: 대리 기장 비용 | H57: 지급수수료
B58: =B5 -> 신한 #672 | C58: 2022.12.26 | D58: 코웨이렌탈12 | E58: 0 | F58: 1240 | G58: 공기청정기 사용료 | H58: 지급수수료
B59: =B5 -> 신한 #672 | C59: 2022.12.26 | D59: 코웨이렌탈12 | E59: 0 | F59: 1240 | G59: 공기청정기 사용료 | H59: 지급수수료
B60: =B5 -> 신한 #672 | C60: 2022.12.26 | D60: 코웨이렌탈12 | E60: 0 | F60: 1540 | G60: 정수기 사용료 | H60: 지급수수료
B61: =B5 -> 신한 #672 | C61: 2022.12.26 | D61: 현대카드(주) | E61: 0 | F61: 4658456 | G61: 현대카드 사용료 | H61: 지급수수료
B62: =B5 -> 신한 #672 | C62: 2022.12.30 | D62: 안양신도판매 | E62: 0 | F62: 77000 | G62: 복합기 사용료 | H62: 지급수수료
B63: =B7 -> 하나 #304 | C63: 2022.12.26 | D63: 하나카드 | E63: 0 | F63: 11558274 | G63: 하나카드 사용료 | H63: 지급수수료
B64: =B7 -> 하나 #304 | C64: 2022.12.23 | D64: HNB_대량이체_KO | E64: 0 | F64: 60682808 | G64: 12월 급여 | H64: 급여
B65: =B13 -> OCBC SGD | C65: 2022.12.31 | D65: Service charge | E65: 0 | F65: 15 | G65: Service charge | H65: 지급수수료
B66: =B6 -> 신한 #543 | C66: 2022.12.17 | D66: 이자원가 | E66: 2.31 | F66: 0 | G66: 이자 | H66: 이자수익
B67: =B8 -> 하나 #138 | C67: 2022.12.17 | D67: 이자원가 | E67: 0.02 | F67: 0 | G67: 이자 | H67: 이자수익
B68: =B8 -> 하나 #138 | C68: 2022.12.16 | D68: 환전 | E68: 0 | F68: 100000 | G68: 환전 | H68: 보통예금

Sheet 23.01월
B1: 자 금 일 보
I2: Currency | J2: KRW | L2: 계정과목 | M2: 설명
B3: ※ 자금현황 | G3: 기준일: 2023.01.31 | I3: USD | J3: 1228.7 | L3: 광고매출 | M3: 타법인 매출
B4: 구 분 | C4: 단위 | D4: 전월잔액 | E4: 수 입 | F4: 지 출 | G4: 기준일 기준 잔액 | I4: SGD | J4: 934.76 | L4: 급여 | M4: 직원 급여
B5: 신한 #672 | C5: KRW | D5: 56663274 | E5: =sumif(B22:B129,B5,E22:E129) -> 80000000 | F5: =sumif(B22:B172,B5,F22:F172) -> 107409230 | G5: =D5+E5-F5 -> 29254044 | L5: 미수금 | M5: 돌려 받을 예정인 금액 (ex. 부가세 환급금)
B6: 신한 #543 | C6: USD | D6: 2.31 | E6: =sumif(B22:B131,B6,E22:E131) -> 0 | F6: =sumif(B22:B172,B6,F22:F172) -> 0 | G6: =D6+E6-F6 -> 2.31 | L6: 보증금 | M6: 보증금 (사무실 임대, 장비 리스 등)
B7: 하나 #304 | C7: KRW | D7: 85269299 | E7: =sumif(B22:B131,B7,E22:E131) -> 0 | F7: =sumif(B22:B172,B7,F22:F172) -> 82987474 | G7: =D7+E7-F7 -> 2281825 | L7: 보통예금 | M7: 예금간 이체
B8: 하나 #138 | C8: USD | D8: 0.02 | E8: =sumif(B22:B131,B8,E22:E131) -> 0 | F8: =sumif(B22:B172,B8,F22:F172) -> 0 | G8: =D8+E8-F8 -> 0.02 | L8: 복리후생비 | M8: 회식, 식대
B9: WISE USD | C9: USD | D9: 30184.72 | E9: =sumif(B22:B172,B9,E22:E129) -> 134788.82 | F9: =sumif(B22:B172,B9,F22:F172) -> 17800.51 | G9: =D9+E9-F9 -> 147173.03 | L9: 비품 | M9: 가구, 가전등 개당 단가 150만원이 넘는 용품
B10: WISE SGD | C10: SGD | D10: 0 | E10: =sumif(B22:B129,B10,E22:E172) -> 0 | F10: =sumif(B22:B172,B10,F22:F172) -> 0 | G10: =sumif(C22:C172,C10,G22:G172) -> 0 | L10: 사무용품비 | M10: 비품, 소모품비를 제외한 업무용 사무용품 구입
B11: WISE KRW | C11: KRW | D11: 0 | E11: =sumif(B22:B131,B11,E22:E131) -> 0 | F11: =sumif(B22:B172,B11,F22:F172) -> 0 | G11: =D11+E11-F11 -> 0 | L11: 서비스용역매출 | M11: 싱가폴 -> 한국 지사 송금
B12: OCBC USD | C12: USD | D12: 7121.24 | E12: =sumif(B22:B131,B12,E22:E131) -> 0 | F12: =sumif(B22:B171,B12,F22:F171) -> 0 | G12: =D12+E12-F12 -> 7121.24 | L12: 세금과공과 | M12: 세금 납부시
B13: OCBC SGD | C13: SGD | D13: 880 | E13: =sumif(B22:B131,B13,E22:E131) -> 0 | F13: =sumif(B22:B171,B13,F22:F171) -> 0 | G13: =D13+E13-F13 -> 880 | L13: 소모품비 | M13: 비품(150만원)으로 잡기에는 금액이 작은 비품
B15: KRW 합 계 | D15: =D5+D7+D11 -> 141932573 | E15: =E5+E7+E11 -> 80000000 | F15: =F5+F7+F11 -> 190396704 | G15: =G5+G11+G7 -> 31535869 | H15: =G15 -> 31535869 | L15: 여비교통비 | M15: 출장, 대중교통, 대리운전
B16: USD 합 계 | D16: =D6+D8+D9+D12 -> 37308.29 | E16: =E6+E8+E9+E12 -> 134788.82 | F16: =F6+F8+F9+F12 -> 17800.51 | G16: =G9+G6+G8+G12 -> 154296.6 | H16: =rounddown(G16*$J$3,0) -> 189584232 | L16: 용역비 | M16: 외주용역비
B17: SGD 합 계 | D17: =D10+D13 -> 880 | E17: =E10+E13 -> 0 | F17: =F10+F13 -> 0 | G17: =G10+G13 -> 880 | H17: =rounddown(G17*$J$4,0) -> 822588 | L17: 접대비 | M17: 외부 미팅
H18: =SUM(H15:H17) -> 221942689 | I18: =SUM(I15:I17) -> 0 | L18: 지급수수료 | M18: sms 수수료, 송금 수수료, 일반적으로 발생되는 모든 비용
L19: 이자수익 | M19: 은행이자
B20: ※ 세부내역 | L20: 통신비 | M20: 등기, 퀵 사용비
B21: 구 분 | C21: 날 짜 | D21: 은 행 적 요 | E21: 수입 | F21: 지출 | G21: 상세메모 | H21: 계정과목 | L21: 마케팅비 | M21: PR 기사등 마케팅 비용
B22: =B5 -> 신한 #672 | C22: 2023.01.02 | D22: 신규입사장비 | E22: 0 | F22: 5489500 | G22: 맥플러스 신규입사자 장비 구매 | H22: 비품
B23: =B9 -> WISE USD | C23: 2023.01.02 | D23: Google Cloud Bsrtnl | E23: 0 | F23: 14.17 | G23: Google Cloud 사용료 | H23: 지급수수료
B24: =B9 -> WISE USD | C24: 2023.01.02 | D24: Milestone Business Group, LLC. | E24: 0 | F24: 10423.07 | G24: Christ 급여 | H24: 급여
B25: =B5 -> 신한 #672 | C25: 2023.01.04 | D25: 12월 주민세 | E25: 0 | F25: 422860 | G25: 12월 주민세 납부 | H25: 세금과공과
B26: =B5 -> 신한 #672 | C26: 2023.01.04 | D26: 12월 소득세 | E26: 0 | F26: 4229330 | G26: 12월 소득세 납부 | H26: 세금과공과
B27: =B5 -> 신한 #672 | C27: 2023.01.04 | D27: 12월법률자문료 | E27: 0 | F27: 825000 | G27: 비앤케이 12월 법률자문료 | H27: 지급수수료 | L27: 대여금 | M27: 싱가폴 -> 한국 지사 송금
B28: =B5 -> 신한 #672 | C28: 2023.01.04 | D28: 12월언주사무실 | E28: 0 | F28: 5913330 | G28: 12월 그림바우빌딩 임대료,관리비,전기료 | H28: 지급수수료
B29: =B5 -> 신한 #672 | C29: 2023.01.07 | D29: 2212국민건강 | E29: 0 | F29: 5371520 | G29: 12월 국민건강료 | H29: 세금과공과
B30: =B5 -> 신한 #672 | C30: 2023.01.07 | D30: 2212국민연금 | E30: 0 | F30: 5544600 | G30: 12월 국민연금료 | H30: 세금과공과
B31: =B5 -> 신한 #672 | C31: 2023.01.07 | D31: 2212고용보험 | E31: 0 | F31: 1272420 | G31: 12월 고용보험료 | H31: 세금과공과
B32: =B5 -> 신한 #672 | C32: 2023.01.07 | D32: 2212산재보험 | E32: 0 | F32: 471550 | G32: 12월 산재보험료 | H32: 세금과공과
B33: =B5 -> 신한 #672 | C33: 2023.01.10 | D33: Gon-개인비용 | E33: 0 | F33: 4500 | G33: 12월 고니 개인비용 정산 | H33: 지급수수료
B34: =B9 -> WISE USD | C34: 2023.01.11 | D34: Milestone Business Group, LLC. | E34: 0 | F34: 660.39 | G34: 12월 Chris 개인비용 정산 | H34: 지급수수료
B35: =B5 -> 신한 #672 | C35: 2023.01.11 | D35: 서울시세입금 | E35: 0 | F35: 64370 | G35: 미납부 세금 | H35: 세금과공과
B36: =B5 -> 신한 #672 | C36: 2023.01.11 | D36: 메가존소프트 | E36: 0 | F36: 5289865 | G36: 메가존 구글 사용료 | H36: 지급수수료
B37: =B9 -> WISE USD | C37: 2023.01.14 | D37: Postmarkapp.com | E37: 0 | F37: 10 | G37: 개발용 서비스 이용료 | H37: 지급수수료
B38: =B5 -> 신한 #672 | C38: 2023.01.18 | D38: 웰리더PR비용 | E38: 0 | F38: 1208300 | G38: 웰리더 하바 파트너쉽 배포 (PR수수료) | H38: 마케팅비
B39: =B9 -> WISE USD | C39: 2023.01.18 | D39: JUHONG LEE | E39: 0 | F39: 4303.29 | G39: 베트남 법인 청산 비용 | H39: 지급수수료
B40: =B9 -> WISE USD | C40: 2023.01.18 | D40: PRESTO INVESTMENT (BVI) LTD. | E40: 134788.82 | F40: 0 | G40: LN 매도 | H40: 보통예금
B41: =B9 -> WISE USD | C41: 2023.01.19 | D41: Name-Cheap.com * Xfjuxi | E41: 0 | F41: 38.4 | G41: 개발용 서비스 사용료 | H41: 지급수수료
B42: =B5 -> 신한 #672 | C42: 2023.01.20 | D42: 주식회사제로엑스앤드 | E42: 80000000 | F42: 0 | G42: 하나은행 에서 송금 | H42: 보통예금
B43: =B5 -> 신한 #672 | C43: 2023.01.20 | D43: 베트남영사인증 | E43: 0 | F43: 476800 | G43: 베트남 영사인증 대행 서비스 비 | H43: 지급수수료
B44: =B5 -> 신한 #672 | C44: 2023.01.25 | D44: 세콤 | E44: 0 | F44: 110000 | G44: 세콤 사용비 | H44: 지급수수료
B45: =B7 -> 하나 #304 | C45: 2023.01.20 | D45: 주식회사제로엑스앤드코리아 | E45: 0 | F45: 80000500 | G45: 신한계좌로 송금 | H45: 보통예금
B46: =B7 -> 하나 #304 | C46: 2023.01.25 | D46: 하나카드 | E46: 0 | F46: 2986974 | G46: 하나카드 사용료 | H46: 지급수수료
B47: =B9 -> WISE USD | C47: 2023.01.20 | D47: EBOS SG PTE LTD | E47: 0 | F47: 1209.69 | G47: Cloud accounting package | H47: 지급수수료
B48: =B9 -> WISE USD | C48: 2023.01.20 | D48: EBOS Edvisory Pte Ltd | E48: 0 | F48: 1141.5 | G48: Nominee Director Fee | H48: 지급수수료
B49: =B5 -> 신한 #672 | C49: 2023.01.25 | D49: 전준영 | E49: 0 | F49: 5736068 | G49: 2023.01급여 | H49: 급여
B50: =B5 -> 신한 #672 | C50: 2023.01.25 | D50: 김석준 | E50: 0 | F50: 5436478 | G50: 2023.01급여 | H50: 급여
B51: =B5 -> 신한 #672 | C51: 2023.01.25 | D51: 최고은 | E51: 0 | F51: 5436478 | G51: 2023.01급여 | H51: 급여
B52: =B5 -> 신한 #672 | C52: 2023.01.25 | D52: 강진석 | E52: 0 | F52: 5673958 | G52: 2023.01급여 | H52: 급여
B53: =B5 -> 신한 #672 | C53: 2023.01.25 | D53: 고유빈 | E53: 0 | F53: 3057815 | G53: 2023.01급여 | H53: 급여
B54: =B5 -> 신한 #672 | C54: 2023.01.25 | D54: 이태호 | E54: 0 | F54: 4934670 | G54: 2023.01급여 | H54: 급여
B55: =B5 -> 신한 #672 | C55: 2023.01.25 | D55: 최지현 | E55: 0 | F55: 6426014 | G55: 2023.01급여 | H55: 급여
B56: =B5 -> 신한 #672 | C56: 2023.01.25 | D56: 황정원 | E56: 0 | F56: 4551677 | G56: 2023.01급여 | H56: 급여
B57: =B5 -> 신한 #672 | C57: 2023.01.25 | D57: 권우철 | E57: 0 | F57: 4571980 | G57: 2023.01급여 | H57: 급여
B58: =B5 -> 신한 #672 | C58: 2023.01.25 | D58: 이이슬 | E58: 0 | F58: 4235850 | G58: 2023.01급여 | H58: 급여
B59: =B5 -> 신한 #672 | C59: 2023.01.25 | D59: 정향진 | E59: 0 | F59: 6256740 | G59: 2023.01급여 | H59: 급여
B60: =B5 -> 신한 #672 | C60: 2023.01.25 | D60: 류성탁 | E60: 0 | F60: 4505390 | G60: 2023.01급여 | H60: 급여
B61: =B5 -> 신한 #672 | C61: 2023.01.25 | D61: Lee Elisha | E61: 0 | F61: 6504490 | G61: 2023.01급여 | H61: 급여
B62: =B5 -> 신한 #672 | C62: 2023.01.25 | D62: 노무법인청안 | E62: 0 | F62: 110000 | G62: 노무컨설팅 비용 | H62: 지급수수료
B63: =B5 -> 신한 #672 | C63: 2023.01.25 | D63: 삼덕회계법인 | E63: 0 | F63: 330000 | G63: 대리기장 수수료 | H63: 지급수수료
B64: =B5 -> 신한 #672 | C64: 2023.01.25 | D64: 코웨이렌탈01 | E64: 0 | F64: 37430 | G64: 정수기, 비데 렌탈비 | H64: 지급수수료
B65: =B5 -> 신한 #672 | C65: 2023.01.25 | D65: 코웨이렌탈01 | E65: 0 | F65: 49700 | G65: 정수기, 비데 렌탈비 | H65: 지급수수료
B66: =B5 -> 신한 #672 | C66: 2023.01.25 | D66: 코웨이렌탈01 | E66: 0 | F66: 11970 | G66: 정수기, 비데 렌탈비 | H66: 지급수수료
B67: =B5 -> 신한 #672 | C67: 2023.01.25 | D67: 코웨이렌탈01 | E67: 0 | F67: 37430 | G67: 정수기, 비데 렌탈비 | H67: 지급수수료
B68: =B5 -> 신한 #672 | C68: 2023.01.25 | D68: 코웨이렌탈01 | E68: 0 | F68: 11970 | G68: 정수기, 비데 렌탈비 | H68: 지급수수료
B69: =B5 -> 신한 #672 | C69: 2023.01.25 | D69: KT0540091101 | E69: 0 | F69: 110770 | G69: KT인터넷, 전화 사용료 | H69: 지급수수료
B70: =B5 -> 신한 #672 | C70: 2023.01.25 | D70: 현대카드(주) | E70: 0 | F70: 2590407 | G70: 현대 카드 사용료 | H70: 지급수수료
B71: =B5 -> 신한 #672 | C71: 2023.01.25 | D71: 바디프랜드1 | E71: 0 | F71: 98000 | G71: 안마의자 렌탈료 | H71: 지급수수료

Sheet 23.02월
B1: 자 금 일 보
I2: Currency | J2: KRW | L2: 계정과목 | M2: 설명
B3: ※ 자금현황 | G3: 기준일: 2023.02.28 | I3: USD | J3: =IFERROR(__xludf.DUMMYFUNCTION("GOOGLEFINANCE(""USDKRW"")"),1472.7250000000001) -> 1472.725 | L3: 광고매출 | M3: 타법인 매출
B4: 구 분 | C4: 단위 | D4: 전월잔액 | E4: 수 입 | F4: 지 출 | G4: 기준일 기준 잔액 | I4: SGD | J4: =IFERROR(__xludf.DUMMYFUNCTION("GOOGLEFINANCE(""SGDKRW"")"),1143.885) -> 1143.885 | L4: 급여 | M4: 직원 급여
B5: 신한 #672 | C5: KRW | D5: ='23.01월'!G5 -> 29254044 | E5: =sumif(B22:B142,B5,E22:E142) -> 27511820 | F5: =sumif(B22:B185,B5,F22:F185) -> 51478971 | G5: =D5+E5-F5 -> 5286893 | L5: 미수금 | M5: 돌려 받을 예정인 금액 (ex. 부가세 환급금)
B6: 신한 #543 | C6: USD | D6: ='23.01월'!G6 -> 2.31 | E6: =sumif(B22:B144,B6,E22:E144) -> 0 | F6: =sumif(B22:B185,B6,F22:F185) -> 0 | G6: =D6+E6-F6 -> 2.31 | L6: 보증금 | M6: 보증금 (사무실 임대, 장비 리스 등)
B7: 하나 #304 | C7: KRW | D7: ='23.01월'!G7 -> 2281825 | E7: =sumif(B22:B144,B7,E22:E144) -> 148271622 | F7: =sumif(B22:B185,B7,F22:F185) -> 86435272 | G7: =D7+E7-F7 -> 64118175 | L7: 보통예금 | M7: 예금간 이체
B8: 하나 #138 | C8: USD | D8: ='23.01월'!G8 -> 0.02 | E8: =sumif(B22:B144,B8,E22:E144) -> 115426.76 | F8: =sumif(B22:B185,B8,F22:F185) -> 115426 | G8: =D8+E8-F8 -> 0.78 | L8: 복리후생비 | M8: 회식, 식대
B9: WISE USD | C9: USD | D9: ='23.01월'!G9 -> 147173.03 | E9: =sumif(B22:B185,B9,E22:E142) -> 0 | F9: =sumif(B22:B185,B9,F22:F185) -> 138527.06 | G9: =D9+E9-F9 -> 8645.97 | L9: 비품 | M9: 가구, 가전등 개당 단가 150만원이 넘는 용품
B10: WISE SGD | C10: SGD | D10: ='23.01월'!G10 -> 0 | E10: =sumif(B22:B142,B10,E22:E185) -> 0 | F10: =sumif(B22:B185,B10,F22:F185) -> 0 | G10: =D10+E10-F10 -> 0 | L10: 사무용품비 | M10: 비품, 소모품비를 제외한 업무용 사무용품 구입
B11: WISE KRW | C11: KRW | D11: ='23.01월'!G11 -> 0 | E11: =sumif(B22:B144,B11,E22:E144) -> 0 | F11: =sumif(B22:B185,B11,F22:F185) -> 0 | G11: =D11+E11-F11 -> 0 | L11: 서비스용역매출 | M11: 싱가폴 -> 한국 지사 송금
B12: OCBC USD | C12: USD | D12: ='23.01월'!G12 -> 7121.24 | E12: =sumif(B22:B144,B12,E22:E144) -> 0 | F12: =sumif(B22:B184,B12,F22:F184) -> 0 | G12: =D12+E12-F12 -> 7121.24 | L12: 세금과공과 | M12: 세금 납부시
B13: OCBC SGD | C13: SGD | D13: ='23.01월'!G13 -> 880 | E13: =sumif(B22:B144,B13,E22:E144) -> 0 | F13: =sumif(B22:B184,B13,F22:F184) -> 50 | G13: =D13+E13-F13 -> 830 | L13: 소모품비 | M13: 비품(150만원)으로 잡기에는 금액이 작은 비품
L14: 여비교통비 | M14: 출장, 대중교통, 대리운전
B15: KRW 합 계 | D15: =D5+D7+D11 -> 31535869 | E15: =E5+E7+E11 -> 175783442 | F15: =F5+F7+F11 -> 137914243 | G15: =G5+G11+G7 -> 69405068 | H15: =G15 -> 69405068 | L15: 용역비 | M15: 외주용역비
B16: USD 합 계 | D16: =D6+D8+D9+D12 -> 154296.6 | E16: =E6+E8+E9+E12 -> 115426.76 | F16: =F6+F8+F9+F12 -> 253953.06 | G16: =G9+G6+G8+G12 -> 15770.3 | H16: =rounddown(G16*$J$3,0) -> 23225315 | L16: 접대비 | M16: 외부 미팅
B17: SGD 합 계 | D17: =D10+D13 -> 880 | E17: =E10+E13 -> 0 | F17: =F10+F13 -> 50 | G17: =G10+G13 -> 830 | H17: =rounddown(G17*$J$4,0) -> 949424 | L17: 지급수수료 | M17: sms 수수료, 송금 수수료, 일반적으로 발생되는 모든 비용
H18: =SUM(H15:H17) -> 93579807 | I18: =SUM(I15:I17) -> 0 | L18: 이자수익 | M18: 은행이자
L19: 통신비 | M19: 등기, 퀵 사용비
B20: ※ 세부내역
B21: 구 분 | C21: 날 짜 | D21: 은 행 적 요 | E21: 수입 | F21: 지출 | G21: 상세메모 | H21: 계정과목
B22: =B5 -> 신한 #672 | C22: 2023.02.01 | D22: 안양신도판매 | F22: 77000 | G22: 복합기 사용료 지급 | H22: 지급수수료
B23: =B5 -> 신한 #672 | C23: 2023.02.03 | D23: 강남세무서 | E23: 7511820 | G23: 22년 4분기 부가세 환급 | H23: 미수금
B24: =B5 -> 신한 #672 | C24: 2023.02.03 | D24: 법률자문1월 | F24: 825000 | G24: 비앤케이 1월 법률자문료 | H24: 지급수수료
B25: =B5 -> 신한 #672 | C25: 2023.02.03 | D25: 1월임대료 | F25: 6333530 | G25: 1월 그림바우빌딩 임대료,관리비,전기료 | H25: 지급수수료
B26: =B5 -> 신한 #672 | C26: 2023.02.08 | D26: 국세_주식회사 | F26: 4856960 | G26: 근로소득 원천세 지급 | H26: 세금과공과
B27: =B5 -> 신한 #672 | C27: 2023.02.08 | D27: 서울지방제로엑 | F27: 485630 | G27: 근로소득 지방소득세 지급 | H27: 세금과공과
B28: =B5 -> 신한 #672 | C28: 2023.02.10 | D28: 2301국민건강 | F28: 5474480 | G28: 1월 건강보험료 지급 | H28: 세금과공과
B29: =B5 -> 신한 #672 | C29: 2023.02.10 | D29: 2301국민연금 | F29: 6042300 | G29: 1월 연금보험료 지급 | H29: 세금과공과
B30: =B5 -> 신한 #672 | C30: 2023.02.10 | D30: 2301고용보험 | F30: 1272420 | G30: 1월 고용보험료 지급 | H30: 세금과공과
B31: =B5 -> 신한 #672 | C31: 2023.02.10 | D31: 2301산재보험 | F31: 471550 | G31: 1월 산재보험료 지급 | H31: 세금과공과
B32: =B5 -> 신한 #672 | C32: 2023.02.10 | D32: 메가존소프트( | F32: 5541944 | G32: google suite 1월 비용 지급 | H32: 지급수수료
B33: =B5 -> 신한 #672 | C33: 2023.02.10 | D33: 박성준 | F33: 200500 | G33: 넵튠 박성준 본부장 결혼 축의금 지급 | H33: 접대비
B34: =B5 -> 신한 #672 | C34: 2023.02.21 | D34: 세콤 | F34: 110000 | G34: 세콤 비용 지급 | H34: 지급수수료
B35: =B5 -> 신한 #672 | C35: 2023.02.24 | D35: 주식회사 제로엑스앤드코리아 | E35: 20000000 | G35: 계좌간 자금 이체 | H35: 보통예금
B36: =B5 -> 신한 #672 | C36: 2023.02.27 | D36: 코웨이렌탈02 | F36: 37430 | G36: 공청기 | H36: 복리후생비
B37: =B5 -> 신한 #672 | C37: 2023.02.27 | D37: 코웨이렌탈02 | F37: 37430 | G37: 공청기 | H37: 복리후생비
B38: =B5 -> 신한 #672 | C38: 2023.02.27 | D38: 코웨이렌탈02 | F38: 20660 | G38: 비데 | H38: 복리후생비
B39: =B5 -> 신한 #672 | C39: 2023.02.27 | D39: 코웨이렌탈02 | F39: 20660 | G39: 비데 | H39: 복리후생비
B40: =B5 -> 신한 #672 | C40: 2023.02.27 | D40: 코웨이렌탈02 | F40: 50250 | G40: 정수기 | H40: 복리후생비
B41: =B5 -> 신한 #672 | C41: 2023.02.27 | D41: 노무법인청안 | F41: 110000 | G41: 노무 자문료 지급 | H41: 지급수수료
B42: =B5 -> 신한 #672 | C42: 2023.02.27 | D42: 삼덕회계법인 | F42: 330000 | G42: 회계 자문료 지급 | H42: 지급수수료
B43: =B5 -> 신한 #672 | C43: 2023.02.27 | D43: KT0540091102 | F43: 55600 | G43: 인터넷, 전화 요금 지급 | H43: 통신비
B44: =B5 -> 신한 #672 | C44: 2023.02.27 | D44: 현대카드(주) | F44: 2527627 | G44: 법인카드 대금 지급 | H44: 지급수수료
B45: =B5 -> 신한 #672 | C45: 2023.02.27 | D45: 바디프랜드2 | F45: 98000 | G45: 안마의자 | H45: 지급수수료
B46: =B5 -> 신한 #672 | C46: 2023.02.28 | D46: (주)엔시엘오 | F46: 16500000 | G46: 용역대금 선금 지급 | H46: 용역비
B47: =B7 -> 하나 #304 | C47: 2023.02.23 | D47: 주식회사 제로엑스앤드코리아 | E47: 148271622 | G47: 환전 | H47: 보통예금
B48: =B7 -> 하나 #304 | C48: 2023.02.24 | D48: (주)제로엑스앤드코 | F48: 20000500 | G48: 계좌간 자금 이체 | H48: 보통예금
B49: =B7 -> 하나 #304 | C49: 2023.02.24 | D49: 2월 급여 | F49: 56299351 | G49: 2월 직원급여 | H49: 급여
B50: =B7 -> 하나 #304 | C50: 2023.02.24 | D50: 이태호 | F50: 2460020 | G50: 중도퇴사자 소득세 정산 | H50: 급여
B51: =B7 -> 하나 #304 | C51: 2023.02.27 | D51: 하나카드기업 | F51: 7675401 | G51: 하나카드 대금 지급 | H51: 지급수수료
B52: =B8 -> 하나 #138 | C52: 2023.02.03 | D52: ZERO X AND PTE. LTD | E52: 115426.76 | F52: 0 | G52: 싱가폴 -> 한국지사 송금 (11월 용역대금) | H52: 보통예금
B53: =B8 -> 하나 #138 | C53: 2023.02.23 | D53: 주식회사 제로엑스앤드코리아 | F53: 115426 | G53: 환전 | H53: 보통예금
B54: =B9 -> WISE USD | C54: 2022.02.01 | D54: Milestone Business Group | F54: 10422.68 | G54: Chris 2월급여 | H54: 급여
B55: =B9 -> WISE USD | C55: 2022.02.01 | D55: wise | F55: 0.39 | G55: Chris 2월급여 송금 수수료 | H55: 지급수수료
B56: =B9 -> WISE USD | C56: 2022.02.01 | D56: Tran Nguyen Ngoc Tam | F56: 120 | G56: 따미 22.12~23.01 외주 급여 지급 | H56: 급여
B57: =B9 -> WISE USD | C57: 2022.02.01 | D57: wise | F57: 2.42 | G57: 따미 22.12~23.01 외주 급여 지급시 송금수수료 | H57: 지급수수료
B58: =B9 -> WISE USD | C58: 2023.02.02 | D58: Zero X And Korea Inc. | E58: 0 | F58: 115426.76 | G58: 싱가폴 -> 한국지사 송금 (11월 용역대금) | H58: 서비스용역매출
B59: =B9 -> WISE USD | C59: 2023.02.02 | D59: wise | F59: 14.39 | G59: 싱가폴 -> 한국지사 송금 수수료 | H59: 지급수수료
B60: =B9 -> WISE USD | C60: 2023.02.14 | D60: Postmarkapp.com | F60: 10 | G60: 서비스 이용료 지급 | H60: 지급수수료
B61: =B9 -> WISE USD | C61: 2023.02.15 | D61: COO BUILDER COMPANY LIMITED | F61: 4180 | G61: 베트남 법인 청산 변호사 비용 | H61: 지급수수료
B62: =B9 -> WISE USD | C62: 2023.02.15 | D62: WISE | F62: 3.29 | G62: 송금수수료 | H62: 지급수수료
B63: =B9 -> WISE USD | C63: 2023.02.24 | D63: Nguyen Duc Hieu Thao | F63: 7739.23 | G63: 프리랜서 계약비 지급 (184,135,600 VND) | H63: 지급수수료
B64: =B9 -> WISE USD | C64: 2023.02.24 | D64: WISE | F64: 67.91 | G64: 환전&송금수수료 | H64: 지급수수료
B65: =B9 -> WISE USD | C65: 2023.02.26 | D65: Iconscout.com | F65: 155.99 | G65: 서비스 이용료 지급 | H65: 지급수수료
B66: =B9 -> WISE USD | C66: 2023.02.28 | D66: Gitbook Inc. | F66: 384 | G66: 서비스 이용료 지급 | H66: 지급수수료
B67: =B13 -> OCBC SGD | C67: 2023.02.01 | D67: OCBC | F67: 15 | G67: 은행 수수료 | H67: 지급수수료
B68: =B13 -> OCBC SGD | C68: 2023.02.03 | D68: OCBC | F68: 20 | G68: 은행 수수료 | H68: 지급수수료
B69: =B13 -> OCBC SGD | C69: 2023.02.28 | D69: OCBC | F69: 15 | G69: 은행 수수료 | H69: 지급수수료

Sheet 23.03월
B1: 자 금 일 보
I2: Currency | J2: KRW | L2: 계정과목 | M2: 설명
B3: ※ 자금현황 | G3: 기준일: 2023.03.31 | I3: USD | J3: =IFERROR(__xludf.DUMMYFUNCTION("GOOGLEFINANCE(""USDKRW"")"),1472.7250000000001) -> 1472.725 | L3: 광고매출 | M3: 타법인 매출
B4: 구 분 | C4: 단위 | D4: 전월잔액 | E4: 수 입 | F4: 지 출 | G4: 기준일 기준 잔액 | I4: SGD | J4: =IFERROR(__xludf.DUMMYFUNCTION("GOOGLEFINANCE(""SGDKRW"")"),1143.885) -> 1143.885 | L4: 급여 | M4: 직원 급여
B5: 신한 #672 | C5: KRW | D5: ='23.02월'!G5 -> 5286893 | E5: =sumif(B22:B142,B5,E22:E142) -> 46006686 | F5: =sumif(B22:B185,B5,F22:F185) -> 21719091 | G5: =D5+E5-F5 -> 29574488 | L5: 미수금 | M5: 돌려 받을 예정인 금액 (ex. 부가세 환급금)
B6: 신한 #543 | C6: USD | D6: ='23.02월'!G6 -> 2.31 | E6: =sumif(B22:B144,B6,E22:E144) -> 0 | F6: =sumif(B22:B185,B6,F22:F185) -> 0 | G6: =D6+E6-F6 -> 2.31 | L6: 보증금 | M6: 보증금 (사무실 임대, 장비 리스 등)
B7: 하나 #304 | C7: KRW | D7: ='23.02월'!G7 -> 64118175 | E7: =sumif(B22:B144,B7,E22:E144) -> 115956794 | F7: =sumif(B22:B185,B7,F22:F185) -> 141909628 | G7: =D7+E7-F7 -> 38165341 | L7: 보통예금 | M7: 예금간 이체
B8: 하나 #138 | C8: USD | D8: ='23.02월'!G8 -> 0.78 | E8: =sumif(B22:B144,B8,E22:E144) -> 91350.11 | F8: =sumif(B22:B185,B8,F22:F185) -> 91350 | G8: =D8+E8-F8 -> 0.89 | L8: 복리후생비 | M8: 회식, 식대
B9: WISE USD | C9: USD | D9: ='23.02월'!G9 -> 8645.97 | E9: =sumif(B22:B185,B9,E22:E142) -> 395592.5 | F9: =sumif(B22:B185,B9,F22:F185) -> 102168.77 | G9: =D9+E9-F9 -> 302069.7 | L9: 비품 | M9: 가구, 가전등 개당 단가 150만원이 넘는 용품
B10: WISE SGD | C10: SGD | D10: ='23.02월'!G10 -> 0 | E10: =sumif(B22:B142,B10,E22:E185) -> 500 | F10: =sumif(B22:B185,B10,F22:F185) -> 300 | G10: =D10+E10-F10 -> 200 | L10: 사무용품비 | M10: 비품, 소모품비를 제외한 업무용 사무용품 구입
B11: WISE KRW | C11: KRW | D11: ='23.02월'!G11 -> 0 | E11: =sumif(B22:B144,B11,E22:E144) -> 0 | F11: =sumif(B22:B185,B11,F22:F185) -> 0 | G11: =D11+E11-F11 -> 0 | L11: 서비스용역매출 | M11: 매출
B12: OCBC USD | C12: USD | D12: ='23.02월'!G12 -> 7121.24 | E12: =sumif(B22:B144,B12,E22:E144) -> 0 | F12: =sumif(B22:B184,B12,F22:F184) -> 0 | G12: =D12+E12-F12 -> 7121.24 | L12: 세금과공과 | M12: 세금 납부시
B13: OCBC SGD | C13: SGD | D13: ='23.02월'!G13 -> 830 | E13: =sumif(B22:B144,B13,E22:E144) -> 0 | F13: =sumif(B22:B184,B13,F22:F184) -> 25 | G13: =D13+E13-F13 -> 805 | L13: 소모품비 | M13: 비품(150만원)으로 잡기에는 금액이 작은 비품
L14: 여비교통비 | M14: 출장, 대중교통, 대리운전
B15: KRW 합 계 | D15: =D5+D7+D11 -> 69405068 | E15: =E5+E7+E11 -> 161963480 | F15: =F5+F7+F11 -> 163628719 | G15: =G5+G11+G7 -> 67739829 | H15: =G15 -> 67739829 | L15: 용역비 | M15: 외주용역비
B16: USD 합 계 | D16: =D6+D8+D9+D12 -> 15770.3 | E16: =E6+E8+E9+E12 -> 486942.61 | F16: =F6+F8+F9+F12 -> 193518.77 | G16: =G9+G6+G8+G12 -> 309194.14 | H16: =rounddown(G16*$J$3,0) -> 455357939 | L16: 접대비 | M16: 외부 미팅
B17: SGD 합 계 | D17: =D10+D13 -> 830 | E17: =E10+E13 -> 500 | F17: =F10+F13 -> 325 | G17: =G10+G13 -> 1005 | H17: =rounddown(G17*$J$4,0) -> 1149604 | L17: 지급수수료 | M17: sms 수수료, 송금 수수료, 일반적으로 발생되는 모든 비용
H18: =SUM(H15:H17) -> 524247372 | I18: =SUM(I15:I17) -> 0 | L18: 이자수익 | M18: 은행이자
L19: 통신비 | M19: 등기, 퀵 사용비
B20: ※ 세부내역 | L20: 마케팅비 | M20: PR 기사등 마케팅 비용
B21: 구 분 | C21: 날 짜 | D21: 은 행 적 요 | E21: 수입 | F21: 지출 | G21: 상세메모 | H21: 계정과목 | L21: 대여금 | M21: 싱가폴 -> 한국 지사 송금
B22: =B5 -> 신한 #672 | C22: 2023.03.02 | D22: 안양신도판매 | F22: 77000 | G22: 복합기 사용료 지급 | H22: 지급수수료
B23: =B5 -> 신한 #672 | C23: 2023.03.03 | D23: 법률자문2월 | F23: 825000 | G23: 비앤케이 2월 법률자문료 | H23: 지급수수료
B24: =B7 -> 하나 #304 | C24: 2023.03.03 | D24: 2월임대료 | F24: =6419820+500 -> 6420320 | G24: 2월 그림바우빌딩 임대료,관리비,전기료 | H24: 지급수수료
B25: =B7 -> 하나 #304 | C25: 2023.03.08 | D25: (주)제로엑스앤드코리아 | F25: 15000500 | G25: 계좌간 자금 이체 | H25: 보통예금
B26: =B7 -> 하나 #304 | C26: 2023.03.08 | D26: 국고_주식회사 제로 | F26: 7975340 | G26: 2월 근로 소득세 | H26: 세금과공과
B27: =B7 -> 하나 #304 | C27: 2023.03.08 | D27: 서울지방제로엑 | F27: 797840 | G27: 2월 근로 지방 소득세 | H27: 세금과공과
B28: =B5 -> 신한 #672 | C28: 2023.03.08 | D28: (주)제로엑스앤드코리아 | E28: 15000000 | G28: 계좌간 자금 이체 | H28: 보통예금
B29: =B7 -> 하나 #304 | C29: 2023.03.08 | D29: 우윤성(디자인멘토) | F29: 330500 | G29: 명함 제작 비용 지급 (3명) | H29: 소모품비
B30: =B7 -> 하나 #304 | C30: 2023.03.08 | D30: 메가존소프트(주) | F30: =4787236+500 -> 4787736 | G30: google suite 2월 비용 지급 | H30: 지급수수료
B31: =B5 -> 신한 #672 | C31: 2023.03.10 | D31: 2302국민건강 | F31: 6058320 | G31: 2월 건강보험료 지급 | H31: 세금과공과
B32: =B5 -> 신한 #672 | C32: 2023.03.10 | D32: 2302국민연금 | F32: 6042300 | G32: 2월 연금보험료 지급 | H32: 세금과공과
B33: =B5 -> 신한 #672 | C33: 2023.03.10 | D33: 2303고용보험 | F33: 1451020 | G33: 2월 고용보험료 지급 | H33: 세금과공과
B34: =B5 -> 신한 #672 | C34: 2023.03.10 | D34: 2302산재보험 | F34: 580720 | G34: 2월 산재보험료 지급 | H34: 세금과공과
B35: =B7 -> 하나 #304 | C35: 2023.03.16 | D35: ㈜ 웰리더 | F35: 1098300 | G35: PR 기사 수수료 | H35: 마케팅비
B36: =B9 -> WISE USD | C36: 2023.03.16 | D36: PRESTO INVESTMENT (BVI) LTD. | E36: 375519.22 | G36: LN 입금 | H36: 광고매출
B37: =B9 -> WISE USD | C37: 2023.03.14 | D37: Postmarkapp.com | F37: 10 | G37: 서비스 이용료 지급 | H37: 지급수수료
B38: =B9 -> WISE USD | C38: 2023.03.16 | D38: ZERO X AND | F38: =371.84 -> 371.84 | G38: 환전 | H38: 보통예금
B39: =B10 -> WISE SGD | C39: 2023.03.16 | D39: ZERO X AND | E39: 500 | G39: 환전 | H39: 보통예금
B40: =B10 -> WISE SGD | C40: 2023.03.16 | D40: EBOS Advisory Pte Ltd | F40: 300 | G40: 정관변경 수수료 | H40: 지급수수료
B41: =B9 -> WISE USD | C41: 2023.03.16 | D41: Milestone Business Group | F41: 10422.68 | G41: Chris 3월급여 | H41: 급여
B42: =B9 -> WISE USD | C42: 2023.03.16 | D42: wise | F42: 0.39 | G42: Chris 3월급여 송금 수수료 | H42: 지급수수료
B43: =B7 -> 하나 #304 | C43: 2023.03.18 | D43: 하나은행 | E43: 10807 | G43: 예금이자 | H43: 이자수익
B44: =B7 -> 하나 #304 | C44: 2023.03.20 | D44: 전준영 | F44: 500500 | G44: 태국 현지 출장용 경비 지급 | H44: 여비교통비
B45: =B9 -> WISE USD | C45: 2023.03.20 | D45: ZERO X AND PTE. LTD | F45: 91349.47 | G45: 한국법인 운영비 | H45: 대여금
B46: =B9 -> WISE USD | C46: 2023.03.20 | D46: WISE | F46: 14.39 | G46: 송금 수수료 | H46: 지급수수료
B47: =B5 -> 신한 #672 | C47: 2023.03.18 | D47: 신한은행 | E47: 6686 | G47: 예금이자 | H47: 이자수익
B48: =B8 -> 하나 #138 | C48: 2023.03.18 | D48: 하나은행 | E48: 0.64 | G48: 예금이자 | H48: 이자수익
B49: =B8 -> 하나 #138 | C49: 2023.03.21 | D49: ZERO X AND PTE. LTD | E49: 91349.47 | G49: 한국법인 운영비 | H49: 대여금
B50: =B8 -> 하나 #138 | C50: 2023.03.23 | D50: 주식회사 제로엑스앤드코리아 | F50: 91350 | G50: 환전 | H50: 보통예금
B51: =B7 -> 하나 #304 | C51: 2023.03.23 | D51: 주식회사 제로엑스앤드코리아 | E51: 115945987 | G51: 환전 | H51: 보통예금
B52: =B7 -> 하나 #304 | C52: 2023.03.24 | D52: 주식회사 제로엑스앤드코리아 | F52: 20000500 | G52: 계좌간 자금 이체 | H52: 보통예금
B53: =B7 -> 하나 #304 | C53: 2023.03.24 | D53: 급여 | F53: 64067302 | G53: 급여 | H53: 급여
B54: =B7 -> 하나 #304 | C54: 2023.03.27 | D54: 하나카드 | F54: 5270110 | G54: 법인카드 대금 지급 | H54: 복리후생비
B55: =B5 -> 신한 #672 | C55: 2023.03.21 | D55: 세콤 | F55: 110000 | G55: 세콤 비용 지급 | H55: 지급수수료
B56: =B5 -> 신한 #672 | C56: 2023.03.24 | D56: 주식회사 제로엑스앤드코리아 | E56: 20000000 | G56: 계좌간 자금 이체 | H56: 보통예금
B57: =B5 -> 신한 #672 | C57: 2023.03.27 | D57: 코웨이렌탈03 | F57: 37430 | G57: 공청기 | H57: 복리후생비
B58: =B5 -> 신한 #672 | C58: 2023.03.27 | D58: 코웨이렌탈03 | F58: 50250 | G58: 공청기 | H58: 복리후생비
B59: =B5 -> 신한 #672 | C59: 2023.03.27 | D59: 코웨이렌탈03 | F59: 20660 | G59: 비데 | H59: 복리후생비
B60: =B5 -> 신한 #672 | C60: 2023.03.27 | D60: 코웨이렌탈03 | F60: 20660 | G60: 비데 | H60: 복리후생비
B61: =B5 -> 신한 #672 | C61: 2023.03.27 | D61: 코웨이렌탈03 | F61: 37430 | G61: 정수기 | H61: 복리후생비
B62: =B5 -> 신한 #672 | C62: 2023.03.27 | D62: 삼덕회계법인 | F62: 330000 | G62: 노무 자문료 지급 | H62: 지급수수료
B63: =B5 -> 신한 #672 | C63: 2023.03.27 | D63: 노무법인청안 | F63: 110000 | G63: 회계 자문료 지급 | H63: 지급수수료
B64: =B5 -> 신한 #672 | C64: 2023.03.27 | D64: KT0540091103 | F64: 55570 | G64: 인터넷, 전화 요금 지급 | H64: 복리후생비
B65: =B5 -> 신한 #672 | C65: 2023.03.27 | D65: 현대카드(주) | F65: 1869231 | G65: 법인카드 대금 지급 | H65: 복리후생비
B66: =B5 -> 신한 #672 | C66: 2023.03.27 | D66: 바디프랜드3 | F66: 98000 | G66: 안마의자 | H66: 복리후생비
B67: =B5 -> 신한 #672 | C67: 2023.03.39 | D67: 주식회사 알엑스메타 | E67: 11000000 | G67: 서울랜드 페스티벌 서비스 기획 및 컨설팅 1차 | H67: 서비스용역매출
B68: =B5 -> 신한 #672 | C68: 2023.03.39 | D68: 안현웅 | F68: 3868500 | G68: 신규 앱서비스 개발 기획 외주 선금 | H68: 용역비
B69: =B7 -> 하나 #304 | C69: 2023.03.31 | D69: 국고_주식회사제로엑스 | F69: 12321500 | G69: 2022년 결산 법인세 지급 | H69: 세금과공과
B70: =B7 -> 하나 #304 | C70: 2023.03.31 | D70: 서울 제로엑스 | F70: 2188680 | G70: 2022년 결산 법인 지방세 지급 | H70: 세금과공과
B71: =B7 -> 하나 #304 | C71: 2023.03.31 | D71: (주)맥플러스 | F71: 1150500 | G71: 맥북 m1 구입 (코빈) | H71: 소모품비
B72: =B9 -> WISE USD | C72: 2023.03.30 | D72: ZENA AD | E72: 20073.28 | G72: 대여금 반환 (USDT로 빌려주고 USD로 받음) | H72: 대여금
B73: =B5 -> 신한 #672 | C73: 2023.03.31 | D73: 안양신도판매 | F73: 77000 | G73: 복합기 사용료 지급 | H73: 지급수수료
B74: =B13 -> OCBC SGD | C74: 2023.03.06 | D74: OCBC | F74: 10 | G74: 은행 수수료 | H74: 지급수수료
B75: =B13 -> OCBC SGD | C75: 2023.03.31 | D75: OCBC | F75: 15 | G75: 은행 수수료 | H75: 지급수수료

Sheet 23.04월
A1: ㄹ | B1: 자 금 일 보
I2: Currency | J2: KRW | L2: 계정과목 | M2: 설명
B3: ※ 자금현황 | G3: 기준일: 2023.04.28 | I3: USD | J3: =IFERROR(__xludf.DUMMYFUNCTION("GOOGLEFINANCE(""USDKRW"")"),1472.7250000000001) -> 1472.725 | L3: 광고매출 | M3: 타법인 매출
B4: 구 분 | C4: 단위 | D4: 전월잔액 | E4: 수 입 | F4: 지 출 | G4: 기준일 기준 잔액 | I4: SGD | J4: =IFERROR(__xludf.DUMMYFUNCTION("GOOGLEFINANCE(""SGDKRW"")"),1143.885) -> 1143.885 | L4: 급여 | M4: 직원 급여
B5: 신한 #672 | C5: KRW | D5: ='23.03월'!G5 -> 29574488 | E5: =sumif(B22:B123,B5,E22:E123) -> 20000000 | F5: =sumif(B22:B166,B5,F22:F166) -> 32872562 | G5: =D5+E5-F5 -> 16701926 | L5: 미수금 | M5: 돌려 받을 예정인 금액 (ex. 부가세 환급금)
B6: 신한 #543 | C6: USD | D6: ='23.03월'!G6 -> 2.31 | E6: =sumif(B22:B125,B6,E22:E125) -> 0 | F6: =sumif(B22:B166,B6,F22:F166) -> 0 | G6: =D6+E6-F6 -> 2.31 | L6: 보증금 | M6: 보증금 (사무실 임대, 장비 리스 등)
B7: 하나 #304 | C7: KRW | D7: ='23.03월'!G7 -> 38165341 | E7: =sumif(B22:B125,B7,E22:E125) -> 130739000 | F7: =sumif(B22:B166,B7,F22:F166) -> 123293445 | G7: =D7+E7-F7 -> 45610896 | L7: 보통예금 | M7: 예금간 이체
B8: 하나 #138 | C8: USD | D8: ='23.03월'!G8 -> 0.89 | E8: =sumif(B22:B125,B8,E22:E125) -> 100000 | F8: =sumif(B22:B166,B8,F22:F166) -> 100000 | G8: =D8+E8-F8 -> 0.89 | L8: 복리후생비 | M8: 회식, 식대
B9: WISE USD | C9: USD | D9: ='23.03월'!G9 -> 302069.7 | E9: =sumif(B22:B166,B9,E22:E123) -> 0 | F9: =sumif(B22:B166,B9,F22:F166) -> 238296.11 | G9: =D9+E9-F9 -> 63773.59 | L9: 비품 | M9: 가구, 가전등 개당 단가 150만원이 넘는 용품
B10: WISE SGD | C10: SGD | D10: ='23.03월'!G10 -> 200 | E10: =sumif(B22:B123,B10,E22:E166) -> 0 | F10: =sumif(B22:B166,B10,F22:F166) -> 0 | G10: =D10+E10-F10 -> 200 | L10: 사무용품비 | M10: 비품, 소모품비를 제외한 업무용 사무용품 구입
B11: WISE KRW | C11: KRW | D11: ='23.03월'!G11 -> 0 | E11: =sumif(B22:B125,B11,E22:E125) -> 0 | F11: =sumif(B22:B166,B11,F22:F166) -> 0 | G11: =D11+E11-F11 -> 0 | L11: 서비스용역매출 | M11: 매출
B12: OCBC USD | C12: USD | D12: ='23.03월'!G12 -> 7121.24 | E12: =sumif(B25:B117,B12,E25:E99) -> 949990.42 | F12: =sumif(B22:B165,B12,F22:F165) -> 22.39 | G12: =D12+E12-F12 -> 957089.27 | L12: 세금과공과 | M12: 세금 납부시
B13: OCBC SGD | C13: SGD | D13: ='23.03월'!G13 -> 805 | E13: =sumif(B22:B125,B13,E22:E125) -> 0 | F13: =sumif(B22:B165,B13,F22:F165) -> 25 | G13: =D13+E13-F13 -> 780 | L13: 소모품비 | M13: 비품(150만원)으로 잡기에는 금액이 작은 비품
L14: 여비교통비 | M14: 출장, 대중교통, 대리운전
B15: KRW 합 계 | D15: =D5+D7+D11 -> 67739829 | E15: =E5+E7+E11 -> 150739000 | F15: =F5+F7+F11 -> 156166007 | G15: =G5+G11+G7 -> 62312822 | H15: =G15 -> 62312822 | L15: 용역비 | M15: 외주용역비
B16: USD 합 계 | D16: =D6+D8+D9+D12 -> 309194.14 | E16: =E6+E8+E9+E12 -> 1049990.4 | F16: =F6+F8+F9+F12 -> 338318.5 | G16: =G9+G6+G8+G12 -> 1020866.1 | H16: =rounddown(G16*$J$3,0) -> 1503454968 | L16: 접대비 | M16: 외부 미팅
B17: SGD 합 계 | D17: =D10+D13 -> 1005 | E17: =E10+E13 -> 0 | F17: =F10+F13 -> 25 | G17: =G10+G13 -> 980 | H17: =rounddown(G17*$J$4,0) -> 1121007 | L17: 지급수수료 | M17: sms 수수료, 송금 수수료, 일반적으로 발생되는 모든 비용
H18: =SUM(H15:H17) -> 1566888797 | I18: =SUM(I15:I17) -> 0 | L18: 이자수익 | M18: 은행이자
L19: 통신비 | M19: 등기, 퀵 사용비
B20: ※ 세부내역 | L20: 마케팅비 | M20: PR 기사등 마케팅 비용
B21: 구 분 | C21: 날 짜 | D21: 은 행 적 요 | E21: 수입 | F21: 지출 | G21: 상세메모 | H21: 계정과목 | L21: 대여금 | M21: 싱가폴 -> 한국 지사 송금
B22: =B5 -> 신한 #672 | C22: 2023.04.04 | D22: 법률자문3월 | F22: 825000 | G22: 비앤케이 2월 법률자문료 | H22: 지급수수료
B23: =B7 -> 하나 #304 | C23: 2023.04.03 | D23: 3월임대료 | F23: =6198060+500 -> 6198560 | G23: 2월 그림바우빌딩 임대료,관리비,전기료 | H23: 지급수수료
B24: =B9 -> WISE USD | C24: 2023.04.01 | D24: zoom | F24: 161.89 | G24: zoom 비용 지급 | H24: 지급수수료
B25: =B9 -> WISE USD | C25: 2023.04.03 | D25: Milestone Business Group | F25: 11657.73 | G25: Chris 4월 급여 | H25: 급여
B26: =B9 -> WISE USD | C26: 2023.04.03 | D26: wise | F26: 0.39 | G26: Chris 4월 급여 송금 수수료 | H26: 지급수수료 | L26: 1020866.1
B27: =B9 -> WISE USD | C27: 2023.04.05 | D27: Sevio FZC | F27: 36720.98 | G27: 게임 도시 마케팅 비용 지급_PlaytoEarn | H27: 마케팅비
B28: =B9 -> WISE USD | C28: 2023.04.05 | D28: Nguyen Duc Hieu Thao | F28: 10014.39 | G28: 게임 도시 마케팅 비용 지급_Hatten Guild | H28: 마케팅비
B29: =B9 -> WISE USD | C29: 2023.04.05 | D29: Momo Tech Company Limited | F29: 10294.39 | G29: 게임 도시 마케팅 비용 지급_ChainPlay | H29: 마케팅비
B30: =B9 -> WISE USD | C30: 2023.04.05 | D30: SecuChart Global | F30: 18014.39 | G30: 게임 도시 마케팅 비용 지급_P2eAll | H30: 마케팅비
B31: =B9 -> WISE USD | C31: 2023.04.05 | D31: Coin68 Limited | F31: 5014.39 | G31: 게임 도시 마케팅 비용 지급_Acient8 | H31: 마케팅비
B32: =B9 -> WISE USD | C32: 2023.04.05 | D32: UAB DappRadar | F32: 36014.39 | G32: 게임 도시 마케팅 비용 지급_DappRader | H32: 마케팅비
B33: =B9 -> WISE USD | C33: 2023.04.05 | D33: Siam commercial bank | F33: 5364.39 | G33: 게임 도시 마케팅 비용 지급_Guildfi | H33: 마케팅비
B34: =B9 -> WISE USD | C34: 2023.04.06 | D34: Telos Labs Pte. Ltd | F34: 5014.39 | G34: 게임 도시 마케팅 비용 지급_Avocado | H34: 마케팅비
B35: =B5 -> 신한 #672 | C35: 2023.04.10 | D35: 2303국민건강 | F35: 5316960 | G35: 2303국민건강 | H35: 세금과공과
B36: =B5 -> 신한 #672 | C36: 2023.04.10 | D36: 2303국민연금 | F36: 5283520 | G36: 2303국민연금 | H36: 세금과공과
B37: =B5 -> 신한 #672 | C37: 2023.04.10 | D37: 2303고용보험 | F37: 1249620 | G37: 2303고용보험 | H37: 세금과공과
B38: =B5 -> 신한 #672 | C38: 2023.04.10 | D38: 2303산재보험 | F38: 463030 | G38: 2303산재보험 | H38: 세금과공과
B39: =B5 -> 신한 #672 | C39: 2023.04.10 | D39: 삼덕회계법인 | F39: 1650000 | G39: 2022년 결산 세무 조정 | H39: 지급수수료
B40: =B7 -> 하나 #304 | C40: 2023.04.10 | D40: 국고_주식회사제로엑스 | F40: 7138660 | G40: 3월 근로 소득세 | H40: 세금과공과
B41: =B7 -> 하나 #304 | C41: 2023.04.10 | D41: 서울지방제로엑스 | F41: 725850 | G41: 3월 근로 지방 소득세 | H41: 세금과공과
B42: =B7 -> 하나 #304 | C42: 2023.04.10 | D42: 국고_주식회사제로엑스 | F42: 120000 | G42: 3월 사업 소득세 | H42: 세금과공과
B43: =B7 -> 하나 #304 | C43: 2023.04.10 | D43: 메가존소프트(주) | F43: 5304867 | G43: google suite 3월 비용 지급 | H43: 지급수수료
B44: =B7 -> 하나 #304 | C44: 2023.04.10 | D44: 김소연(연법무사합동) | F44: 540740 | G44: 임원변경(대표자 포함) 등기 진행 | H44: 지급수수료
B45: =B9 -> WISE USD | C45: 2023.04.17 | D45: ZERO X AND PTE. LTD | F45: 100014.39 | G45: 한국법인 운영비 | H45: 대여금
B46: =B5 -> 신한 #672 | C46: 2023.04.17 | D46: 주식회사 크몽 | F46: 1588720 | G46: 게더 오피스 리모델링 | H46: 지급수수료
B47: =B8 -> 하나 #138 | C47: 2023.04.18 | D47: ZERO X AND PTE. LTD | E47: 100000 | G47: 한국법인 운영비 | H47: 보통예금
B48: =B8 -> 하나 #138 | C48: 2023.04.19 | D48: 주식회사 제로엑스앤드 | F48: 100000 | G48: 환전 | H48: 보통예금
B49: =B7 -> 하나 #304 | C49: 2023.04.19 | D49: 주식회사 제로엑스앤드 | E49: 130739000 | G49: 환전 | H49: 보통예금
B50: =B7 -> 하나 #304 | C50: 2023.04.20 | D50: 안현웅 | F50: 967500 | G50: 신규 앱서비스 개발 기획 외주 잔금 | H50: 용역비
B51: =B7 -> 하나 #304 | C51: 2023.04.20 | D51: 메가존소프트(주) | F51: 131117 | G51: 메가존 구글 계정 추가비용 | H51: 지급수수료
B52: =B7 -> 하나 #304 | C52: 2023.04.20 | D52: (주)컴퓨존 | F52: 3992800 | G52: 업무용 데스크탑 구매 | H52: 사무용품비
B53: =B5 -> 신한 #672 | C53: 2023.04.17 | D53: 권영채(대부도 하이클래스) | F53: 750500 | G53: 워크샵 숙박비 | H53: 복리후생비
B54: =B5 -> 신한 #672 | C54: 2023.04.17 | D54: 권영채(대부도 하이클래스) | F54: 70500 | G54: 워크샵 숙박비 (얼리입실) | H54: 복리후생비
B55: =B9 -> WISE USD | C55: 2023.04.14 | D55: Postmarkapp.com | F55: 10 | G55: 서비스 이용료 지급 | H55: 지급수수료
B56: =B7 -> 하나 #304 | C56: 2023.04.24 | D56: 주식회사 제로엑스앤드코리아 | F56: 20000500 | G56: 계좌간 자금 이체 | H56: 보통예금
B57: =B7 -> 하나 #304 | C57: 2023.04.25 | D57: 하나카드 | F57: 8339054 | G57: 법인카드 대금 지급 | H57: 지급수수료
B58: =B7 -> 하나 #304 | C58: 2023.04.25 | D58: 급여 | F58: 69773297 | G58: 급여 | H58: 급여
B59: =B7 -> 하나 #304 | C59: 2023.04.25 | D59: 권영채(대부도 하이클래스) | F59: 60500 | G59: 워크샵 숯이용 | H59: 복리후생비
B60: =B5 -> 신한 #672 | C60: 2023.04.21 | D60: 세콤(N5905012) | F60: 110000 | G60: 세콤 비용 지급 | H60: 지급수수료
B61: =B5 -> 신한 #672 | C61: 2023.04.24 | D61: 주식회사 제로 | E61: 20000000 | G61: 계좌간 자금 이체 | H61: 보통예금
B62: =B5 -> 신한 #672 | C62: 2023.04.25 | D62: KT0540091104 | F62: 55980 | G62: 인터넷, 전화 요금 지급 | H62: 복리후생비
B63: =B5 -> 신한 #672 | C63: 2023.04.25 | D63: 코웨이렌탈04 | F63: 37430 | G63: 공청기 | H63: 복리후생비
B64: =B5 -> 신한 #672 | C64: 2023.04.25 | D64: 코웨이렌탈04 | F64: 50250 | G64: 정수기 | H64: 복리후생비
B65: =B5 -> 신한 #672 | C65: 2023.04.25 | D65: 코웨이렌탈04 | F65: 37430 | G65: 공청기 | H65: 복리후생비
B66: =B5 -> 신한 #672 | C66: 2023.04.25 | D66: 코웨이렌탈04 | F66: 20660 | G66: 비데 | H66: 복리후생비
B67: =B5 -> 신한 #672 | C67: 2023.04.25 | D67: 코웨이렌탈04 | F67: 20660 | G67: 정수기 | H67: 복리후생비
B68: =B5 -> 신한 #672 | C68: 2023.04.25 | D68: 노무법인청안 | F68: 110000 | G68: 노무 자문료 지급 | H68: 지급수수료
B69: =B5 -> 신한 #672 | C69: 2023.04.25 | D69: 삼덕회계법인 | F69: 330000 | G69: 회계 자문료 지급 | H69: 지급수수료
B70: =B5 -> 신한 #672 | C70: 2023.04.25 | D70: 현대카드(주) | F70: 3606802 | G70: 법인카드 대금 지급 | H70: 지급수수료
B71: =B5 -> 신한 #672 | C71: 2023.04.25 | D71: 바디프랜드4 | F71: 98000 | G71: 안마의자 | H71: 복리후생비 | L71: 투자금 | M71: 싱가폴 투자금 입금
B72: =B5 -> 신한 #672 | C72: 2023.04.28 | D72: (주)이오엠 | F72: 11000000 | G72: 트레일러 제작 선수금 | H72: 마케팅비
B73: =B5 -> 신한 #672 | C73: 2023.04.28 | D73: 강진석 | F73: 40000 | G73: 워크샵 교통비 + 간식비 지원 (2명) | H73: 복리후생비
B74: =B5 -> 신한 #672 | C74: 2023.04.28 | D74: LEE ELISHA | F74: 40500 | G74: 워크샵 교통비 + 간식비 지원 (2명) | H74: 복리후생비
B75: =B5 -> 신한 #672 | C75: 2023.04.28 | D75: 김종식 | F75: 40000 | G75: 워크샵 교통비 + 간식비 지원 (2명) | H75: 복리후생비
B76: =B5 -> 신한 #672 | C76: 2023.04.28 | D76: 안양신도판매 | F76: 77000 | G76: 복합기 사용료 지급 | H76: 지급수수료
B77: =B12 -> OCBC USD | C77: 2023.04.04 | D77: NEPTUNE COMPANY | E77: =499990.12 -> 499990.12 | G77: 투자금 입금 | H77: 투자금
B78: =B12 -> OCBC USD | C78: 2023.04.04 | D78: OCBC | F78: 7.48 | G78: 투자금 입금시 수수료 지급 | H78: 지급수수료
B79: =B12 -> OCBC USD | C79: 2023.04.11 | D79: FERTILERAINS | E79: 150003.43 | G79: 투자금 입금 | H79: 투자금
B80: =B12 -> OCBC USD | C80: 2023.04.11 | D80: OCBC | F80: 7.46 | G80: 투자금 입금시 수수료 지급 | H80: 지급수수료
B81: =B12 -> OCBC USD | C81: 2023.04.17 | D81: SEMA PUBLIC TECHNOL | E81: 299996.87 | G81: 투자금 입금 | H81: 투자금
B82: =B12 -> OCBC USD | C82: 2023.04.17 | D82: OCBC | F82: 7.45 | G82: 투자금 입금시 수수료 지급 | H82: 지급수수료
B83: =B13 -> OCBC SGD | C83: 2023.04.04 | D83: OCBC | F83: 10 | G83: 은행 수수료 | H83: 지급수수료
B84: =B13 -> OCBC SGD | C84: 2023.04.29 | D84: OCBC | F84: 15 | G84: 은행 수수료 | H84: 지급수수료

Sheet 23.05월
B1: 자 금 일 보
I2: Currency | J2: KRW | L2: 계정과목 | M2: 설명
B3: ※ 자금현황 | G3: 기준일: 2023.05.31 | I3: USD | J3: =IFERROR(__xludf.DUMMYFUNCTION("GOOGLEFINANCE(""USDKRW"")"),1472.7250000000001) -> 1472.725 | L3: 광고매출 | M3: 타법인 매출
B4: 구 분 | C4: 단위 | D4: 전월잔액 | E4: 수 입 | F4: 지 출 | G4: 기준일 기준 잔액 | I4: SGD | J4: =IFERROR(__xludf.DUMMYFUNCTION("GOOGLEFINANCE(""SGDKRW"")"),1143.885) -> 1143.885 | L4: 급여 | M4: 직원 급여
B5: 신한 #672 | C5: KRW | D5: ='23.04월'!G5 -> 16701926 | E5: =sumif(B22:B180,B5,E22:E182) -> 34000000 | F5: =sumif(B22:B122,B5,F22:F122) -> 29151834 | G5: =D5+E5-F5 -> 21550092 | L5: 미수금 | M5: 돌려 받을 예정인 금액 (ex. 부가세 환급금)
B6: 신한 #543 | C6: USD | D6: ='23.04월'!G6 -> 2.31 | E6: =sumif(B22:B182,B6,E22:E182) -> 0 | F6: =sumif(B22:B122,B6,F22:F122) -> 0 | G6: =D6+E6-F6 -> 2.31 | L6: 보증금 | M6: 보증금 (사무실 임대, 장비 리스 등)
B7: 하나 #304 | C7: KRW | D7: ='23.04월'!G7 -> 45610896 | E7: =sumif(B22:B182,B7,E22:E182) -> 196646017 | F7: =sumif(B22:B122,B7,F22:F122) -> 221721127 | G7: =D7+E7-F7 -> 20535786 | L7: 보통예금 | M7: 예금간 이체
B8: 하나 #138 | C8: USD | D8: ='23.04월'!G8 -> 0.89 | E8: =sumif(B22:B182,B8,E22:E182) -> 149990 | F8: =sumif(B22:B122,B8,F22:F122) -> 149990.89 | G8: =D8+E8-F8 -> 0 | L8: 복리후생비 | M8: 회식, 식대
B9: WISE USD | C9: USD | D9: ='23.04월'!G9 -> 63773.59 | E9: =sumif(B22:B122,B9,E22:E182) -> 1995.86 | F9: =sumif(B22:B122,B9,F22:F122) -> 53684.89 | G9: =D9+E9-F9 -> 12084.56 | L9: 비품 | M9: 가구, 가전등 개당 단가 150만원이 넘는 용품
B10: WISE SGD | C10: SGD | D10: ='23.04월'!G10 -> 200 | E10: =sumif(B22:B180,B10,E22:E122) -> 10564 | F10: =sumif(B22:B122,B10,F22:F122) -> 10764 | G10: =D10+E10-F10 -> 0 | L10: 사무용품비 | M10: 비품, 소모품비를 제외한 업무용 사무용품 구입
B11: WISE KRW | C11: KRW | D11: ='23.04월'!G11 -> 0 | E11: =sumif(B22:B182,B11,E22:E182) -> 1569941 | F11: =sumif(B22:B122,B11,F22:F122) -> 1569941 | G11: =D11+E11-F11 -> 0 | L11: 서비스용역매출 | M11: 매출
B12: OCBC USD | C12: USD | D12: ='23.04월'!G12 -> 957089.27 | E12: =sumif(B25:B125,B12,E25:E183) -> 1000 | F12: =sumif(B22:B121,B12,F22:F121) -> 123196.42 | G12: =D12+E12-F12 -> 834892.85 | L12: 세금과공과 | M12: 세금 납부시
B13: OCBC SGD | C13: SGD | D13: ='23.04월'!G13 -> 780 | E13: =sumif(B22:B182,B13,E22:E122) -> 0 | F13: =sumif(B22:B121,B13,F22:F121) -> 25 | G13: =D13+E13-F13 -> 755 | L13: 소모품비 | M13: 비품(150만원)으로 잡기에는 금액이 작은 비품
L14: 여비교통비 | M14: 출장, 대중교통, 대리운전
B15: KRW 합 계 | D15: =D5+D7+D11 -> 62312822 | E15: =E5+E7+E11 -> 232215958 | F15: =F5+F7+F11 -> 252442902 | G15: =G5+G11+G7 -> 42085878 | H15: =G15 -> 42085878 | I15: =D15 -> 62312822 | L15: 용역비 | M15: 외주용역비
B16: USD 합 계 | D16: =D6+D8+D9+D12 -> 1020866.1 | E16: =E6+E8+E9+E12 -> 152985.86 | F16: =F6+F8+F9+F12 -> 326872.2 | G16: =G9+G6+G8+G12 -> 846979.72 | H16: =rounddown(G16*$J$3,0) -> 1247368208 | I16: =rounddown(D16*$J$3,0) -> 1503454968 | L16: 접대비 | M16: 외부 미팅
B17: SGD 합 계 | D17: =D10+D13 -> 980 | E17: =E10+E13 -> 10564 | F17: =F10+F13 -> 10789 | G17: =G10+G13 -> 755 | H17: =rounddown(G17*$J$4,0) -> 863633 | I17: =rounddown(D17*$J$4,0) -> 1121007 | L17: 지급수수료 | M17: sms 수수료, 송금 수수료, 일반적으로 발생되는 모든 비용
H18: =SUM(H15:H17) -> 1290317719 | I18: =SUM(I15:I17) -> 1566888797 | L18: 이자수익 | M18: 은행이자
L19: 통신비 | M19: 등기, 퀵 사용비
B20: ※ 세부내역 | L20: 마케팅비 | M20: PR 기사등 마케팅 비용
B21: 구 분 | C21: 날 짜 | D21: 은 행 적 요 | E21: 수입 | F21: 지출 | G21: 상세메모 | H21: 계정과목 | L21: 대여금 | M21: 싱가폴 -> 한국 지사 송금
B22: =B9 -> WISE USD | C22: 2023.05.01 | D22: Milestone Business Group | F22: 10422.68 | G22: Chris 5월 급여 | H22: 급여
B23: =B9 -> WISE USD | C23: 2023.05.01 | D23: wise | F23: 0.39 | G23: Chris 5월 급여 송금 수수료 | H23: 지급수수료
B24: =B7 -> 하나 #304 | C24: 2023.05.01 | D24: 강진석 | F24: 30000500 | G24: 대여금 | H24: 대여금
B25: =B7 -> 하나 #304 | C25: 2023.05.04 | D25: 드호스타일 | F25: 3842800 | G25: 행사 케이터링 서비스 | H25: 마케팅비
B26: =B7 -> 하나 #304 | C26: 2023.05.04 | D26: 그림바우빌딩 | F26: 6029820 | G26: 4월 임대료,관리비,전기료 | H26: 지급수수료
B27: =B7 -> 하나 #304 | C27: 2023.05.04 | D27: 비앤케이 | F27: 825500 | G27: 4월법률자문료 | H27: 지급수수료
B28: =B7 -> 하나 #304 | C28: 2023.05.04 | D28: 석진상회 | F28: 90500 | G28: 행사용 주류 구입 | H28: 마케팅비
B29: =B7 -> 하나 #304 | C29: 2023.05.04 | D29: 최고은 | F29: 40500 | G29: 워크샵 교통비 + 간식비 지원 (2명) | H29: 복리후생비
B30: =B7 -> 하나 #304 | C30: 2023.05.04 | D30: 최지현 | F30: 20500 | G30: 워크샵 교통비 + 간식비 지원 (1명) | H30: 복리후생비
B31: =B7 -> 하나 #304 | C31: 2023.05.04 | D31: 권우철 | F31: 20500 | G31: 워크샵 교통비 + 간식비 지원 (1명) | H31: 복리후생비
B32: =B7 -> 하나 #304 | C32: 2023.05.04 | D32: 이이슬 | F32: 100480 | G32: 개인경비 | H32: 복리후생비
B33: =B7 -> 하나 #304 | C33: 2023.05.08 | D33: 주식회사 제로엑스앤드 | F33: 4000500 | G33: 계좌간 자금 이체 | H33: 보통예금
B34: =B5 -> 신한 #672 | C34: 2023.05.08 | D34: 주식회사 제로엑스앤드 | E34: 4000000 | G34: 계좌간 자금 이체 | H34: 보통예금
B35: =B9 -> WISE USD | C35: 2023.05.08 | D35: ZERO X AND PTE. LTD | F35: 30014.39 | G35: 한국법인 운영비 | H35: 보통예금
B36: =B9 -> WISE USD | C36: 2023.05.08 | D36: Milestone Business Group | F36: =1735.02+0.39 -> 1735.41 | G36: Chris 개인경비 | H36: 복리후생비
B37: =B9 -> WISE USD | C37: 2023.05.08 | D37: ZERO X AND PTE. LTD | F37: 1200 | G37: 환전 | H37: 보통예금
B38: =B11 -> WISE KRW | C38: 2023.05.08 | D38: ZERO X AND PTE. LTD | E38: 1569941 | G38: 환전 | H38: 보통예금
B39: =B11 -> WISE KRW | C39: 2023.05.08 | D39: Jeon Juneyoung | F39: 1531450 | G39: 바트 개인경비 | H39: 복리후생비
B40: =B5 -> 신한 #672 | C40: 2023.05.10 | D40: 2304국민건강 | F40: 4894740 | G40: 2304국민건강 | H40: 세금과공과
B41: =B5 -> 신한 #672 | C41: 2023.05.10 | D41: 2304국민연금 | F41: 5781560 | G41: 2304국민연금 | H41: 세금과공과
B42: =B5 -> 신한 #672 | C42: 2023.05.10 | D42: 2304고용보험 | F42: 1423710 | G42: 2304고용보험 | H42: 세금과공과
B43: =B5 -> 신한 #672 | C43: 2023.05.10 | D43: 2304산재보험 | F43: 527580 | G43: 2304산재보험 | H43: 세금과공과
B44: =B8 -> 하나 #138 | C44: 2023.05.10 | D44: ZERO X AND PTE. LTD | E44: 30000 | G44: 한국법인 운영비 | H44: 보통예금
B45: =B8 -> 하나 #138 | C45: 2023.05.10 | D45: 주식회사 제로엑스앤드코리아 | F45: 30000 | G45: 환전 | H45: 보통예금
B46: =B7 -> 하나 #304 | C46: 2023.05.10 | D46: 주식회사 제로엑스앤드코리아 | E46: 39401700 | G46: 환전 | H46: 보통예금
B47: =B7 -> 하나 #304 | C47: 2023.05.10 | D47: 국고_주식회사 제로 | F47: 7918280 | G47: 4월 근로 소득세 | H47: 세금과공과
B48: =B7 -> 하나 #304 | C48: 2023.05.10 | D48: 서울지방제로엑 | F48: 794790 | G48: 4월 근로 지방 소득세 | H48: 세금과공과
B49: =B7 -> 하나 #304 | C49: 2023.05.10 | D49: 국고_주식회사 제로 | F49: 30000 | G49: 4월 사업 소득세 | H49: 세금과공과
B50: =B7 -> 하나 #304 | C50: 2023.05.10 | D50: 메가존소프트(주) | F50: 4600317 | G50: 메가존 구글사용료 | H50: 지급수수료
B51: =B9 -> WISE USD | C51: 2023.05.11 | D51: ZERO X AND PTE. LTD | F51: 8001.67 | G51: 환전 | H51: 보통예금
B52: =B10 -> WISE SGD | C52: 2023.05.11 | D52: ZERO X AND PTE. LTD | E52: 10564 | G52: 환전 | H52: 보통예금
B53: =B10 -> WISE SGD | C53: 2023.05.11 | D53: EBOS Advisory Pte Ltd | F53: 10564 | G53: 등기 수수료 지급 | H53: 지급수수료
B54: =B10 -> WISE SGD | C54: 2023.05.13 | D54: EBOS Advisory Pte Ltd | F54: 10 | G54: 등기 수수료 지급 | H54: 지급수수료
B55: =B9 -> WISE USD | C55: 2023.05.14 | D55: Postmarkapp.com | F55: 10 | G55: 서비스 이용료 지급 | H55: 지급수수료
B56: =B9 -> WISE USD | C56: 2023.05.15 | D56: Fiverr | F56: 1055 | G56: 서비스 이용료 지급 | H56: 지급수수료
B57: =B5 -> 신한 #672 | C57: 2023.05.19 | D57: 신한은행 | F57: 4400 | G57: 인증수수료 갱신 수수료 지급 | H57: 지급수수료
B58: =B5 -> 신한 #672 | C58: 2023.05.19 | D58: (주)엔시엘오 | F58: 220000 | G58: 모니터 구입 | H58: 소모품비
B59: =B7 -> 하나 #304 | C59: 2023.05.19 | D59: (주)원티드랩 | F59: =2860000+500 -> 2860500 | G59: 채용플랫폼 이용수수료(주시온) | H59: 지급수수료
B60: =B7 -> 하나 #304 | C60: 2023.05.19 | D60: 메가존소프트(주) | F60: =113049+500 -> 113549 | G60: 메가존 구글 계정 추가비용 | H60: 지급수수료
B61: =B7 -> 하나 #304 | C61: 2023.05.19 | D61: (주)웰리더 | F61: =917400+500 -> 917900 | G61: PR 기사 수수료 | H61: 마케팅비
B62: =B5 -> 신한 #672 | C62: 2023.05.22 | D62: 세콤 | F62: 110000 | G62: 세콤 비용 지급 | H62: 지급수수료
B63: =B8 -> 하나 #138 | C63: 2023.05.22 | D63: ZERO X AND PTE. LTD | E63: 69995 | G63: 한국법인 운영비 | H63: 보통예금
B64: =B10 -> WISE SGD | C64: 2023.05.23 | D64: Fiverr | F64: 190 | G64: 서비스 이용료 지급 | H64: 지급수수료
B65: =B9 -> WISE USD | C65: 2023.05.23 | D65: Fiverr | F65: 942.47 | G65: 서비스 이용료 지급 | H65: 지급수수료
B66: =B11 -> WISE KRW | C66: 2023.05.23 | D66: Fiverr | F66: 38491 | G66: 서비스 이용료 지급 | H66: 지급수수료
B67: =B9 -> WISE USD | C67: 2023.05.24 | D67: EBOS Advisory Pte Ltd | F67: 302.88 | G67: 22년 재무제표, 법인세 신고 비용 지급 | H67: 지급수수료
B68: =B8 -> 하나 #138 | C68: 2023.05.24 | D68: ZERO X AND PTE. LTD | F68: 69995.89 | G68: 환전 | H68: 보통예금
B69: =B7 -> 하나 #304 | C69: 2023.05.24 | D69: ZERO X AND PTE. LTD | E69: 91371934 | G69: 환전 | H69: 보통예금
B70: =B7 -> 하나 #304 | C70: 2023.05.24 | D70: 현금 | F70: 200000 | G70: 거래처 경조사 축의금 | H70: 접대비
B71: =B5 -> 신한 #672 | C71: 2023.05.25 | D71: 주식회사 제로엑스앤드코리아 | E71: 20000000 | G71: 계좌간 자금이체 | H71: 보통예금
B72: =B5 -> 신한 #672 | C72: 2023.05.25 | D72: KT0540091105 | F72: 57360 | G72: 인터넷, 전화 요금 지급 | H72: 복리후생비
B73: =B5 -> 신한 #672 | C73: 2023.05.25 | D73: 노무법인청안 | F73: 110000 | G73: 노무 자문료 지급 | H73: 지급수수료
B74: =B5 -> 신한 #672 | C74: 2023.05.25 | D74: 삼덕회계법인 | F74: 330000 | G74: 회계 자문료 지급 | H74: 지급수수료
B75: =B5 -> 신한 #672 | C75: 2023.05.25 | D75: 코웨이렌탈05 | F75: 50250 | G75: 정수기 | H75: 복리후생비
B76: =B5 -> 신한 #672 | C76: 2023.05.25 | D76: 코웨이렌탈05 | F76: 37430 | G76: 공청기 | H76: 복리후생비
B77: =B5 -> 신한 #672 | C77: 2023.05.25 | D77: 코웨이렌탈05 | F77: 37430 | G77: 공청기 | H77: 복리후생비
B78: =B5 -> 신한 #672 | C78: 2023.05.25 | D78: 코웨이렌탈05 | F78: 20660 | G78: 비데 | H78: 복리후생비
B79: =B5 -> 신한 #672 | C79: 2023.05.25 | D79: 코웨이렌탈05 | F79: 20660 | G79: 비데 | H79: 복리후생비
B80: =B5 -> 신한 #672 | C80: 2023.05.25 | D80: 현대카드(주) | F80: 4428054 | G80: 법인카드 대금 지급 | H80: 지급수수료
B81: =B5 -> 신한 #672 | C81: 2023.05.25 | D81: 바디프랜드4 | F81: 98000 | G81: 안마의자 | H81: 복리후생비
B82: =B7 -> 하나 #304 | C82: 2023.05.25 | D82: 하나카드기업 | F82: 7809143 | G82: 법인카드 대금 지급 | H82: 지급수수료
B83: =B7 -> 하나 #304 | C83: 2023.05.25 | D83: 급여 | F83: 75097288 | G83: 5월 급여 | H83: 용역비
B84: =B7 -> 하나 #304 | C84: 2023.05.25 | D84: 여택기 | F84: 150500 | G84: 프리랜서 외주_디스코드 세팅 | H84: 용역비
B85: =B7 -> 하나 #304 | C85: 2023.05.25 | D85: (주)제로엑스앤드코 | F85: 20000500 | G85: 계좌간 자금이체 | H85: 보통예금
B86: =B7 -> 하나 #304 | C86: 2023.05.25 | D86: 안현지 | F86: 309940 | G86: 프리랜서 외주_커뮤니티 이미지 제작 | H86: 용역비
B87: =B7 -> 하나 #304 | C87: 2023.05.26 | D87: 안현지 | E87: 309440 | G87: 프리랜서 외주_커뮤니티 이미지 제작 | H87: 용역비
B88: =B7 -> 하나 #304 | C88: 2023.05.26 | D88: 안현웅 | F88: 309940 | G88: 프리랜서 외주_커뮤니티 이미지 제작 | H88: 용역비
B89: =B5 -> 신한 #672 | C89: 2023.05.30 | D89: (주)이오엠 | F89: 11000000 | G89: 트레일러 제작 선수금 | H89: 마케팅비
B90: =B8 -> 하나 #138 | C90: 2023.05.30 | D90: ZERO X AND PTE. LTD | E90: 49995 | G90: 한국법인 운영비 | H90: 보통예금
B91: =B8 -> 하나 #138 | C91: 2023.05.31 | D91: ZERO X AND PTE. LTD | F91: 49995 | G91: 환전 | H91: 보통예금
B92: =B7 -> 하나 #304 | C92: 2023.05.31 | D92: ZERO X AND PTE. LTD | E92: 65562943 | G92: 환전 | H92: 보통예금
B93: =B7 -> 하나 #304 | C93: 2023.05.31 | D93: 상여금 | F93: 45636380 | G93: 상여금 지급 | H93: 급여
B94: =B7 -> 하나 #304 | C94: 2023.05.31 | D94: ZERO X AND PTE. LTD | F94: 10000500 | G94: 계좌간 자금이체 | H94: 보통예금
B95: =B5 -> 신한 #672 | C95: 2023.05.31 | D95: ZERO X AND PTE. LTD | E95: 10000000 | G95: 계좌간 자금이체 | H95: 보통예금
B96: =B9 -> WISE USD | C96: 2023.05.31 | D96: ZERO X AND PTE. LTD | E96: 1995.86 | G96: 계좌간 자금이체 | H96: 보통예금
B97: =B12 -> OCBC USD | C97: 2023.05.19 | D97: ZERO X AND PTE. LTD | F97: 1000 | G97: 자금이동 | H97: 보통예금
B98: =B12 -> OCBC USD | C98: 2023.05.19 | D98: OCBC | F98: 22.42 | G98: 은행 수수료 | H98: 지급수수료
B99: =B12 -> OCBC USD | C99: 2023.05.19 | D99: ZERO X AND PTE. LTD | F99: 70000 | G99: 한국법인 운영비 | H99: 보통예금
B100: =B12 -> OCBC USD | C100: 2023.05.19 | D100: OCBC | F100: 43 | G100: 은행 수수료 | H100: 지급수수료
...

Sheet 23.06월
B1: 자 금 일 보
I2: Currency | J2: KRW | L2: 계정과목 | M2: 설명
B3: ※ 자금현황 | G3: 기준일: 2023.06.26 | I3: USD | J3: =IFERROR(__xludf.DUMMYFUNCTION("GOOGLEFINANCE(""USDKRW"")"),1472.7250000000001) -> 1472.725 | L3: 광고매출 | M3: 타법인 매출
B4: 구 분 | C4: 단위 | D4: 전월잔액 | E4: 수 입 | F4: 지 출 | G4: 기준일 기준 잔액 | I4: SGD | J4: =IFERROR(__xludf.DUMMYFUNCTION("GOOGLEFINANCE(""SGDKRW"")"),1143.885) -> 1143.885 | L4: 급여 | M4: 직원 급여
B5: 신한 #672 | C5: KRW | D5: ='23.05월'!G5 -> 21550092 | E5: =sumif(B22:B184,B5,E22:E186) -> 30004999 | F5: =sumif(B22:B126,B5,F22:F187) -> 30841057 | G5: =D5+E5-F5 -> 20714034 | L5: 미수금 | M5: 돌려 받을 예정인 금액 (ex. 부가세 환급금)
B6: 신한 #543 | C6: USD | D6: ='23.05월'!G6 -> 2.31 | E6: =sumif(B22:B186,B6,E22:E186) -> 0 | F6: =sumif(B22:B126,B6,F22:F186) -> 0 | G6: =D6+E6-F6 -> 2.31 | L6: 보증금 | M6: 보증금 (사무실 임대, 장비 리스 등)
B7: 하나 #304 | C7: KRW | D7: ='23.05월'!G7 -> 20535786 | E7: =sumif(B22:B186,B7,E22:E186) -> 129556871 | F7: =sumif(B22:B126,B7,F22:F186) -> 146820392 | G7: =D7+E7-F7 -> 3272265 | L7: 보통예금 | M7: 예금간 이체
B8: 하나 #138 | C8: USD | D8: ='23.05월'!G8 -> 0 | E8: =sumif(B22:B186,B8,E22:E186) -> 100000.12 | F8: =sumif(B22:B126,B8,F22:F186) -> 100000 | G8: =D8+E8-F8 -> 0.12 | L8: 복리후생비 | M8: 회식, 식대
B9: WISE USD | C9: USD | D9: ='23.05월'!G9 -> 12084.56 | E9: =sumif(B22:B126,B9,E22:E186) -> 447995.98 | F9: =sumif(B22:B126,B9,F22:F186) -> 139469.69 | G9: =D9+E9-F9 -> 320610.85 | L9: 비품 | M9: 가구, 가전등 개당 단가 150만원이 넘는 용품
B10: WISE SGD | C10: SGD | D10: ='23.05월'!G10 -> 0 | E10: =sumif(B22:B184,B10,E22:E126) -> 0 | F10: =sumif(B22:B126,B10,F22:F186) -> 0 | G10: =D10+E10-F10 -> 0 | L10: 사무용품비 | M10: 비품, 소모품비를 제외한 업무용 사무용품 구입
B11: WISE KRW | C11: KRW | D11: ='23.05월'!G11 -> 0 | E11: =sumif(B22:B186,B11,E22:E186) -> 0 | F11: =sumif(B22:B126,B11,F22:F186) -> 0 | G11: =D11+E11-F11 -> 0 | L11: 서비스용역매출 | M11: 매출
B12: OCBC USD | C12: USD | D12: ='23.05월'!G12 -> 834892.85 | E12: =sumif(B22:B129,B12,E22:E129) -> 0 | F12: =sumif(B22:B125,B12,F22:F187) -> 448058.12 | G12: =D12+E12-F12 -> 386834.73 | L12: 세금과공과 | M12: 세금 납부시
B13: OCBC SGD | C13: SGD | D13: ='23.05월'!G13 -> 755 | E13: =sumif(B22:B186,B13,E22:E187) -> 0 | F13: =sumif(B22:B125,B13,F22:F187) -> 25 | G13: =D13+E13-F13 -> 730 | L13: 소모품비 | M13: 비품(150만원)으로 잡기에는 금액이 작은 비품
L14: 여비교통비 | M14: 출장, 대중교통, 대리운전
B15: KRW 합 계 | D15: =D5+D7+D11 -> 42085878 | E15: =E5+E7+E11 -> 159561870 | F15: =F5+F7+F11 -> 177661449 | G15: =G5+G11+G7 -> 23986299 | H15: =G15 -> 23986299 | I15: =D15 -> 42085878 | L15: 용역비 | M15: 외주용역비
B16: USD 합 계 | D16: =D6+D8+D9+D12 -> 846979.72 | E16: =E6+E8+E9+E12 -> 547996.1 | F16: =F6+F8+F9+F12 -> 687527.81 | G16: =G9+G6+G8+G12 -> 707448.01 | H16: =rounddown(G16*$J$3,0) -> 1041876370 | I16: =rounddown(D16*$J$3,0) -> 1247368208 | L16: 접대비 | M16: 외부 미팅
B17: SGD 합 계 | D17: =D10+D13 -> 755 | E17: =E10+E13 -> 0 | F17: =F10+F13 -> 25 | G17: =G10+G13 -> 730 | H17: =rounddown(G17*$J$4,0) -> 835036 | I17: =rounddown(D17*$J$4,0) -> 863633 | L17: 지급수수료 | M17: sms 수수료, 송금 수수료, 일반적으로 발생되는 모든 비용
H18: =SUM(H15:H17) -> 1066697705 | I18: =SUM(I15:I17) -> 1290317719 | L18: 이자수익 | M18: 은행이자
H19: =H18-I18 -> -223620014 | L19: 통신비 | M19: 등기, 퀵 사용비
B20: ※ 세부내역 | L20: 마케팅비 | M20: PR 기사등 마케팅 비용
B21: 구 분 | C21: 날 짜 | D21: 은 행 적 요 | E21: 수입 | F21: 지출 | G21: 상세메모 | H21: 계정과목 | L21: 대여금 | M21: 싱가폴 -> 한국 지사 송금
B22: =B9 -> WISE USD | C22: 2023.06.01 | D22: Milestone Business Group | F22: 10422.68 | G22: Chris 6월 급여 | H22: 급여
B23: =B9 -> WISE USD | C23: 2023.06.01 | D23: Milestone Business Group | F23: 90.92 | G23: Chris 개인 경비 | H23: 복리후생비
B24: =B9 -> WISE USD | C24: 2023.06.01 | D24: wise | F24: 0.39 | G24: Chris 6월 급여 송금 수수료 | H24: 지급수수료
B25: =B12 -> OCBC USD | C25: 2023.06.01 | D25: ZERO X AND PTE. LTD | F25: 448000.12 | G25: 계좌간 자금이체 | H25: 보통예금
B26: =B12 -> OCBC USD | C26: 2023.06.01 | D26: OCBC | F26: 43 | G26: 은행 수수료 | H26: 지급수수료
B27: =B12 -> OCBC USD | C27: 2023.06.01 | D27: OCBC | F27: 15 | G27: 은행 수수료 | H27: 지급수수료
B28: =B9 -> WISE USD | C28: 2023.06.05 | D28: ZERO X AND PTE. LTD | E28: 447995.98 | G28: 계좌간 자금이체 | H28: 보통예금
B29: =B9 -> WISE USD | C29: 2023.06.05 | D29: Nimas Ayu Putri Surasmi Soekidin | F29: 393.75 | G29: 프리랜서 계약 선수금 지급 | H29: 용역비
B30: =B9 -> WISE USD | C30: 2023.06.05 | D30: wise 송금수수료 | F30: 14.39 | G30: wise 송금수수료 | H30: 지급수수료
B31: =B7 -> 하나 #304 | C31: 2023.06.05 | D31: 그림바우빌딩 | F31: =6123810+500 -> 6124310 | G31: 5월 임대료,관리비,전기료 | H31: 지급수수료
B32: =B7 -> 하나 #304 | C32: 2023.06.05 | D32: 비앤케이 | F32: =825000+500 -> 825500 | G32: 5월법률자문료 | H32: 지급수수료
B33: =B5 -> 신한 #672 | C33: 2023.06.01 | D33: 안양신도판매 | F33: 77000 | G33: 복합기 사용료 지급 | H33: 지급수수료
B34: =B8 -> 하나 #138 | C34: 2023.06.08 | D34: ZERO X AND PTE. LTD | E34: 100000 | G34: 계좌간 자금이체 | H34: 보통예금
B35: =B8 -> 하나 #138 | C35: 2023.06.08 | D35: ZERO X AND PTE. LTD | F35: 100000 | G35: 계좌간 자금이체 | H35: 보통예금
B36: =B7 -> 하나 #304 | C36: 2023.06.08 | D36: 제로엑스앤드코리아 | E36: 129548000 | G36: 환전 | H36: 보통예금
B37: =B7 -> 하나 #304 | C37: 2023.06.08 | D37: 국세청 | F37: 19755050 | G37: 5월 근로 소득세 | H37: 세금과공과
B38: =B7 -> 하나 #304 | C38: 2023.06.08 | D38: 강남구청 | F38: 1976350 | G38: 5월 근로 지방 소득세 | H38: 세금과공과
B39: =B7 -> 하나 #304 | C39: 2023.06.08 | D39: 국세청 | F39: 9450 | G39: 5월 사업 소득세 | H39: 세금과공과
B40: =B7 -> 하나 #304 | C40: 2023.06.08 | D40: 메가존소프트(주) | F40: 4244500 | G40: 메가존 구글사용료 | H40: 지급수수료
B41: =B7 -> 하나 #304 | C41: 2023.06.08 | D41: 제로엑스앤드코리아 | F41: 30000500 | G41: 계좌간 자금 이체 | H41: 보통예금
B42: =B5 -> 신한 #672 | C42: 2023.06.08 | D42: 제로엑스앤드코리아 | E42: 30000000 | G42: 계좌간 자금 이체 | H42: 보통예금
B43: =B9 -> WISE USD | C43: 2023.06.07 | D43: Neicon Inc. | F43: 27395 | G43: 게임 도시 마케팅 비용 지급 | H43: 마케팅비
B44: =B9 -> WISE USD | C44: 2023.06.07 | D44: wise | F44: 14.39 | G44: 송금수수료 지급 | H44: 지급수수료
B45: =B9 -> WISE USD | C45: 2023.06.07 | D45: ZERO X AND PTE. LTD | F45: 100000 | G45: 한국법인 운영비 | H45: 보통예금
B46: =B9 -> WISE USD | C46: 2023.06.07 | D46: wise | F46: 14.39 | G46: 송금수수료 지급 | H46: 지급수수료
B47: =B9 -> WISE USD | C47: 2023.06.12 | D47: Fiverr | F47: 1113.78 | G47: 서비스 이용료 지급 | H47: 지급수수료
B48: =B5 -> 신한 #672 | C48: 2023.06.12 | D48: 2305국민건강 | F48: 6056380 | G48: 2305국민건강 | H48: 세금과공과
B49: =B5 -> 신한 #672 | C49: 2023.06.12 | D49: 2305국민연금 | F49: 6279260 | G49: 2305국민연금 | H49: 세금과공과
B50: =B5 -> 신한 #672 | C50: 2023.06.12 | D50: 2305고용보험 | F50: 1200510 | G50: 2305고용보험 | H50: 세금과공과
B51: =B5 -> 신한 #672 | C51: 2023.06.12 | D51: 2305산재보험 | F51: 444900 | G51: 2305산재보험 | H51: 세금과공과
B52: =B13 -> OCBC SGD | C52: 2023.06.05 | D52: OCBC | F52: 10 | G52: 은행 수수료 | H52: 지급수수료
B53: =B13 -> OCBC SGD | C53: 2023.06.30 | D53: OCBC | F53: 15 | G53: 은행 수수료 | H53: 지급수수료
B54: =B5 -> 신한 #672 | C54: 2023.06.17 | D54: 신한은행 | E54: 4999 | G54: 예금이자 | H54: 이자수익
B55: =B7 -> 하나 #304 | C55: 2023.06.17 | D55: 하나은행 | E55: 8871 | G55: 예금이자 | H55: 이자수익
B56: =B8 -> 하나 #138 | C56: 2023.06.17 | D56: 하나은행 | E56: 0.12 | G56: 예금이자 | H56: 이자수익
B57: =B5 -> 신한 #672 | C57: 2023.06.21 | D57: 세콤 | F57: 110000 | G57: 세콤 비용 지급 | H57: 지급수수료
B58: =B5 -> 신한 #672 | C58: 2023.06.23 | D58: 주식회사웰리더 | F58: 572000 | G58: PR 기사 비용 지급 | H58: 마케팅비
B59: =B7 -> 하나 #304 | C59: 2023.06.23 | D59: 급여 | F59: 78738716 | G59: 6월 급여 지급 | H59: 급여
B60: =B9 -> WISE USD | C60: 2023.06.14 | D60: Postmarkapp.com | F60: 10 | G60: 서비스 이용료 지급 | H60: 지급수수료
B61: =B7 -> 하나 #304 | C61: 2023.06.26 | D61: 하나카드기업 | F61: 5146016 | G61: 법인카드 대금 지급 | H61: 지급수수료
B62: =B5 -> 신한 #672 | C62: 2023.06.26 | D62: KT0540091106 | F62: 55770 | G62: 인터넷, 전화 요금 지급 | H62: 복리후생비
B63: =B5 -> 신한 #672 | C63: 2023.06.26 | D63: 노무법인청안 | F63: 110000 | G63: 노무 자문료 지급 | H63: 지급수수료
B64: =B5 -> 신한 #672 | C64: 2023.06.26 | D64: 삼덕회계법인 | F64: 330000 | G64: 회계 자문료 지급 | H64: 지급수수료
B65: =B5 -> 신한 #672 | C65: 2023.06.26 | D65: 코웨이렌탈06 | F65: 20660 | G65: 공청기 | H65: 복리후생비
B66: =B5 -> 신한 #672 | C66: 2023.06.26 | D66: 코웨이렌탈06 | F66: 20660 | G66: 공청기 | H66: 복리후생비
B67: =B5 -> 신한 #672 | C67: 2023.06.26 | D67: 코웨이렌탈06 | F67: 37430 | G67: 비데 | H67: 복리후생비
B68: =B5 -> 신한 #672 | C68: 2023.06.26 | D68: 코웨이렌탈06 | F68: 50250 | G68: 정수기 | H68: 복리후생비
B69: =B5 -> 신한 #672 | C69: 2023.06.26 | D69: 코웨이렌탈06 | F69: 37430 | G69: 비데 | H69: 복리후생비
B70: =B5 -> 신한 #672 | C70: 2023.06.26 | D70: 현대카드(주) | F70: 4263807 | G70: 법인카드 대금 지급 | H70: 지급수수료
B71: =B5 -> 신한 #672 | C71: 2023.06.26 | D71: 바디프랜드6 | F71: 98000 | G71: 안마의자 | H71: 복리후생비
B72: =B5 -> 신한 #672 | C72: 2023.06.28 | D72: (주)이오엠 | F72: 11000000 | G72: 트레일러 제작 선수금 | H72: 마케팅비
B73: =B5 -> 신한 #672 | C73: 2023.06.30 | D73: 안양신도판매 | F73: 77000 | G73: 복합기 사용료 지급 | H73: 지급수수료

Sheet 23.07월
B1: 자 금 일 보
I2: Currency | J2: KRW | L2: 계정과목 | M2: 설명
B3: ※ 자금현황 | G3: 기준일: 2023.07.31 | I3: USD | J3: =IFERROR(__xludf.DUMMYFUNCTION("GOOGLEFINANCE(""USDKRW"")"),1472.7250000000001) -> 1472.725 | L3: 광고매출 | M3: 타법인 매출
B4: 구 분 | C4: 단위 | D4: 전월잔액 | E4: 수 입 | F4: 지 출 | G4: 기준일 기준 잔액 | I4: SGD | J4: =IFERROR(__xludf.DUMMYFUNCTION("GOOGLEFINANCE(""SGDKRW"")"),1143.885) -> 1143.885 | L4: 급여 | M4: 직원 급여
B5: 신한 #672 | C5: KRW | D5: ='23.06월'!G5 -> 20714034 | E5: =sumif(B22:B175,B5,E22:E177) -> 30000000 | F5: =sumif(B22:B117,B5,F22:F178) -> 31973499 | G5: =D5+E5-F5 -> 18740535 | L5: 미수금 | M5: 돌려 받을 예정인 금액 (ex. 부가세 환급금)
B6: 신한 #543 | C6: USD | D6: ='23.06월'!G6 -> 2.31 | E6: =sumif(B22:B177,B6,E22:E177) -> 0 | F6: =sumif(B22:B117,B6,F22:F177) -> 0 | G6: =D6+E6-F6 -> 2.31 | L6: 보증금 | M6: 보증금 (사무실 임대, 장비 리스 등)
B7: 하나 #304 | C7: KRW | D7: ='23.06월'!G7 -> 3272265 | E7: =sumif(B22:B177,B7,E22:E177) -> 129468000 | F7: =sumif(B22:B117,B7,F22:F177) -> 130213403 | G7: =D7+E7-F7 -> 2526862 | L7: 보통예금 | M7: 예금간 이체
B8: 하나 #138 | C8: USD | D8: ='23.06월'!G8 -> 0.12 | E8: =sumif(B22:B177,B8,E22:E177) -> 100000 | F8: =sumif(B22:B117,B8,F22:F177) -> 100000 | G8: =D8+E8-F8 -> 0.12 | L8: 복리후생비 | M8: 회식, 식대
B9: WISE USD | C9: USD | D9: ='23.06월'!G9 -> 320610.85 | E9: =sumif(B22:B117,B9,E22:E177) -> 1814.39 | F9: =sumif(B22:B117,B9,F22:F177) -> 124145.97 | G9: =D9+E9-F9 -> 198279.27 | L9: 비품 | M9: 가구, 가전등 개당 단가 150만원이 넘는 용품
B10: WISE SGD | C10: SGD | D10: ='23.06월'!G10 -> 0 | E10: =sumif(B22:B175,B10,E22:E117) -> 0 | F10: =sumif(B22:B117,B10,F22:F177) -> 0 | G10: =D10+E10-F10 -> 0 | L10: 사무용품비 | M10: 비품, 소모품비를 제외한 업무용 사무용품 구입
B11: WISE KRW | C11: KRW | D11: ='23.06월'!G11 -> 0 | E11: =sumif(B22:B177,B11,E22:E177) -> 0 | F11: =sumif(B22:B117,B11,F22:F177) -> 0 | G11: =D11+E11-F11 -> 0 | L11: 서비스용역매출 | M11: 매출
B12: OCBC USD | C12: USD | D12: ='23.06월'!G12 -> 386834.73 | E12: =sumif(B22:B120,B12,E22:E120) -> 0 | F12: =sumif(B22:B116,B12,F22:F178) -> 0 | G12: =D12+E12-F12 -> 386834.73 | L12: 세금과공과 | M12: 세금 납부시
B13: OCBC SGD | C13: SGD | D13: ='23.06월'!G13 -> 730 | E13: =sumif(B22:B177,B13,E22:E178) -> 0 | F13: =sumif(B22:B116,B13,F22:F178) -> 25 | G13: =D13+E13-F13 -> 705 | L13: 소모품비 | M13: 비품(150만원)으로 잡기에는 금액이 작은 비품
L14: 여비교통비 | M14: 출장, 대중교통, 대리운전
B15: KRW 합 계 | D15: =D5+D7+D11 -> 23986299 | E15: =E5+E7+E11 -> 159468000 | F15: =F5+F7+F11 -> 162186902 | G15: =G5+G11+G7 -> 21267397 | H15: =G15 -> 21267397 | I15: =D15 -> 23986299 | L15: 용역비 | M15: 외주용역비
B16: USD 합 계 | D16: =D6+D8+D9+D12 -> 707448.01 | E16: =E6+E8+E9+E12 -> 101814.39 | F16: =F6+F8+F9+F12 -> 224145.97 | G16: =G9+G6+G8+G12 -> 585116.43 | H16: =rounddown(G16*$J$3,0) -> 861715594 | I16: =rounddown(D16*$J$3,0) -> 1041876370 | L16: 접대비 | M16: 외부 미팅
B17: SGD 합 계 | D17: =D10+D13 -> 730 | E17: =E10+E13 -> 0 | F17: =F10+F13 -> 25 | G17: =G10+G13 -> 705 | H17: =rounddown(G17*$J$4,0) -> 806438 | I17: =rounddown(D17*$J$4,0) -> 835036 | L17: 지급수수료 | M17: sms 수수료, 송금 수수료, 일반적으로 발생되는 모든 비용
H18: =SUM(H15:H17) -> 883789429 | I18: =SUM(I15:I17) -> 1066697705 | L18: 이자수익 | M18: 은행이자
H19: =H18-I18 -> -182908276 | L19: 통신비 | M19: 등기, 퀵 사용비
B20: ※ 세부내역 | L20: 마케팅비 | M20: PR 기사등 마케팅 비용
B21: 구 분 | C21: 날 짜 | D21: 은 행 적 요 | E21: 수입 | F21: 지출 | G21: 상세메모 | H21: 계정과목 | L21: 대여금 | M21: 싱가폴 -> 한국 지사 송금
B22: =B9 -> WISE USD | C22: 2023.07.01 | D22: Milestone Business Group | F22: 10422.68 | G22: Chris 7월 급여 | H22: 급여 | L22: 출장비 | M22: 출장여비
B23: =B9 -> WISE USD | C23: 2023.07.01 | D23: wise | F23: 0.39 | G23: Chris 7월 급여 송금 수수료 | H23: 지급수수료
B24: =B7 -> 하나 #304 | C24: 2023.07.04 | D24: 최유빈 면접비+사무실현금시재 | F24: 100000 | G24: 최유빈 면접비(7만원)+사무실현금시재 | H24: 복리후생비
B25: =B9 -> WISE USD | C25: 2023.07.05 | D25: ZERO X AND PTE. LTD. | F25: 100000 | G25: 계좌간 자금이체 | H25: 보통예금
B26: =B9 -> WISE USD | C26: 2023.07.05 | D26: wise 송금수수료 | F26: 14.39 | G26: wise 송금수수료 | H26: 지급수수료
B27: =B8 -> 하나 #138 | C27: 2023.07.06 | D27: ZERO X AND PTE. LTD. | E27: 100000 | G27: 계좌간 자금이체 | H27: 보통예금
B28: =B8 -> 하나 #138 | C28: 2023.07.07 | D28: 주식회사 제로엑스앤드코리아 | F28: 100000 | G28: 환전 | H28: 보통예금
B29: =B7 -> 하나 #304 | C29: 2023.07.07 | D29: 주식회사 제로엑스앤드코리아 | E29: 129468000 | G29: 환전 | H29: 보통예금
B30: =B7 -> 하나 #304 | C30: 2023.07.10 | D30: 국고_주식회사 제로 | F30: 6947970 | G30: 6월 근로 소득세 | H30: 세금과공과
B31: =B7 -> 하나 #304 | C31: 2023.07.10 | D31: 서울지방제로엑 | F31: 694720 | G31: 6월 근로 지방 소득세 | H31: 세금과공과
B32: =B7 -> 하나 #304 | C32: 2023.07.10 | D32: (주)제로엑스앤드코 | F32: 30000500 | G32: 계좌간 자금 이체 | H32: 보통예금
B33: =B7 -> 하나 #304 | C33: 2023.07.11 | D33: 전준영 | F33: 300500 | G33: 태국 출장 현지 여비 지급 | H33: 출장비
B34: =B5 -> 신한 #672 | C34: 2023.07.04 | D34: 문진호(그림바 | E34: 0 | F34: 6096040 | G34: 6월 임대료,관리비,전기료 | H34: 지급수수료
B35: =B5 -> 신한 #672 | C35: 2023.07.04 | D35: 김재욱(법률사 | E35: 0 | F35: 825000 | G35: 6월법률자문료 | H35: 지급수수료
B36: =B5 -> 신한 #672 | C36: 2023.07.07 | D36: DROPBOX SIGN/H | E36: 0 | F36: 239977 | G36: 전자서명서비스 이용료 지급 | H36: 지급수수료
B37: =B5 -> 신한 #672 | C37: 2023.07.10 | D37: 2306국민건강 | E37: 0 | F37: 7330240 | G37: 2306국민건강 | H37: 세금과공과
B38: =B5 -> 신한 #672 | C38: 2023.07.10 | D38: 2306고용보험 | E38: 0 | F38: 1579220 | G38: 2306고용보험 | H38: 세금과공과
B39: =B5 -> 신한 #672 | C39: 2023.07.10 | D39: 2306산재보험 | E39: 0 | F39: 585290 | G39: 2306산재보험 | H39: 세금과공과
B40: =B5 -> 신한 #672 | C40: 2023.07.10 | D40: 주식회사 제로 | E40: 30000000 | F40: 0 | G40: 계좌간 자금 이체 | H40: 보통예금
B41: =B5 -> 신한 #672 | C41: 2023.07.10 | D41: 2306국민연금 | E41: 0 | F41: 6543220 | G41: 2306국민연금 | H41: 세금과공과
B42: =B9 -> WISE USD | C42: 2023.07.10 | D42: 차앤권 법률사무소 | F42: 9331.99 | G42: BVI 제도 법인 설립 용역비 | H42: 지급수수료
B43: =B9 -> WISE USD | C43: 2023.07.10 | D43: wise 송금수수료 | F43: 14.39 | G43: wise 송금수수료 | H43: 지급수수료
B44: =B5 -> 신한 #672 | C44: 2023.07.18 | D44: 상상특허법률사무소 | F44: =4950000 -> 4950000 | G44: 특허 1건 출원 및 등록 비용 | H44: 지급수수료
B45: =B5 -> 신한 #672 | C45: 2023.07.18 | D45: 강진석 | F45: 24800 | G45: 진 개인비용 정산 | H45: 복리후생비
B46: =B5 -> 신한 #672 | C46: 2023.07.18 | D46: 메가존소프트(주) | F46: =76310 -> 76310 | G46: 메가존 구글 계정 추가비용 | H46: 지급수수료
B47: =B5 -> 신한 #672 | C47: 2023.07.18 | D47: 신한은행 | F47: 1000 | G47: 송금 수수료 2건 | H47: 지급수수료
B48: =B9 -> WISE USD | C48: 2023.07.14 | D48: Ngo Xuan Huy | F48: 1800 | G48: 6월 외주 급여(Patrick) | H48: 용역비
B49: =B9 -> WISE USD | C49: 2023.07.14 | D49: Wise | F49: 14.39 | G49: 송금 수수료 | H49: 지급수수료
B50: =B9 -> WISE USD | C50: 2023.07.14 | D50: Postmarkapp.com | F50: 10 | G50: 서비스 이용료 지급 | H50: 지급수수료
B51: =B5 -> 신한 #672 | C51: 2023.07.21 | D51: 세콤 | F51: 110000 | G51: 세콤 비용 지급 | H51: 지급수수료
B52: =B7 -> 하나 #304 | C52: 2023.07.20 | D52: 최유빈 교통비 | F52: 50000 | G52: 최유빈 교통비 | H52: 여비교통비
B53: =B7 -> 하나 #304 | C53: 2023.07.25 | D53: 급여 | F53: 79872522 | G53: 7월 급여 지급 | H53: 급여
B54: =B7 -> 하나 #304 | C54: 2023.07.25 | D54: 하나은행 | F54: 7500 | G54: 7월 급여 지급시 송금 수수료 | H54: 지급수수료
B55: =B7 -> 하나 #304 | C55: 2023.07.25 | D55: 하나카드기업 | F55: 8609191 | G55: 법인카드 대금 지급 | H55: 지급수수료
B56: =B7 -> 하나 #304 | C56: 2023.07.26 | D56: 맥플러스 | F56: 3630000 | G56: 맥북 m1 구입 (포마) | H56: 비품
B57: =B7 -> 하나 #304 | C57: 2023.07.26 | D57: 하나은행 | F57: 500 | G57: 송금 수수료 | H57: 지급수수료
B58: =B5 -> 신한 #672 | C58: 2023.07.25 | D58: KT0540091107 | F58: 55690 | G58: 인터넷, 전화 요금 지급 | H58: 복리후생비
B59: =B5 -> 신한 #672 | C59: 2023.07.25 | D59: 코웨이렌탈07 | F59: 20660 | G59: 공청기 | H59: 복리후생비
B60: =B5 -> 신한 #672 | C60: 2023.07.25 | D60: 코웨이렌탈07 | F60: 20660 | G60: 공청기 | H60: 복리후생비
B61: =B5 -> 신한 #672 | C61: 2023.07.25 | D61: 코웨이렌탈07 | F61: 50250 | G61: 정수기 | H61: 복리후생비
B62: =B5 -> 신한 #672 | C62: 2023.07.25 | D62: 코웨이렌탈07 | F62: 37430 | G62: 비데 | H62: 복리후생비
B63: =B5 -> 신한 #672 | C63: 2023.07.25 | D63: 코웨이렌탈07 | F63: 37430 | G63: 비데 | H63: 복리후생비
B64: =B5 -> 신한 #672 | C64: 2023.07.25 | D64: 삼덕회계법인 | F64: 330000 | G64: 회계 자문료 지급 | H64: 지급수수료
B65: =B5 -> 신한 #672 | C65: 2023.07.25 | D65: 현대카드(주) | F65: 2656516 | G65: 법인카드 대금 지급 | H65: 지급수수료
B66: =B5 -> 신한 #672 | C66: 2023.07.25 | D66: 바디프랜드7 | F66: 98000 | G66: 안마의자 | H66: 복리후생비
B67: =B9 -> WISE USD | C67: 2023.07.19 | D67: Ngo Xuan Huy | E67: 1814.39 | G67: 6월 외주 급여(Patrick)_계좌오류로 인한 반환 | H67: 용역비
B68: =B9 -> WISE USD | C68: 2023.07.21 | D68: Ngo Xuan Huy | F68: 1800 | G68: 6월 외주 급여(Patrick) | H68: 용역비
B69: =B9 -> WISE USD | C69: 2023.07.21 | D69: wise 송금수수료 | F69: 14.39 | G69: wise 송금수수료 | H69: 지급수수료
B70: =B9 -> WISE USD | C70: 2023.07.21 | D70: Nimas Ayu Putri Surasmi Soekidin | F70: 393.75 | G70: 프리랜서 계약 선수금 지급 | H70: 용역비
B71: =B9 -> WISE USD | C71: 2023.07.21 | D71: wise 송금수수료 | F71: 14.39 | G71: wise 송금수수료 | H71: 지급수수료
B72: =B9 -> WISE USD | C72: 2023.07.25 | D72: Traffic Light | F72: 315.21 | G72: 출장비 | H72: 여비교통비
B73: =B5 -> 신한 #672 | C73: 2023.07.28 | D73: ZOOM. US 888-79 | F73: 228766 | G73: zoom 이용료 | H73: 지급수수료
B74: =B5 -> 신한 #672 | C74: 2023.07.31 | D74: 안양신도판매 | F74: 77000 | G74: 복합기 사용료 지급 | H74: 지급수수료
B75: OCBC SGD | C75: 2023.07.03 | D75: OCBC | F75: 10 | G75: 은행 수수료 | H75: 지급수수료
B76: OCBC SGD | C76: 2023.07.31 | D76: OCBC | F76: 15 | G76: 은행 수수료 | H76: 지급수수료

Sheet 23.08월
B1: 자 금 일 보
I2: Currency | J2: KRW | L2: 계정과목 | M2: 설명
B3: ※ 자금현황 | G3: 기준일: 2023.08.31 | I3: USD | J3: =IFERROR(__xludf.DUMMYFUNCTION("GOOGLEFINANCE(""USDKRW"")"),1472.7250000000001) -> 1472.725 | L3: 광고매출 | M3: 타법인 매출
B4: 구 분 | C4: 단위 | D4: 전월잔액 | E4: 수 입 | F4: 지 출 | G4: 기준일 기준 잔액 | I4: SGD | J4: =IFERROR(__xludf.DUMMYFUNCTION("GOOGLEFINANCE(""SGDKRW"")"),1143.885) -> 1143.885 | L4: 급여 | M4: 직원 급여
B5: 신한 #672 | C5: KRW | D5: ='23.07월'!G5 -> 18740535 | E5: =sumif(B22:B158,B5,E22:E160) -> 33490180 | F5: =sumif(B22:B100,B5,F22:F161) -> 26052986 | G5: =D5+E5-F5 -> 26177729 | L5: 미수금 | M5: 돌려 받을 예정인 금액 (ex. 부가세 환급금)
B6: 신한 #543 | C6: USD | D6: ='23.07월'!G6 -> 2.31 | E6: =sumif(B22:B160,B6,E22:E160) -> 0 | F6: =sumif(B22:B100,B6,F22:F160) -> 0 | G6: =D6+E6-F6 -> 2.31 | L6: 보증금 | M6: 보증금 (사무실 임대, 장비 리스 등)
B7: 하나 #304 | C7: KRW | D7: ='23.07월'!G7 -> 2526862 | E7: =sumif(B22:B160,B7,E22:E160) -> 130438000 | F7: =sumif(B22:B100,B7,F22:F160) -> 125786524 | G7: =D7+E7-F7 -> 7178338 | L7: 보통예금 | M7: 예금간 이체
B8: 하나 #138 | C8: USD | D8: ='23.07월'!G8 -> 0.12 | E8: =sumif(B22:B160,B8,E22:E160) -> 453582 | F8: =sumif(B22:B100,B8,F22:F160) -> 100000 | G8: =D8+E8-F8 -> 353582.12 | L8: 복리후생비 | M8: 회식, 식대
B9: WISE USD | C9: USD | D9: ='23.07월'!G9 -> 198279.27 | E9: =sumif(B22:B100,B9,E22:E160) -> 0 | F9: =sumif(B22:B100,B9,F22:F160) -> 139920.75 | G9: =D9+E9-F9 -> 58358.52 | L9: 비품 | M9: 가구, 가전등 개당 단가 150만원이 넘는 용품
B10: WISE SGD | C10: SGD | D10: ='23.07월'!G10 -> 0 | E10: =sumif(B22:B158,B10,E22:E100) -> 0 | F10: =sumif(B22:B100,B10,F22:F160) -> 0 | G10: =D10+E10-F10 -> 0 | L10: 사무용품비 | M10: 비품, 소모품비를 제외한 업무용 사무용품 구입
B11: WISE KRW | C11: KRW | D11: ='23.07월'!G11 -> 0 | E11: =sumif(B22:B160,B11,E22:E160) -> 0 | F11: =sumif(B22:B100,B11,F22:F160) -> 0 | G11: =D11+E11-F11 -> 0 | L11: 서비스용역매출 | M11: 매출
B12: OCBC USD | C12: USD | D12: ='23.07월'!G12 -> 386834.73 | E12: =sumif(B22:B103,B12,E22:E103) -> 0 | F12: =sumif(B22:B99,B12,F22:F161) -> 352032 | G12: =D12+E12-F12 -> 34802.73 | L12: 세금과공과 | M12: 세금 납부시
B13: OCBC SGD | C13: SGD | D13: ='23.07월'!G13 -> 705 | E13: =sumif(B22:B160,B13,E22:E161) -> 0 | F13: =sumif(B22:B99,B13,F22:F161) -> 10 | G13: =D13+E13-F13 -> 695 | L13: 소모품비 | M13: 비품(150만원)으로 잡기에는 금액이 작은 비품
L14: 여비교통비 | M14: 출장, 대중교통, 대리운전
B15: KRW 합 계 | D15: =D5+D7+D11 -> 21267397 | E15: =E5+E7+E11 -> 163928180 | F15: =F5+F7+F11 -> 151839510 | G15: =G5+G11+G7 -> 33356067 | H15: =G15 -> 33356067 | I15: =D15 -> 21267397 | L15: 용역비 | M15: 외주용역비
B16: USD 합 계 | D16: =D6+D8+D9+D12 -> 585116.43 | E16: =E6+E8+E9+E12 -> 453582 | F16: =F6+F8+F9+F12 -> 591952.75 | G16: =G9+G6+G8+G12 -> 446745.68 | H16: =rounddown(G16*$J$3,0) -> 657933531 | I16: =rounddown(D16*$J$3,0) -> 861715594 | L16: 접대비 | M16: 외부 미팅
B17: SGD 합 계 | D17: =D10+D13 -> 705 | E17: =E10+E13 -> 0 | F17: =F10+F13 -> 10 | G17: =G10+G13 -> 695 | H17: =rounddown(G17*$J$4,0) -> 795000 | I17: =rounddown(D17*$J$4,0) -> 806438 | L17: 지급수수료 | M17: sms 수수료, 송금 수수료, 일반적으로 발생되는 모든 비용
H18: =SUM(H15:H17) -> 692084598 | I18: =SUM(I15:I17) -> 883789429 | L18: 이자수익 | M18: 은행이자
H19: =H18-I18 -> -191704831 | L19: 통신비 | M19: 등기, 퀵 사용비
B20: ※ 세부내역 | L20: 마케팅비 | M20: PR 기사등 마케팅 비용
B21: 구 분 | C21: 날 짜 | D21: 은 행 적 요 | E21: 수입 | F21: 지출 | G21: 상세메모 | H21: 계정과목 | L21: 대여금 | M21: 싱가폴 -> 한국 지사 송금
B22: =B9 -> WISE USD | C22: 2023.08.01 | D22: Milestone Business Group | F22: =10422.68+159.97 -> 10582.65 | G22: Chris 8월 급여+ 개인경비 | H22: 급여 | L22: 출장비 | M22: 출장여비
B23: =B9 -> WISE USD | C23: 2023.08.01 | D23: wise | F23: 0.39 | G23: Chris 8월 급여+ 개인경비 송금 수수료 | H23: 지급수수료 | L23: 투자자산 | M23: 투자
B24: =B9 -> WISE USD | C24: 2023.08.01 | D24: Entra Law LLC | F24: 5294.98 | G24: 라그몬 백서 법률 자문료 | H24: 지급수수료
B25: =B9 -> WISE USD | C25: 2023.08.01 | D25: wise | F25: 30.74 | G25: 송금 & 환전 수수료 | H25: 지급수수료
B26: =B5 -> 신한 #672 | C26: 2023.08.01 | D26: 그림바우빌딩 | F26: 6243270 | G26: 7월 임대료,관리비,전기료 | H26: 지급수수료
B27: =B5 -> 신한 #672 | C27: 2023.08.01 | D27: 비앤케이 | F27: 825000 | G27: 7월 법률자문료 | H27: 지급수수료
B28: =B5 -> 신한 #672 | C28: 2023.08.01 | D28: 메가존소프트(주) | F28: 67082 | G28: 메가존 구글 계정 추가비용 | H28: 지급수수료
B29: =B5 -> 신한 #672 | C29: 2023.08.01 | D29: 신한은행 | F29: 1000 | G29: 송금 수수료 | H29: 지급수수료
B30: =B9 -> WISE USD | C30: 2023.08.07 | D30: ZERO X AND PTE. LTD. | F30: 100000 | G30: 계좌간 자금이체 | H30: 보통예금
B31: =B9 -> WISE USD | C31: 2023.08.07 | D31: wise 송금수수료 | F31: 14.39 | G31: wise 송금수수료 | H31: 지급수수료
B32: =B9 -> WISE USD | C32: 2023.08.07 | D32: Neicon Inc. | F32: 18140.45 | G32: 게임 도시 마케팅 비용 지급 | H32: 마케팅비
B33: =B9 -> WISE USD | C33: 2023.08.07 | D33: wise | F33: 14.39 | G33: 송금수수료 지급 | H33: 지급수수료
B34: =B9 -> WISE USD | C34: 2023.08.08 | D34: Elenkei L&k | F34: 458.58 | G34: 접대비(600,000 KRW) | H34: 접대비
B35: =B8 -> 하나 #138 | C35: 2023.08.09 | D35: ZERO X AND PTE. LTD. | E35: 100000 | G35: 계좌간 자금이체 | H35: 보통예금
B36: =B8 -> 하나 #138 | C36: 2023.08.10 | D36: 주식회사 제로엑스앤드코리아 | F36: 100000 | G36: 환전 | H36: 보통예금
B37: =B7 -> 하나 #304 | C37: 2023.08.10 | D37: 주식회사 제로엑스앤드코리아 | E37: 130438000 | G37: 환전 | H37: 보통예금
B38: =B7 -> 하나 #304 | C38: 2023.08.10 | D38: 국세청 | F38: 6863490 | G38: 7월 근로 소득세 | H38: 세금과공과
B39: =B7 -> 하나 #304 | C39: 2023.08.10 | D39: 국세청 | F39: 4800 | G39: 7월 사업 소득세 | H39: 세금과공과
B40: =B7 -> 하나 #304 | C40: 2023.08.10 | D40: 강남구청 | F40: 686750 | G40: 7월 지방 소득세 | H40: 세금과공과
B41: =B7 -> 하나 #304 | C41: 2023.08.10 | D41: 강남구청 | F41: 62500 | G41: 2023년 8월 사업소분 주민세 | H41: 세금과공과
B42: =B7 -> 하나 #304 | C42: 2023.08.10 | D42: 주식회사 제로엑스앤드코리아 | F42: 20000000 | G42: 계좌간 자금 이체 | H42: 보통예금
B43: =B7 -> 하나 #304 | C43: 2023.08.10 | D43: 하나은행 | F43: 500 | G43: 송금 수수료 | H43: 지급수수료
B44: =B5 -> 신한 #672 | C44: 2023.08.10 | D44: 2307국민건강 | F44: 6853840 | G44: 2307국민건강 | H44: 세금과공과
B45: =B5 -> 신한 #672 | C45: 2023.08.10 | D45: 2307산재보험 | F45: 545450 | G45: 2307산재보험 | H45: 세금과공과
B46: =B5 -> 신한 #672 | C46: 2023.08.10 | D46: 2307고용보험 | F46: 1471770 | G46: 2307고용보험 | H46: 세금과공과
B47: =B5 -> 신한 #672 | C47: 2023.08.10 | D47: 주식회사 제로 | E47: 20000000 | G47: 계좌간 자금 이체 | H47: 보통예금
B48: =B5 -> 신한 #672 | C48: 2023.08.10 | D48: 2307국민연금 | F48: 6753820 | G48: 2307국민연금 | H48: 세금과공과
B49: =B5 -> 신한 #672 | C49: 2023.08.21 | D49: 세콤(N5905012) | F49: 110000 | G49: 세콤(N5905012) | H49: 지급수수료
B50: =B9 -> WISE USD | C50: 2023.08.11 | D50: Chris | F50: 1757.64 | G50: 개인경비 | H50: 복리후생비
B51: =B9 -> WISE USD | C51: 2023.08.11 | D51: Wise | F51: 0.39 | G51: 송금 수수료 | H51: 지급수수료
B52: =B9 -> WISE USD | C52: 2023.08.11 | D52: 주식회사 제로엑스앤드코리아 | F52: 3597 | G52: 해튼길드 투자금용 계좌이체 | H52: 보통예금
B53: =B9 -> WISE USD | C53: 2023.08.11 | D53: Wise | F53: 14.39 | G53: 송금 수수료 | H53: 지급수수료
B54: =B8 -> 하나 #138 | C54: 2023.08.14 | D54: 주식회사 제로엑스앤드코리아 | E54: 3597 | G54: 해튼길드 투자금용 계좌이체 | H54: 보통예금
B55: =B7 -> 하나 #304 | C55: 2023.08.14 | D55: DO KHANH TIEN | F55: 4834285 | G55: 해튼길드 투자금 | H55: 투자자산
B56: =B7 -> 하나 #304 | C56: 2023.08.14 | D56: 하나은행 | F56: 45600 | G56: 송금 수수료 | H56: 지급수수료
B57: =B12 -> OCBC USD | C57: 2023.08.21 | D57: 주식회사 제로엑스앤드코리아 | F57: 100000 | G57: 계좌간 자금이체 | H57: 보통예금
B58: =B12 -> OCBC USD | C58: 2023.08.21 | D58: OCBC | F58: 43 | G58: 은행 수수료 | H58: 지급수수료
B59: =B12 -> OCBC USD | C59: 2023.08.21 | D59: OCBC | F59: 15 | G59: 은행 수수료 | H59: 지급수수료
B60: =B8 -> 하나 #138 | C60: 2023.08.21 | D60: ZERO X AND PTE. LTD. | E60: 99995 | G60: 계좌간 자금이체 | H60: 보통예금
B61: =B12 -> OCBC USD | C61: 2023.08.22 | D61: 주식회사 제로엑스앤드코리아 | F61: 150000 | G61: 계좌간 자금이체 | H61: 보통예금
B62: =B12 -> OCBC USD | C62: 2023.08.22 | D62: OCBC | F62: 43 | G62: 은행 수수료 | H62: 지급수수료
B63: =B12 -> OCBC USD | C63: 2023.08.22 | D63: OCBC | F63: 15 | G63: 은행 수수료 | H63: 지급수수료
B64: =B8 -> 하나 #138 | C64: 2023.08.22 | D64: ZERO X AND PTE. LTD. | E64: 149995 | G64: 계좌간 자금이체 | H64: 보통예금
B65: =B5 -> 신한 #672 | C65: 2023.08.25 | D65: 강남세무서 | E65: 13490180 | G65: 부가세 환급 | H65: 미수금
B66: =B5 -> 신한 #672 | C66: 2023.08.25 | D66: KT0540091108 | F66: 55740 | G66: 인터넷, 전화 요금 지급 | H66: 복리후생비
B67: =B5 -> 신한 #672 | C67: 2023.08.25 | D67: 삼덕회계법인 | F67: 330000 | G67: 회계 자문료 지급 | H67: 지급수수료
B68: =B5 -> 신한 #672 | C68: 2023.08.25 | D68: 코웨이렌탈08 | F68: 20660 | G68: 비데 | H68: 복리후생비
B69: =B5 -> 신한 #672 | C69: 2023.08.25 | D69: 코웨이렌탈08 | F69: 50250 | G69: 정수기 | H69: 복리후생비
B70: =B5 -> 신한 #672 | C70: 2023.08.25 | D70: 코웨이렌탈08 | F70: 37430 | G70: 공청기 | H70: 복리후생비
B71: =B5 -> 신한 #672 | C71: 2023.08.25 | D71: 코웨이렌탈08 | F71: 20660 | G71: 비데 | H71: 복리후생비
B72: =B5 -> 신한 #672 | C72: 2023.08.25 | D72: 코웨이렌탈08 | F72: 37430 | G72: 공청기 | H72: 복리후생비
B73: =B5 -> 신한 #672 | C73: 2023.08.25 | D73: 현대카드(주) | F73: 2235084 | G73: 법인카드 대금 지급 | H73: 지급수수료
B74: =B5 -> 신한 #672 | C74: 2023.08.25 | D74: 바디프랜드8 | F74: 98000 | G74: 안마의자 | H74: 복리후생비
B75: =B7 -> 하나 #304 | C75: 2023.08.25 | D75: 하나카드 | F75: 10275023 | G75: 법인카드 대금 지급 | H75: 지급수수료
B76: =B7 -> 하나 #304 | C76: 2023.08.25 | D76: 급여 | F76: 80990016 | G76: 8월 급여 지급 | H76: 급여
B77: =B7 -> 하나 #304 | C77: 2023.08.25 | D77: 하나은행 | F77: 7500 | G77: 8월 급여 지급시 송금 수수료 | H77: 지급수수료
B78: =B7 -> 하나 #304 | C78: 2023.08.25 | D78: 급여 | F78: 2016060 | G78: 8월 급여 지급 (poma) | H78: 급여
B79: =B12 -> OCBC USD | C79: 2023.08.25 | D79: 주식회사 제로엑스앤드코리아 | F79: 100000 | G79: 계좌간 자금이체 | H79: 보통예금
B80: =B12 -> OCBC USD | C80: 2023.08.25 | D80: OCBC | F80: 43 | G80: 은행 수수료 | H80: 지급수수료
B81: =B12 -> OCBC USD | C81: 2023.08.25 | D81: OCBC | F81: 15 | G81: 은행 수수료 | H81: 지급수수료
B82: =B12 -> OCBC USD | C82: 2023.08.25 | D82: Patrick | F82: 1800 | G82: Patrick 7월 스마트컨트랙트 개발 용역비 | H82: 용역비
B83: =B12 -> OCBC USD | C83: 2023.08.25 | D83: OCBC | F83: 43 | G83: 은행 수수료 | H83: 지급수수료
B84: =B12 -> OCBC USD | C84: 2023.08.25 | D84: OCBC | F84: 15 | G84: 은행 수수료 | H84: 지급수수료
B85: =B8 -> 하나 #138 | C85: 2023.08.29 | D85: ZERO X AND PTE. LTD. | E85: 99995 | G85: 계좌간 자금이체 | H85: 보통예금
B86: =B5 -> 신한 #672 | C86: 2023.08.31 | D86: 김소연법무사 | F86: 219500 | G86: KYC 공증료 지급 (알마,바트) | H86: 지급수수료
B87: =B5 -> 신한 #672 | C87: 2023.08.31 | D87: 안양신도판매 | F87: 77000 | G87: 복합기 사용료 지급 | H87: 지급수수료
B88: =B9 -> WISE USD | C88: 2023.08.16 | D88: Namecheap.com | F88: 14.76 | G88: 서비스 이용료 지급 | H88: 지급수수료
B89: =B13 -> OCBC SGD | C89: 2023.08.31 | D89: OCBC | F89: 10 | G89: 은행 수수료 | H89: 지급수수료

Sheet 23.09월
B1: 자 금 일 보
I2: Currency | J2: KRW | L2: 계정과목 | M2: 설명
B3: ※ 자금현황 | G3: 기준일: 2023.09.25 | I3: USD | J3: =IFERROR(__xludf.DUMMYFUNCTION("GOOGLEFINANCE(""USDKRW"")"),1472.7250000000001) -> 1472.725 | L3: 광고매출 | M3: 타법인 매출
B4: 구 분 | C4: 단위 | D4: 전월잔액 | E4: 수 입 | F4: 지 출 | G4: 기준일 기준 잔액 | I4: SGD | J4: =IFERROR(__xludf.DUMMYFUNCTION("GOOGLEFINANCE(""SGDKRW"")"),1143.885) -> 1143.885 | L4: 급여 | M4: 직원 급여
B5: 신한 #672 | C5: KRW | D5: ='23.08월'!G5 -> 26177729 | E5: =sumif(B22:B141,B5,E22:E143) -> 20005469 | F5: =sumif(B22:B83,B5,F22:F144) -> 34158054 | G5: =D5+E5-F5 -> 12025144 | L5: 미수금 | M5: 돌려 받을 예정인 금액 (ex. 부가세 환급금)
B6: 신한 #543 | C6: USD | D6: ='23.08월'!G6 -> 2.31 | E6: =sumif(B22:B143,B6,E22:E143) -> 0 | F6: =sumif(B22:B83,B6,F22:F143) -> 0 | G6: =D6+E6-F6 -> 2.31 | L6: 보증금 | M6: 보증금 (사무실 임대, 장비 리스 등)
B7: 하나 #304 | C7: KRW | D7: ='23.08월'!G7 -> 7178338 | E7: =sumif(B22:B143,B7,E22:E143) -> 132210783 | F7: =sumif(B22:B83,B7,F22:F143) -> 118639920 | G7: =D7+E7-F7 -> 20749201 | L7: 보통예금 | M7: 예금간 이체
B8: 하나 #138 | C8: USD | D8: ='23.08월'!G8 -> 353582.12 | E8: =sumif(B22:B143,B8,E22:E143) -> 2.16 | F8: =sumif(B22:B83,B8,F22:F143) -> 100000 | G8: =D8+E8-F8 -> 253584.28 | L8: 복리후생비 | M8: 회식, 식대
B9: WISE USD | C9: USD | D9: ='23.08월'!G9 -> 58358.52 | E9: =sumif(B22:B83,B9,E22:E143) -> 0 | F9: =sumif(B22:B83,B9,F22:F143) -> 10 | G9: =D9+E9-F9 -> 58348.52 | L9: 비품 | M9: 가구, 가전등 개당 단가 150만원이 넘는 용품
B10: WISE SGD | C10: SGD | D10: ='23.08월'!G10 -> 0 | E10: =sumif(B22:B141,B10,E22:E83) -> 0 | F10: =sumif(B22:B83,B10,F22:F143) -> 0 | G10: =D10+E10-F10 -> 0 | L10: 사무용품비 | M10: 비품, 소모품비를 제외한 업무용 사무용품 구입
B11: WISE KRW | C11: KRW | D11: ='23.08월'!G11 -> 0 | E11: =sumif(B22:B143,B11,E22:E143) -> 0 | F11: =sumif(B22:B83,B11,F22:F143) -> 0 | G11: =D11+E11-F11 -> 0 | L11: 서비스용역매출 | M11: 매출
B12: OCBC USD | C12: USD | D12: ='23.08월'!G12 -> 34802.73 | E12: =sumif(B22:B86,B12,E22:E86) -> 0 | F12: =sumif(B22:B82,B12,F22:F144) -> 21019.26 | G12: =D12+E12-F12 -> 13783.47 | L12: 세금과공과 | M12: 세금 납부시
B13: OCBC SGD | C13: SGD | D13: ='23.08월'!G13 -> 695 | E13: =sumif(B22:B143,B13,E22:E144) -> 0 | F13: =sumif(B22:B82,B13,F22:F144) -> 40 | G13: =D13+E13-F13 -> 655 | L13: 소모품비 | M13: 비품(150만원)으로 잡기에는 금액이 작은 비품
H14: 기준일 기준 잔액 | I14: 전월잔액 | L14: 여비교통비 | M14: 출장, 대중교통, 대리운전
B15: KRW 합 계 | D15: =D5+D7+D11 -> 33356067 | E15: =E5+E7+E11 -> 152216252 | F15: =F5+F7+F11 -> 152797974 | G15: =G5+G11+G7 -> 32774345 | H15: =G15 -> 32774345 | I15: =D15 -> 33356067 | L15: 용역비 | M15: 외주용역비
B16: USD 합 계 | D16: =D6+D8+D9+D12 -> 446745.68 | E16: =E6+E8+E9+E12 -> 2.16 | F16: =F6+F8+F9+F12 -> 121029.26 | G16: =G9+G6+G8+G12 -> 325718.58 | H16: =rounddown(G16*$J$3,0) -> 479693895 | I16: =rounddown(D16*$J$3,0) -> 657933531 | L16: 접대비 | M16: 외부 미팅
B17: SGD 합 계 | D17: =D10+D13 -> 695 | E17: =E10+E13 -> 0 | F17: =F10+F13 -> 40 | G17: =G10+G13 -> 655 | H17: =rounddown(G17*$J$4,0) -> 749244 | I17: =rounddown(D17*$J$4,0) -> 795000 | L17: 지급수수료 | M17: sms 수수료, 송금 수수료, 일반적으로 발생되는 모든 비용
H18: =SUM(H15:H17) -> 513217484 | I18: =SUM(I15:I17) -> 692084598 | L18: 이자수익 | M18: 은행이자
H19: =H18-I18 -> -178867114 | L19: 통신비 | M19: 등기, 퀵 사용비
B20: ※ 세부내역 | L20: 마케팅비 | M20: PR 기사등 마케팅 비용
B21: 구 분 | C21: 날 짜 | D21: 은 행 적 요 | E21: 수입 | F21: 지출 | G21: 상세메모 | H21: 계정과목 | L21: 대여금 | M21: 싱가폴 -> 한국 지사 송금
B22: =B12 -> OCBC USD | C22: 2023.09.01 | D22: Milestone Business Group | F22: 10480.58 | G22: Chris 9월 급여+ 개인경비 | H22: 급여 | L22: 출장비 | M22: 출장여비
B23: =B12 -> OCBC USD | C23: 2023.09.01 | D23: OCBC BANK | F23: 43 | G23: 은행 수수료 | H23: 지급수수료 | L23: 투자자산 | M23: 투자
B24: =B12 -> OCBC USD | C24: 2023.09.01 | D24: OCBC BANK | F24: 15 | G24: 은행 수수료 | H24: 지급수수료
B25: =B13 -> OCBC SGD | C25: 2023.09.01 | D25: OCBC BANK | F25: 15 | G25: 은행 수수료 | H25: 지급수수료
B26: =B13 -> OCBC SGD | C26: 2023.09.04 | D26: OCBC BANK | F26: 10 | G26: 은행 수수료 | H26: 지급수수료
B27: =B5 -> 신한 #672 | C27: 2023.09.04 | D27: 그림바우빌딩 | F27: 6364600 | G27: 7월 임대료,관리비,전기료 | H27: 지급수수료
B28: =B5 -> 신한 #672 | C28: 2023.09.04 | D28: 신한은행 | F28: 500 | G28: 송금수수료 | H28: 지급수수료
B29: =B5 -> 신한 #672 | C29: 2023.09.04 | D29: 비앤케이 | F29: 825000 | G29: 7월 법률자문료 | H29: 지급수수료
B30: =B7 -> 하나 #304 | C30: 2023.09.11 | D30: 주식회사 제로엑스앤드코리아 | E30: 132200000 | G30: 환전 | H30: 보통예금
B31: =B7 -> 하나 #304 | C31: 2023.09.11 | D31: 국고_주식회사 제로 | F31: 176840 | G31: 8월 기타 소득세 | H31: 세금과공과
B32: =B7 -> 하나 #304 | C32: 2023.09.11 | D32: 서울지방제로엑 | F32: 708470 | G32: 8월 지방 소득세 | H32: 세금과공과
B33: =B7 -> 하나 #304 | C33: 2023.09.11 | D33: 전준영 | F33: 990500 | G33: 개인 경비 지급 | H33: 복리후생비
B34: =B7 -> 하나 #304 | C34: 2023.09.11 | D34: 최고은 | F34: 14500 | G34: 개인 경비 지급 | H34: 복리후생비
B35: =B7 -> 하나 #304 | C35: 2023.09.11 | D35: (주)제로엑스앤드코 | F35: 20000500 | G35: 계좌간 자금 이체 | H35: 보통예금
B36: =B7 -> 하나 #304 | C36: 2023.09.11 | D36: 국고_주식회사 제로 | F36: 6908640 | G36: 8월 근로 소득세 | H36: 세금과공과
B37: =B8 -> 하나 #138 | C37: 2023.09.11 | D37: 주식회사 제로엑스앤드코리아 | F37: 100000 | G37: 환전 | H37: 보통예금
B38: =B5 -> 신한 #672 | C38: 2023.09.11 | D38: 2308국민건강 | F38: 7017600 | G38: 2308국민건강 | H38: 세금과공과
B39: =B5 -> 신한 #672 | C39: 2023.09.11 | D39: 2308국민연금 | F39: 6962440 | G39: 2308국민연금 | H39: 세금과공과
B40: =B5 -> 신한 #672 | C40: 2023.09.11 | D40: 2308고용보험 | F40: 1542260 | G40: 2308고용보험 | H40: 세금과공과
B41: =B5 -> 신한 #672 | C41: 2023.09.11 | D41: 2308산재보험 | F41: 587050 | G41: 2308산재보험 | H41: 세금과공과
B42: =B5 -> 신한 #672 | C42: 2023.09.11 | D42: 주식회사 제로엑스앤드코리아 | E42: 20000000 | G42: 계좌간 자금 이체 | H42: 보통예금
B43: =B5 -> 신한 #672 | C43: 2023.09.16 | D43: 예금이자 | E43: 5469 | G43: 예금 이자 | H43: 이자수익
B44: =B7 -> 하나 #304 | C44: 2023.09.16 | D44: 예금이자 | E44: 10783 | G44: 예금 이자 | H44: 이자수익
B45: =B8 -> 하나 #138 | C45: 2023.09.16 | D45: 예금이자 | E45: 2.16 | G45: 예금 이자 | H45: 이자수익
B46: =B12 -> OCBC USD | C46: 2023.09.20 | D46: Milestone Business Group | F46: 10422.68 | G46: Chris 10월 급여 | H46: 급여
B47: =B12 -> OCBC USD | C47: 2023.09.20 | D47: OCBC BANK | F47: 43 | G47: Chris 10월 급여 송금 수수료 | H47: 지급수수료
B48: =B12 -> OCBC USD | C48: 2023.09.20 | D48: OCBC BANK | F48: 15 | G48: Chris 10월 급여 송금 수수료 | H48: 지급수수료
B49: =B13 -> OCBC SGD | C49: 2023.09.30 | D49: OCBC BANK | F49: 15 | G49: 은행 수수료 | H49: 지급수수료
B50: =B5 -> 신한 #672 | C50: 2023.09.18 | D50: (주)그라운드케이 | F50: 1287000 | G50: VIP 수송 서비스 | H50: 마케팅비
B51: =B5 -> 신한 #672 | C51: 2023.09.20 | D51: 현대법인카드 | F51: 970000 | G51: 추석 선물 구입 선결제 | H51: 복리후생비
B52: =B5 -> 신한 #672 | C52: 2023.09.21 | D52: 세콤(N5905012) | F52: 110000 | G52: 세콤(N5905012) | H52: 지급수수료
B53: =B7 -> 하나 #304 | C53: 2023.09.25 | D53: 급여 | F53: 80990016 | G53: 9월 급여 지급 | H53: 급여
B54: =B7 -> 하나 #304 | C54: 2023.09.25 | D54: 하나은행 | F54: 7500 | G54: 9월 급여 지급시 송금 수수료 | H54: 지급수수료
B55: =B7 -> 하나 #304 | C55: 2023.09.25 | D55: 급여 | F55: 2016060 | G55: 9월 급여 지급 (poma) | H55: 급여
B56: =B7 -> 하나 #304 | C56: 2023.09.25 | D56: 하나카드 | F56: 6826894 | G56: 법인카드 대금 지급 | H56: 지급수수료
B57: =B5 -> 신한 #672 | C57: 2023.09.25 | D57: KT0540091108 | F57: 55770 | G57: 인터넷, 전화 요금 지급 | H57: 복리후생비
B58: =B5 -> 신한 #672 | C58: 2023.09.25 | D58: 삼덕회계법인 | F58: 330000 | G58: 회계 자문료 지급 | H58: 지급수수료
B59: =B5 -> 신한 #672 | C59: 2023.09.25 | D59: 코웨이렌탈08 | F59: 20660 | G59: 비데 | H59: 복리후생비
B60: =B5 -> 신한 #672 | C60: 2023.09.25 | D60: 코웨이렌탈08 | F60: 50250 | G60: 정수기 | H60: 복리후생비
B61: =B5 -> 신한 #672 | C61: 2023.09.25 | D61: 코웨이렌탈08 | F61: 37430 | G61: 공청기 | H61: 복리후생비
B62: =B5 -> 신한 #672 | C62: 2023.09.25 | D62: 코웨이렌탈08 | F62: 20660 | G62: 비데 | H62: 복리후생비
B63: =B5 -> 신한 #672 | C63: 2023.09.25 | D63: 코웨이렌탈08 | F63: 37430 | G63: 공청기 | H63: 복리후생비
B64: =B5 -> 신한 #672 | C64: 2023.09.25 | D64: 현대카드(주) | F64: 3717232 | G64: 법인카드 대금 지급 | H64: 지급수수료
B65: =B5 -> 신한 #672 | C65: 2023.09.25 | D65: 바디프랜드8 | F65: 98000 | G65: 안마의자 | H65: 복리후생비
B66: =B9 -> WISE USD | C66: 2023.09.22 | D66: Postmarkapp.com | F66: 10 | G66: 서비스 이용료 지급 | H66: 지급수수료
B67: =B5 -> 신한 #672 | C67: 2023.09.26 | D67: 현대카드(주) | F67: 1624800 | G67: 법인카드 대금 지급 | H67: 지급수수료
B68: =B5 -> 신한 #672 | C68: 2023.09.26 | D68: 현대카드(주) | F68: 2422372 | G68: 법인카드 대금 지급 | H68: 지급수수료
B69: =B5 -> 신한 #672 | C69: 2023.09.27 | D69: 안양신도판매 | F69: 77000 | G69: 복합기 사용료 지급 | H69: 지급수수료

Sheet 23.10월
B1: 자 금 일 보
I2: Currency | J2: KRW | L2: 계정과목 | M2: 설명
B3: ※ 자금현황 | G3: 기준일: 2023.10.31 | I3: USD | J3: =IFERROR(__xludf.DUMMYFUNCTION("GOOGLEFINANCE(""USDKRW"")"),1472.7250000000001) -> 1472.725 | L3: 광고매출 | M3: 타법인 매출
B4: 구 분 | C4: 단위 | D4: 전월잔액 | E4: 수 입 | F4: 지 출 | G4: 기준일 기준 잔액 | I4: SGD | J4: =IFERROR(__xludf.DUMMYFUNCTION("GOOGLEFINANCE(""SGDKRW"")"),1143.885) -> 1143.885 | L4: 급여 | M4: 직원 급여
B5: 신한 #672 | C5: KRW | D5: ='23.09월'!G5 -> 12025144 | E5: =sumif(B22:B135,B5,E22:E137) -> 20000000 | F5: =sumif(B22:B77,B5,F22:F138) -> 24097860 | G5: =D5+E5-F5 -> 7927284 | L5: 미수금 | M5: 돌려 받을 예정인 금액 (ex. 부가세 환급금)
B6: 신한 #543 | C6: USD | D6: ='23.09월'!G6 -> 2.31 | E6: =sumif(B22:B137,B6,E22:E137) -> 0 | F6: =sumif(B22:B77,B6,F22:F137) -> 0 | G6: =D6+E6-F6 -> 2.31 | L6: 보증금 | M6: 보증금 (사무실 임대, 장비 리스 등)
B7: 하나 #304 | C7: KRW | D7: ='23.09월'!G7 -> 20749201 | E7: =sumif(B22:B137,B7,E22:E137) -> 133311000 | F7: =sumif(B22:B77,B7,F22:F137) -> 121836105 | G7: =D7+E7-F7 -> 32224096 | L7: 보통예금 | M7: 예금간 이체
B8: 하나 #138 | C8: USD | D8: ='23.09월'!G8 -> 253584.28 | E8: =sumif(B22:B137,B8,E22:E137) -> 0 | F8: =sumif(B22:B77,B8,F22:F137) -> 100000 | G8: =D8+E8-F8 -> 153584.28 | L8: 복리후생비 | M8: 회식, 식대
B9: WISE USD | C9: USD | D9: ='23.09월'!G9 -> 58348.52 | E9: =sumif(B22:B77,B9,E22:E137) -> 0.02 | F9: =sumif(B22:B77,B9,F22:F137) -> 13348.23 | G9: =D9+E9-F9 -> 45000.31 | L9: 비품 | M9: 가구, 가전등 개당 단가 150만원이 넘는 용품
B10: WISE SGD | C10: SGD | D10: ='23.09월'!G10 -> 0 | E10: =sumif(B22:B135,B10,E22:E77) -> 0 | F10: =sumif(B22:B77,B10,F22:F137) -> 0 | G10: =D10+E10-F10 -> 0 | L10: 사무용품비 | M10: 비품, 소모품비를 제외한 업무용 사무용품 구입
B11: WISE KRW | C11: KRW | D11: ='23.09월'!G11 -> 0 | E11: =sumif(B22:B137,B11,E22:E137) -> 2300 | F11: =sumif(B22:B77,B11,F22:F137) -> 0 | G11: =D11+E11-F11 -> 2300 | L11: 서비스용역매출 | M11: 매출
B12: OCBC USD | C12: USD | D12: ='23.09월'!G12 -> 13783.47 | E12: =sumif(B22:B80,B12,E22:E80) -> 0 | F12: =sumif(B22:B76,B12,F22:F138) -> 2798.82 | G12: =D12+E12-F12 -> 10984.65 | L12: 세금과공과 | M12: 세금 납부시
B13: OCBC SGD | C13: SGD | D13: ='23.09월'!G13 -> 655 | E13: =sumif(B22:B137,B13,E22:E138) -> 0 | F13: =sumif(B22:B76,B13,F22:F138) -> 25 | G13: =D13+E13-F13 -> 630 | L13: 소모품비 | M13: 비품(150만원)으로 잡기에는 금액이 작은 비품
H14: 기준일 기준 잔액 | I14: 전월잔액 | L14: 여비교통비 | M14: 출장, 대중교통, 대리운전
B15: KRW 합 계 | D15: =D5+D7+D11 -> 32774345 | E15: =E5+E7+E11 -> 153313300 | F15: =F5+F7+F11 -> 145933965 | G15: =G5+G11+G7 -> 40153680 | H15: =G15 -> 40153680 | I15: =D15 -> 32774345 | L15: 용역비 | M15: 외주용역비
B16: USD 합 계 | D16: =D6+D8+D9+D12 -> 325718.58 | E16: =E6+E8+E9+E12 -> 0.02 | F16: =F6+F8+F9+F12 -> 116147.05 | G16: =G9+G6+G8+G12 -> 209571.55 | H16: =rounddown(G16*$J$3,0) -> 308641260 | I16: =rounddown(D16*$J$3,0) -> 479693895 | L16: 접대비 | M16: 외부 미팅
B17: SGD 합 계 | D17: =D10+D13 -> 655 | E17: =E10+E13 -> 0 | F17: =F10+F13 -> 25 | G17: =G10+G13 -> 630 | H17: =rounddown(G17*$J$4,0) -> 720647 | I17: =rounddown(D17*$J$4,0) -> 749244 | L17: 지급수수료 | M17: sms 수수료, 송금 수수료, 일반적으로 발생되는 모든 비용
H18: =SUM(H15:H17) -> 349515587 | I18: =SUM(I15:I17) -> 513217484 | L18: 이자수익 | M18: 은행이자
H19: =H18-I18 -> -163701897 | L19: 통신비 | M19: 등기, 퀵 사용비
B20: ※ 세부내역 | L20: 마케팅비 | M20: PR 기사등 마케팅 비용
B21: 구 분 | C21: 날 짜 | D21: 은 행 적 요 | E21: 수입 | F21: 지출 | G21: 상세메모 | H21: 계정과목 | L21: 대여금 | M21: 싱가폴 -> 한국 지사 송금
B22: =B5 -> 신한 #672 | C22: 2023.10.04 | D22: 그림바우빌딩 | F22: 6357450 | G22: 9월 임대료,관리비,전기료 | H22: 지급수수료 | L22: 출장비 | M22: 출장여비
B23: =B5 -> 신한 #672 | C23: 2023.10.04 | D23: 신한은행 | F23: 500 | G23: 송금수수료 | H23: 지급수수료 | L23: 투자자산 | M23: 투자
B24: =B5 -> 신한 #672 | C24: 2023.10.04 | D24: 비앤케이 | F24: 825000 | G24: 9월 법률자문료 | H24: 지급수수료
B25: =B9 -> WISE USD | C25: 2023.10.03 | D25: WISE | F25: 10 | G25: 은행 수수료 | H25: 지급수수료
B26: =B5 -> 신한 #672 | C26: 2023.10.10 | D26: 2309고용보험 | F26: 1519280 | G26: 2309고용보험 | H26: 세금과공과
B27: =B5 -> 신한 #672 | C27: 2023.10.10 | D27: 2309산재보험 | F27: 578530 | G27: 2309산재보험 | H27: 세금과공과
B28: =B5 -> 신한 #672 | C28: 2023.10.10 | D28: (주)제로엑스앤드코 | E28: 20000000 | G28: 계좌간 자금 이체 | H28: 보통예금
B29: =B5 -> 신한 #672 | C29: 2023.10.10 | D29: 2309국민건강 | F29: 7017600 | G29: 2309국민건강 | H29: 세금과공과
B30: =B5 -> 신한 #672 | C30: 2023.10.10 | D30: 2309국민연금 | F30: 6962440 | G30: 2309국민연금 | H30: 세금과공과
B31: =B7 -> 하나 #304 | C31: 2023.10.10 | D31: 주식회사 제로엑스앤드코리아 | E31: 133311000 | G31: 환전 | H31: 보통예금
B32: =B8 -> 하나 #138 | C32: 2023.10.10 | D32: 주식회사 제로엑스앤드코리아 | F32: 100000 | G32: 환전 | H32: 보통예금
B33: =B7 -> 하나 #304 | C33: 2023.10.10 | D33: 국고_주식회사 제로엑스 | F33: 6908640 | G33: 9월 근로 소득세 | H33: 세금과공과
B34: =B7 -> 하나 #304 | C34: 2023.10.10 | D34: 국고_주식회사 제로엑스 | F34: 176840 | G34: 9월 기타 소득세 | H34: 세금과공과
B35: =B7 -> 하나 #304 | C35: 2023.10.10 | D35: 서울지방제로엑스 | F35: 708470 | G35: 9월 지방 소득세 | H35: 세금과공과
B36: =B7 -> 하나 #304 | C36: 2023.10.10 | D36: 강진석 | F36: 34000 | G36: 개인경비 | H36: 복리후생비
B37: =B7 -> 하나 #304 | C37: 2023.10.10 | D37: 하나은행 | F37: 500 | G37: 송금 수수료 | H37: 지급수수료
B38: =B7 -> 하나 #304 | C38: 2023.10.10 | D38: 최고은 | F38: 28300 | G38: 개인경비 | H38: 복리후생비
B39: =B7 -> 하나 #304 | C39: 2023.10.10 | D39: 하나은행 | F39: 500 | G39: 송금 수수료 | H39: 지급수수료
B40: =B7 -> 하나 #304 | C40: 2023.10.10 | D40: 주식회사 제로엑스앤드코리아 | F40: 20000000 | G40: 계좌간 자금 이체 | H40: 보통예금
B41: =B7 -> 하나 #304 | C41: 2023.10.10 | D41: 하나은행 | F41: 500 | G41: 송금 수수료 | H41: 지급수수료
B42: =B9 -> WISE USD | C42: 2023.10.11 | D42: WISE | E42: 0.02 | G42: Refund credit | H42: 이자수익
B43: =B9 -> WISE USD | C43: 2023.10.11 | D43: Elenkei L&K | F43: 373.91 | G43: 접대비(500,000 KRW) | H43: 접대비
B44: =B9 -> WISE USD | C44: 2023.10.11 | D44: Apple.com | F44: 109.72 | G44: 업무용 tool 비용 지급 | H44: 지급수수료
B45: =B9 -> WISE USD | C45: 2023.10.11 | D45: EBOS Advisory Pte Ltd | F45: 1164.22 | G45: 등기 수수료 지급 | H45: 지급수수료
B46: =B9 -> WISE USD | C46: 2023.10.11 | D46: wise | F46: 4.76 | G46: 송금 수수료 | H46: 지급수수료
B47: =B9 -> WISE USD | C47: 2023.10.11 | D47: EBOS Advisory Pte Ltd | F47: 1098.35 | G47: 등기 수수료 지급 | H47: 지급수수료
B48: =B9 -> WISE USD | C48: 2023.10.11 | D48: wise | F48: 4.49 | G48: 송금 수수료 | H48: 지급수수료
B49: =B9 -> WISE USD | C49: 2023.10.14 | D49: Milestone Business Group | F49: 10422.68 | G49: Chris 11월 급여 | H49: 급여
B50: =B9 -> WISE USD | C50: 2023.10.14 | D50: wise | F50: 0.39 | G50: Chris 11월 급여 송금 수수료 | H50: 지급수수료
B51: =B9 -> WISE USD | C51: 2023.10.14 | D51: Postmarkapp.com | F51: 10 | G51: 서비스 이용료 지급 | H51: 지급수수료
B52: =B7 -> 하나 #304 | C52: 2023.10.25 | D52: 하나카드기업 | F52: 5190359 | G52: 카드 대금 | H52: 지급수수료
B53: =B7 -> 하나 #304 | C53: 2023.10.25 | D53: 급여 | F53: 80999436 | G53: 10월 급여 | H53: 급여
B54: =B7 -> 하나 #304 | C54: 2023.10.25 | D54: 하나은행 | F54: 7500 | G54: 송금 수수료 | H54: 지급수수료
B55: =B7 -> 하나 #304 | C55: 2023.10.25 | D55: 최유빈 | F55: 2016060 | G55: 10월 급여 (최유빈) | H55: 급여
B56: =B7 -> 하나 #304 | C56: 2023.10.25 | D56: (주)웰리더 | F56: 264000 | G56: PR 기사 수수료 지급 | H56: 마케팅비
B57: =B7 -> 하나 #304 | C57: 2023.10.25 | D57: 하나은행 | F57: 500 | G57: 송금 수수료 | H57: 지급수수료
B58: =B5 -> 신한 #672 | C58: 2023.10.23 | D58: 세콤(N5905012) | F58: 110000 | G58: 세콤(N5905012) | H58: 지급수수료
B59: =B12 -> OCBC USD | C59: 2023.10.19 | D59: Neicon Inc. | F59: 2755.82 | G59: 게임 도시 마케팅 비용 지급 | H59: 마케팅비
B60: =B13 -> OCBC SGD | C60: 2023.10.25 | D60: OCBC BANK | F60: 25 | G60: 송금수수료 지급 | H60: 지급수수료
B61: =B5 -> 신한 #672 | C61: 2023.10.25 | D61: 바디프랜드10 | F61: 98000 | G61: 안마의자 | H61: 복리후생비
B62: =B5 -> 신한 #672 | C62: 2023.10.25 | D62: 코웨이렌탈10 | F62: 37430 | G62: 공청기 | H62: 복리후생비
B63: =B5 -> 신한 #672 | C63: 2023.10.25 | D63: 코웨이렌탈10 | F63: 37430 | G63: 공청기 | H63: 복리후생비
B64: =B5 -> 신한 #672 | C64: 2023.10.25 | D64: 코웨이렌탈10 | F64: 20660 | G64: 비데 | H64: 복리후생비
B65: =B5 -> 신한 #672 | C65: 2023.10.25 | D65: 코웨이렌탈10 | F65: 50250 | G65: 정수기 | H65: 복리후생비
B66: =B5 -> 신한 #672 | C66: 2023.10.25 | D66: 코웨이렌탈10 | F66: 20660 | G66: 비데 | H66: 복리후생비
B67: =B5 -> 신한 #672 | C67: 2023.10.25 | D67: 삼덕회계법인 | F67: 330000 | G67: 회계 자문료 지급 | H67: 지급수수료
B68: =B5 -> 신한 #672 | C68: 2023.10.25 | D68: KT0540091110 | F68: 55630 | G68: 인터넷, 전화 요금 지급 | H68: 복리후생비
B69: =B9 -> WISE USD | C69: 2023.10.27 | D69: GitHub | F69: 148 | G69: 서비스 이용료 지급 | H69: 지급수수료
B70: =B7 -> 하나 #304 | C70: 2023.10.26 | D70: 주식회사 유인어스 | F70: 5500000 | G70: 비재무자산 설계 수수료 지급 | H70: 지급수수료
B71: =B7 -> 하나 #304 | C71: 2023.10.26 | D71: 하나은행 | F71: 500 | G71: 송금 수수료 | H71: 지급수수료
B72: =B5 -> 신한 #672 | C72: 2023.10.31 | D72: 안양신도판매 | F72: 77000 | G72: 복합기 사용료 지급 | H72: 지급수수료
B73: =B9 -> WISE USD | C73: 2023.10.30 | D73: trip.com | F73: 1.71 | G73: 수수료 지급 | H73: 지급수수료
B74: =B11 -> WISE KRW | C74: 2023.10.31 | D74: trip.com | E74: 2300 | G74: 수수료 환불 | H74: 지급수수료
B75: OCBC USD | C75: 2023.10.19 | D75: OCBC BANK | F75: 43 | G75: 수수료 지급 | H75: 지급수수료

Sheet 23.11월
B1: 자 금 일 보
I2: Currency | J2: KRW | L2: 계정과목 | M2: 설명
B3: ※ 자금현황 | G3: 기준일: 2023.11.30 | I3: USD | J3: =IFERROR(__xludf.DUMMYFUNCTION("GOOGLEFINANCE(""USDKRW"")"),1472.7250000000001) -> 1472.725 | L3: 광고매출 | M3: 타법인 매출
B4: 구 분 | C4: 단위 | D4: 전월잔액 | E4: 수 입 | F4: 지 출 | G4: 기준일 기준 잔액 | I4: SGD | J4: =IFERROR(__xludf.DUMMYFUNCTION("GOOGLEFINANCE(""SGDKRW"")"),1143.885) -> 1143.885 | L4: 급여 | M4: 직원 급여
B5: 신한 #672 | C5: KRW | D5: ='23.10월'!G5 -> 7927284 | E5: =sumif(B22:B139,B5,E22:E139) -> 20000000 | F5: =sumif(B22:B140,B5,F22:F140) -> 18140837 | G5: =D5+E5-F5 -> 9786447 | L5: 미수금 | M5: 돌려 받을 예정인 금액 (ex. 부가세 환급금)
B6: 신한 #543 | C6: USD | D6: ='23.10월'!G6 -> 2.31 | E6: =sumif(B22:B139,B6,E22:E139) -> 0 | F6: =sumif(B22:B139,B6,F22:F139) -> 0 | G6: =D6+E6-F6 -> 2.31 | L6: 보증금 | M6: 보증금 (사무실 임대, 장비 리스 등)
B7: 하나 #304 | C7: KRW | D7: ='23.10월'!G7 -> 32224096 | E7: =sumif(B22:B139,B7,E22:E139) -> 130539000 | F7: =sumif(B22:B139,B7,F22:F139) -> 128324270 | G7: =D7+E7-F7 -> 34438826 | L7: 보통예금 | M7: 예금간 이체
B8: 하나 #138 | C8: USD | D8: ='23.10월'!G8 -> 153584.28 | E8: =sumif(B22:B139,B8,E22:E139) -> 0 | F8: =sumif(B22:B139,B8,F22:F139) -> 115000 | G8: =D8+E8-F8 -> 38584.28 | L8: 복리후생비 | M8: 회식, 식대
B9: WISE USD | C9: USD | D9: ='23.10월'!G9 -> 45000.31 | E9: =sumif(B22:B139,B9,E22:E139) -> 0 | F9: =sumif(B22:B139,B9,F22:F139) -> 43635.14 | G9: =D9+E9-F9 -> 1365.17 | L9: 비품 | M9: 가구, 가전등 개당 단가 150만원이 넘는 용품
B10: WISE SGD | C10: SGD | D10: ='23.10월'!G10 -> 0 | E10: =sumif(B22:B137,B10,E22:E137) -> 46000 | F10: =sumif(B22:B139,B10,F22:F139) -> 46000 | G10: =D10+E10-F10 -> 0 | L10: 사무용품비 | M10: 비품, 소모품비를 제외한 업무용 사무용품 구입
B11: WISE KRW | C11: KRW | D11: ='23.10월'!G11 -> 2300 | E11: =sumif(B22:B139,B11,E22:E139) -> 0 | F11: =sumif(B22:B79,B11,F22:F139) -> 2300 | G11: =D11+E11-F11 -> 0 | L11: 서비스용역매출 | M11: 매출
B12: OCBC USD | C12: USD | D12: ='23.10월'!G12 -> 10984.65 | E12: =sumif(B22:B140,B12,E22:E82) -> 15000 | F12: =sumif(B22:B140,B12,F22:F140) -> 24824.03 | G12: =D12+E12-F12 -> 1160.62 | L12: 세금과공과 | M12: 세금 납부시
B13: OCBC SGD | C13: SGD | D13: ='23.10월'!G13 -> 630 | E13: =sumif(B22:B140,B13,E22:E140) -> 19000 | F13: =sumif(B22:B140,B13,F22:F140) -> 14454.41 | G13: =D13+E13-F13 -> 5175.59 | L13: 소모품비 | M13: 비품(150만원)으로 잡기에는 금액이 작은 비품
H14: 기준일 기준 잔액 | I14: 전월잔액 | L14: 여비교통비 | M14: 출장, 대중교통, 대리운전
B15: KRW 합 계 | D15: =D5+D7+D11 -> 40153680 | E15: =E5+E7+E11 -> 150539000 | F15: =F5+F7+F11 -> 146467407 | G15: =G5+G11+G7 -> 44225273 | H15: =G15 -> 44225273 | I15: =D15 -> 40153680 | L15: 용역비 | M15: 외주용역비
B16: USD 합 계 | D16: =D6+D8+D9+D12 -> 209571.55 | E16: =E6+E8+E9+E12 -> 15000 | F16: =F6+F8+F9+F12 -> 183459.17 | G16: =G9+G6+G8+G12 -> 41112.38 | H16: =rounddown(G16*$J$3,0) -> 60547229 | I16: =rounddown(D16*$J$3,0) -> 308641260 | L16: 접대비 | M16: 외부 미팅
B17: SGD 합 계 | D17: =D10+D13 -> 630 | E17: =E10+E13 -> 65000 | F17: =F10+F13 -> 60454.41 | G17: =G10+G13 -> 5175.59 | H17: =rounddown(G17*$J$4,0) -> 5920279 | I17: =rounddown(D17*$J$4,0) -> 720647 | L17: 지급수수료 | M17: sms 수수료, 송금 수수료, 일반적으로 발생되는 모든 비용
H18: =SUM(H15:H17) -> 110692781 | I18: =SUM(I15:I17) -> 349515587 | L18: 이자수익 | M18: 은행이자
H19: =H18-I18 -> -238822806 | L19: 통신비 | M19: 등기, 퀵 사용비
B20: ※ 세부내역 | L20: 마케팅비 | M20: PR 기사등 마케팅 비용
B21: 구 분 | C21: 날 짜 | D21: 은 행 적 요 | E21: 수입 | F21: 지출 | G21: 상세메모 | H21: 계정과목 | L21: 대여금 | M21: 싱가폴 -> 한국 지사 송금
B22: =B7 -> 하나 #304 | C22: 2023.11.03 | D22: 그림바우빌딩 | F22: 6105770 | G22: 10월 임대료,관리비,전기료 | H22: 지급수수료 | L22: 출장비 | M22: 출장여비
B23: =B7 -> 하나 #304 | C23: 2023.11.03 | D23: 비앤케이 | F23: 1375000 | G23: 10월 법률자문료 (자문 초과 포함) | H23: 지급수수료 | L23: 투자자산 | M23: 투자
B24: =B7 -> 하나 #304 | C24: 2023.11.03 | D24: 최고은 | F24: 135500 | G24: 개인 경비 지급 | H24: 복리후생비
B25: =B7 -> 하나 #304 | C25: 2023.11.03 | D25: 하나은행 | F25: 1500 | G25: 송금수수료 | H25: 지급수수료
B26: =B9 -> WISE USD | C26: 2023.11.07 | D26: Zero X And Pte. Ltd. | F26: 1000 | G26: 자금 이동 | H26: 보통예금
B27: =B9 -> WISE USD | C27: 2023.11.07 | D27: wise | F27: 0.39 | G27: 송금 수수료 | H27: 지급수수료
B28: =B9 -> WISE USD | C28: 2023.11.09 | D28: Zero X And Pte. Ltd. | F28: 4448.03 | G28: 자금 이동 | H28: 보통예금
B29: =B10 -> WISE SGD | C29: 2023.11.09 | D29: Zero X And Pte. Ltd. | E29: 6000 | G29: 자금 이동 | H29: 보통예금
B30: =B10 -> WISE SGD | C30: 2023.11.09 | D30: ATOZ SG CONSULTING PTE. LTD | F30: 5520 | G30: 신규 회계법인 1년 수수료 지급 | H30: 지급수수료
B31: =B12 -> OCBC USD | C31: 2023.11.09 | D31: Milestone Business Group | F31: 10422.68 | G31: Chris 12월 급여 | H31: 급여
B32: =B12 -> OCBC USD | C32: 2023.11.09 | D32: OCBC BANK | F32: =43+15 -> 58 | G32: Chris 12월 급여 송금 수수료 | H32: 지급수수료
B33: =B8 -> 하나 #138 | C33: 2023.11.10 | D33: 주식회사 제로엑스앤드코리아 | F33: 100000 | G33: 환전 | H33: 보통예금
B34: =B7 -> 하나 #304 | C34: 2023.11.10 | D34: 주식회사 제로엑스앤드코리아 | E34: 130539000 | G34: 환전 | H34: 보통예금
B35: =B7 -> 하나 #304 | C35: 2023.11.10 | D35: 국고_주식회사 제로엑스 | F35: 6908640 | G35: 10월 근로 소득세 | H35: 세금과공과
B36: =B7 -> 하나 #304 | C36: 2023.11.10 | D36: 국고_주식회사 제로엑스 | F36: 176840 | G36: 10월 기타 소득세 | H36: 세금과공과
B37: =B7 -> 하나 #304 | C37: 2023.11.10 | D37: 서울지방제로엑스 | F37: 708470 | G37: 10월 지방 소득세 | H37: 세금과공과
B38: =B7 -> 하나 #304 | C38: 2023.11.10 | D38: 주식회사 제로엑스앤드코리아 | F38: 20000000 | G38: 계좌간 자금 이체 | H38: 보통예금
B39: =B7 -> 하나 #304 | C39: 2023.11.10 | D39: 하나은행 | F39: 500 | G39: 송금 수수료 | H39: 지급수수료
B40: =B5 -> 신한 #672 | C40: 2023.11.10 | D40: 2309고용보험 | F40: 1519280 | G40: 2310고용보험 | H40: 세금과공과
B41: =B5 -> 신한 #672 | C41: 2023.11.10 | D41: 2309산재보험 | F41: 578530 | G41: 2310산재보험 | H41: 세금과공과
B42: =B5 -> 신한 #672 | C42: 2023.11.10 | D42: (주)제로엑스앤드코 | E42: 20000000 | G42: 계좌간 자금 이체 | H42: 보통예금
B43: =B5 -> 신한 #672 | C43: 2023.11.10 | D43: 2309국민건강 | F43: 7017600 | G43: 2310국민건강 | H43: 세금과공과
B44: =B5 -> 신한 #672 | C44: 2023.11.10 | D44: 2309국민연금 | F44: 6943600 | G44: 2310국민연금 | H44: 세금과공과
B45: =B9 -> WISE USD | C45: 2023.11.10 | D45: Certified Kernel Tech LLC | F45: 8000 | G45: 컨트랙트 오딧 | H45: 지급수수료
B46: =B9 -> WISE USD | C46: 2023.11.10 | D46: wise | F46: 0.39 | G46: 송금 수수료 | H46: 지급수수료
B47: =B7 -> 하나 #304 | C47: 2023.11.24 | D47: 급여 | F47: 82753430 | G47: 11월 급여 | H47: 급여
B48: =B7 -> 하나 #304 | C48: 2023.11.24 | D48: 하나은행 | F48: 7500 | G48: 송금 수수료 | H48: 지급수수료
B49: =B7 -> 하나 #304 | C49: 2023.11.24 | D49: 최유빈 | F49: 403210 | G49: 10월 급여 (최유빈) | H49: 급여
B50: =B7 -> 하나 #304 | C50: 2023.11.27 | D50: 하나카드기업 | F50: 9713596 | G50: 카드 대금 | H50: 지급수수료
B51: =B7 -> 하나 #304 | C51: 2023.11.27 | D51: 당발송금수수료 | F51: 34314 | G51: 송금 수수료 | H51: 지급수수료
B52: =B8 -> 하나 #138 | C52: 2023.11.27 | D52: ZERO X AND PTE. LTD. | F52: 15000 | G52: 마케팅비 지급 | H52: 마케팅비
B53: =B5 -> 신한 #672 | C53: 2023.11.21 | D53: 세콤(N5905012) | F53: 110000 | G53: 세콤(N5905012) | H53: 지급수수료
B54: =B5 -> 신한 #672 | C54: 2023.11.23 | D54: 차앤권법률사무소 | F54: 682000 | G54: CERTIFICATE OF GOOD STANDING 발급 | H54: 지급수수료
B55: =B9 -> WISE USD | C55: 2023.11.14 | D55: Postmarkapp.com | F55: 10 | G55: 서비스 이용료 지급 | H55: 지급수수료
B56: =B9 -> WISE USD | C56: 2023.11.16 | D56: Traffic Light | F56: 98.15 | G56: 출장비 | H56: 여비교통비
B57: =B10 -> WISE SGD | C57: 2023.11.16 | D57: Traffic Light | F57: 480 | G57: 출장비 | H57: 여비교통비
B58: =B11 -> WISE KRW | C58: 2023.11.16 | D58: Traffic Light | F58: 2300 | G58: 출장비 | H58: 여비교통비
B59: =B12 -> OCBC USD | C59: 2023.11.27 | D59: ZERO X AND KOREA | E59: 15000 | G59: 마케팅비 입금 | H59: 마케팅비
B60: =B12 -> OCBC USD | C60: 2023.11.27 | D60: ZERO X AND PTE. LTD. | F60: 11311.36 | G60: USD -> SGD 환전 | H60: 보통예금
B61: =B13 -> OCBC SGD | C61: 2023.11.27 | D61: ZERO X AND PTE. LTD. | E61: 15000 | G61: USD -> SGD 환전 | H61: 보통예금
B62: =B9 -> WISE USD | C62: 2023.11.27 | D62: ZERO X AND PTE. LTD. | F62: 30000 | G62: USD -> SGD 환전 | H62: 보통예금
B63: =B10 -> WISE SGD | C63: 2023.11.27 | D63: ZERO X AND PTE. LTD. | E63: 39896.08 | G63: USD -> SGD 환전 | H63: 보통예금
B64: =B9 -> WISE USD | C64: 2023.11.27 | D64: ZERO X AND PTE. LTD. | F64: 78.18 | G64: USD -> SGD 환전 | H64: 보통예금
B65: =B10 -> WISE SGD | C65: 2023.11.27 | D65: ZERO X AND PTE. LTD. | E65: 103.92 | G65: USD -> SGD 환전 | H65: 보통예금
B66: =B10 -> WISE SGD | C66: 2023.11.27 | D66: Commissioner of Inland Revenue | F66: 40000 | G66: 법인세 납부 | H66: 세금과공과
B67: =B13 -> OCBC SGD | C67: 2023.11.28 | D67: Commissioner of Inland Revenue | F67: 14429.41 | G67: 법인세 납부 | H67: 세금과공과
B68: =B5 -> 신한 #672 | C68: 2023.11.27 | D68: 바디프랜드10 | F68: 98000 | G68: 안마의자 | H68: 복리후생비
B69: =B5 -> 신한 #672 | C69: 2023.11.27 | D69: 코웨이렌탈10 | F69: 37430 | G69: 공청기 | H69: 복리후생비
B70: =B5 -> 신한 #672 | C70: 2023.11.27 | D70: 코웨이렌탈10 | F70: 37430 | G70: 공청기 | H70: 복리후생비
B71: =B5 -> 신한 #672 | C71: 2023.11.27 | D71: 코웨이렌탈10 | F71: 20660 | G71: 비데 | H71: 복리후생비
B72: =B5 -> 신한 #672 | C72: 2023.11.27 | D72: 코웨이렌탈10 | F72: 50250 | G72: 정수기 | H72: 복리후생비
B73: =B5 -> 신한 #672 | C73: 2023.11.27 | D73: 코웨이렌탈10 | F73: 20660 | G73: 비데 | H73: 복리후생비
B74: =B5 -> 신한 #672 | C74: 2023.11.27 | D74: 삼덕회계법인 | F74: 330000 | G74: 회계 자문료 지급 | H74: 지급수수료
B75: =B5 -> 신한 #672 | C75: 2023.11.27 | D75: KT0540091110 | F75: 55660 | G75: 인터넷, 전화 요금 지급 | H75: 복리후생비
B76: =B5 -> 신한 #672 | C76: 2023.11.27 | D76: 하나카드기업 | F76: 562737 | G76: 카드 대금 | H76: 지급수수료
B77: =B5 -> 신한 #672 | C77: 2023.11.30 | D77: 안양신도판매 | F77: 77000 | G77: 복합기 사용료 지급 | H77: 지급수수료
B78: =B13 -> OCBC SGD | C78: 2023.11.30 | D78: ZERO X AND PTE. LTD. | E78: 4000 | G78: USD -> SGD 환전 | H78: 보통예금
B79: =B13 -> OCBC SGD | C79: 2023.11.30 | D79: OCBC BANK | F79: 15 | G79: USD -> SGD 환전 수수료 | H79: 지급수수료
B80: =B13 -> OCBC SGD | C80: 2023.11.03 | D80: OCBC BANK | F80: 10 | G80: USD -> SGD 환전 수수료 | H80: 지급수수료
B81: OCBC USD | C81: 2023.11.30 | D81: ZERO X AND PTE. LTD. | F81: 3024.57 | G81: USD -> SGD 환전 | H81: 보통예금
B82: OCBC USD | C82: 2023.11.27 | D82: OCBC BANK | F82: 7.42 | G82: USD -> SGD 환전 수수료 | H82: 지급수수료

Sheet 23.12월
B1: 자 금 일 보
I2: Currency | J2: KRW | L2: 계정과목 | M2: 설명
B3: ※ 자금현황 | G3: 기준일: 2023.12.31 | I3: USD | J3: =IFERROR(__xludf.DUMMYFUNCTION("GOOGLEFINANCE(""USDKRW"")"),1472.7250000000001) -> 1472.725 | L3: 광고매출 | M3: 타법인 매출
B4: 구 분 | C4: 단위 | D4: 전월잔액 | E4: 수 입 | F4: 지 출 | G4: 기준일 기준 잔액 | I4: SGD | J4: =IFERROR(__xludf.DUMMYFUNCTION("GOOGLEFINANCE(""SGDKRW"")"),1143.885) -> 1143.885 | L4: 급여 | M4: 직원 급여
B5: 신한 #672 | C5: KRW | D5: ='23.11월'!G5 -> 9786447 | E5: =sumif(B22:B131,B5,E22:E131) -> 13002631 | F5: =sumif(B22:B132,B5,F22:F132) -> 19689019 | G5: =D5+E5-F5 -> 3100059 | L5: 미수금 | M5: 돌려 받을 예정인 금액 (ex. 부가세 환급금)
B6: 신한 #543 | C6: USD | D6: ='23.11월'!G6 -> 2.31 | E6: =sumif(B22:B131,B6,E22:E131) -> 0 | F6: =sumif(B22:B131,B6,F22:F131) -> 0 | G6: =D6+E6-F6 -> 2.31 | L6: 보증금 | M6: 보증금 (사무실 임대, 장비 리스 등)
B7: 하나 #304 | C7: KRW | D7: ='23.11월'!G7 -> 34438826 | E7: =sumif(B22:B131,B7,E22:E131) -> 85735959 | F7: =sumif(B22:B131,B7,F22:F131) -> 111606373 | G7: =D7+E7-F7 -> 8568412 | L7: 보통예금 | M7: 예금간 이체
B8: 하나 #138 | C8: USD | D8: ='23.11월'!G8 -> 38584.28 | E8: =sumif(B22:B131,B8,E22:E131) -> 3.35 | F8: =sumif(B22:B131,B8,F22:F131) -> 38584.28 | G8: =D8+E8-F8 -> 3.35 | L8: 복리후생비 | M8: 회식, 식대
B9: WISE USD | C9: USD | D9: ='23.11월'!G9 -> 1365.17 | E9: =sumif(B22:B131,B9,E22:E131) -> 0 | F9: =sumif(B22:B131,B9,F22:F131) -> 847.96 | G9: =D9+E9-F9 -> 517.21 | L9: 비품 | M9: 가구, 가전등 개당 단가 150만원이 넘는 용품
B10: WISE SGD | C10: SGD | D10: ='23.11월'!G10 -> 0 | E10: =sumif(B22:B129,B10,E22:E129) -> 1100 | F10: =sumif(B22:B131,B10,F22:F131) -> 0 | G10: =D10+E10-F10 -> 1100 | L10: 사무용품비 | M10: 비품, 소모품비를 제외한 업무용 사무용품 구입
B11: WISE KRW | C11: KRW | D11: ='23.11월'!G11 -> 0 | E11: =sumif(B22:B131,B11,E22:E131) -> 0 | F11: =sumif(B22:B71,B11,F22:F131) -> 0 | G11: =D11+E11-F11 -> 0 | L11: 서비스용역매출 | M11: 매출
B12: OCBC USD | C12: USD | D12: ='23.11월'!G12 -> 1160.62 | E12: =sumif(B22:B132,B12,E22:E74) -> 0 | F12: =sumif(B22:B132,B12,F22:F132) -> 0 | G12: =D12+E12-F12 -> 1160.62 | L12: 세금과공과 | M12: 세금 납부시
B13: OCBC SGD | C13: SGD | D13: ='23.11월'!G13 -> 5175.59 | E13: =sumif(B22:B132,B13,E22:E132) -> 0 | F13: =sumif(B22:B132,B13,F22:F132) -> 4010 | G13: =D13+E13-F13 -> 1165.59 | L13: 소모품비 | M13: 비품(150만원)으로 잡기에는 금액이 작은 비품
H14: 기준일 기준 잔액 | I14: 전월잔액 | L14: 여비교통비 | M14: 출장, 대중교통, 대리운전
B15: KRW 합 계 | D15: =D5+D7+D11 -> 44225273 | E15: =E5+E7+E11 -> 98738590 | F15: =F5+F7+F11 -> 131295392 | G15: =G5+G11+G7 -> 11668471 | H15: =G15 -> 11668471 | I15: =D15 -> 44225273 | L15: 용역비 | M15: 외주용역비
B16: USD 합 계 | D16: =D6+D8+D9+D12 -> 41112.38 | E16: =E6+E8+E9+E12 -> 3.35 | F16: =F6+F8+F9+F12 -> 39432.24 | G16: =G9+G6+G8+G12 -> 1683.49 | H16: =rounddown(G16*$J$3,0) -> 2479317 | I16: =rounddown(D16*$J$3,0) -> 60547229 | L16: 접대비 | M16: 외부 미팅
B17: SGD 합 계 | D17: =D10+D13 -> 5175.59 | E17: =E10+E13 -> 1100 | F17: =F10+F13 -> 4010 | G17: =G10+G13 -> 2265.59 | H17: =rounddown(G17*$J$4,0) -> 2591574 | I17: =rounddown(D17*$J$4,0) -> 5920279 | L17: 지급수수료 | M17: sms 수수료, 송금 수수료, 일반적으로 발생되는 모든 비용
H18: =SUM(H15:H17) -> 16739362 | I18: =SUM(I15:I17) -> 110692781 | L18: 이자수익 | M18: 은행이자
H19: =H18-I18 -> -93953419 | L19: 통신비 | M19: 등기, 퀵 사용비
B20: ※ 세부내역 | L20: 마케팅비 | M20: PR 기사등 마케팅 비용
B21: 구 분 | C21: 날 짜 | D21: 은 행 적 요 | E21: 수입 | F21: 지출 | G21: 상세메모 | H21: 계정과목 | L21: 대여금 | M21: 싱가폴 -> 한국 지사 송금
B22: =B7 -> 하나 #304 | C22: 2023.12.04 | D22: 그림바우빌딩 | F22: 6170450 | G22: 11월 임대료,관리비,전기료 | H22: 지급수수료 | L22: 출장비 | M22: 출장여비
B23: =B7 -> 하나 #304 | C23: 2023.12.04 | D23: 비앤케이 | F23: 825000 | G23: 11월 법률자문료 | H23: 지급수수료 | L23: 투자자산 | M23: 투자
B24: =B7 -> 하나 #304 | C24: 2023.12.04 | D24: 주식회사 워크앤조이 | F24: 98527 | G24: 11월 그룹웨어 사용료 지급 | H24: 지급수수료 | L24: 가수금 | M24: 가수금
B25: =B7 -> 하나 #304 | C25: 2023.12.04 | D25: 하나은행 | F25: 1000 | G25: 송금 수수료 | H25: 지급수수료 | L25: 잡이익 | M25: 잡이익
B26: =B13 -> OCBC SGD | C26: 2023.12.04 | D26: Entra Law | F26: 4000 | G26: 법률자문료 (투자계약서 작성) | H26: 지급수수료
B27: =B13 -> OCBC SGD | C27: 2023.12.04 | D27: OCBC | F27: 10 | G27: 송금 수수료 | H27: 지급수수료
B28: =B7 -> 하나 #304 | C28: 2023.12.05 | D28: 주식회사 제로엑스앤드코리아 | E28: 50205093 | G28: 환전 | H28: 보통예금
B29: =B8 -> 하나 #138 | C29: 2023.12.05 | D29: 주식회사 제로엑스앤드코리아 | F29: 38584.28 | G29: 환전 | H29: 보통예금
B30: =B7 -> 하나 #304 | C30: 2023.12.11 | D30: 국세청 | F30: 6897000 | G30: 11월 근로 소득세 | H30: 세금과공과
B31: =B7 -> 하나 #304 | C31: 2023.12.11 | D31: 국세청 | F31: 35360 | G31: 11월 기타 소득세 | H31: 세금과공과
B32: =B7 -> 하나 #304 | C32: 2023.12.11 | D32: 강남구청 | F32: 693160 | G32: 11월 지방 소득세 | H32: 세금과공과
B33: =B7 -> 하나 #304 | C33: 2023.12.11 | D33: 정하성 | F33: 12800 | G33: 중도퇴사자 소득세 환급 | H33: 세금과공과
B34: =B7 -> 하나 #304 | C34: 2023.12.11 | D34: 신한은행 | F34: 13000000 | G34: 계좌간 자금 이체 | H34: 보통예금
B35: =B7 -> 하나 #304 | C35: 2023.12.11 | D35: 하나은행 | F35: 1000 | G35: 송금 수수료 지급 | H35: 지급수수료
B36: =B5 -> 신한 #672 | C36: 2023.12.11 | D36: 주식회사 제로 | E36: 13000000 | G36: 계좌간 자금 이체 | H36: 보통예금
B37: =B5 -> 신한 #672 | C37: 2023.12.11 | D37: 2311산재보험 | F37: 578380 | G37: 2311산재보험 | H37: 세금과공과
B38: =B5 -> 신한 #672 | C38: 2023.12.11 | D38: 2311고용보험 | F38: 1552240 | G38: 2311고용보험 | H38: 세금과공과
B39: =B5 -> 신한 #672 | C39: 2023.12.11 | D39: 2311국민건강 | F39: 7017600 | G39: 2311국민건강 | H39: 세금과공과
B40: =B5 -> 신한 #672 | C40: 2023.12.11 | D40: 2311국민연금 | F40: 6962440 | G40: 2311국민연금 | H40: 세금과공과
B41: =B7 -> 하나 #304 | C41: 2023.12.11 | D41: 전준영 | E41: 30000000 | G41: 가수금 입금 | H41: 가수금
B42: =B5 -> 신한 #672 | C42: 2023.12.16 | D42: 신한은행 | E42: 2631 | G42: 예금이자 | H42: 이자수익
B43: =B5 -> 신한 #672 | C43: 2023.12.21 | D43: 세콤(N5905012) | F43: 110000 | G43: 세콤(N5905012) | H43: 지급수수료
B44: =B7 -> 하나 #304 | C44: 2023.12.16 | D44: 하나은행 | E44: 15666 | G44: 예금이자 | H44: 이자수익
B45: =B8 -> 하나 #138 | C45: 2023.12.16 | D45: 하나은행 | E45: 3.35 | G45: 예금이자 | H45: 이자수익
B46: =B7 -> 하나 #304 | C46: 2023.12.22 | D46: 급여 | F46: 80721136 | G46: 12월 급여 | H46: 급여
B47: =B7 -> 하나 #304 | C47: 2023.12.22 | D47: 하나은행 | F47: 7000 | G47: 송금 수수료 | H47: 지급수수료
B48: =B5 -> 신한 #672 | C48: 2023.12.26 | D48: 바디프랜드10 | F48: 98000 | G48: 안마의자 | H48: 복리후생비
B49: =B5 -> 신한 #672 | C49: 2023.12.26 | D49: 코웨이렌탈10 | F49: 37430 | G49: 공청기 | H49: 복리후생비
B50: =B5 -> 신한 #672 | C50: 2023.12.26 | D50: 코웨이렌탈10 | F50: 37430 | G50: 공청기 | H50: 복리후생비
B51: =B5 -> 신한 #672 | C51: 2023.12.26 | D51: 코웨이렌탈10 | F51: 20660 | G51: 비데 | H51: 복리후생비
B52: =B5 -> 신한 #672 | C52: 2023.12.26 | D52: 코웨이렌탈10 | F52: 50250 | G52: 정수기 | H52: 복리후생비
B53: =B5 -> 신한 #672 | C53: 2023.12.26 | D53: 코웨이렌탈10 | F53: 20660 | G53: 비데 | H53: 복리후생비
B54: =B5 -> 신한 #672 | C54: 2023.12.26 | D54: 삼덕회계법인 | F54: 330000 | G54: 회계 자문료 지급 | H54: 지급수수료
B55: =B5 -> 신한 #672 | C55: 2023.12.26 | D55: KT0540091110 | F55: 55750 | G55: 인터넷, 전화 요금 지급 | H55: 복리후생비
B56: =B5 -> 신한 #672 | C56: 2023.12.26 | D56: 현대카드(주) | F56: 2741179 | G56: 카드 대금 | H56: 지급수수료
B57: =B7 -> 하나 #304 | C57: 2023.12.26 | D57: 하나카드기업 | F57: 3143940 | G57: 카드 대금 | H57: 지급수수료
B58: =B7 -> 하나 #304 | C58: 2023.12.26 | D58: 서울강남고용노동지청 | E58: 3600000 | G58: 청년일자리도약장려금 (밀리) | H58: 잡이익
B59: =B7 -> 하나 #304 | C59: 2023.12.29 | D59: 한국장학재단 | E59: 1915200 | G59: 현장 교사 지원금 | H59: 잡이익
B60: =B5 -> 신한 #672 | C60: 2023.12.29 | D60: 안양신도판매 | F60: 77000 | G60: 복합기 사용료 지급 | H60: 지급수수료
B61: =B9 -> WISE USD | C61: 2023.12.14 | D61: Postmarkapp.com | F61: 10 | G61: 서비스 이용료 지급 | H61: 지급수수료
B62: =B9 -> WISE USD | C62: 2023.12.29 | D62: ZERO X AND PTE. LTD. | F62: 837.96 | G62: USD -> SGD 환전 | H62: 보통예금
B63: =B10 -> WISE SGD | C63: 2023.12.29 | D63: ZERO X AND PTE. LTD. | E63: 1100 | G63: USD -> SGD 환전 | H63: 보통예금

Sheet 24.01월
B1: 자 금 일 보
I2: Currency | J2: KRW | L2: 계정과목 | M2: 설명
B3: ※ 자금현황 | G3: 기준일: 2024.01.31 | I3: USD | J3: =IFERROR(__xludf.DUMMYFUNCTION("GOOGLEFINANCE(""USDKRW"")"),1472.7250000000001) -> 1472.725 | L3: 광고매출 | M3: 타법인 매출
B4: 구 분 | C4: 단위 | D4: 전월잔액 | E4: 수 입 | F4: 지 출 | G4: 기준일 기준 잔액 | I4: SGD | J4: =IFERROR(__xludf.DUMMYFUNCTION("GOOGLEFINANCE(""SGDKRW"")"),1143.885) -> 1143.885 | L4: 급여 | M4: 직원 급여
B5: 신한 #672 | C5: KRW | D5: ='23.12월'!G5 -> 3100059 | E5: =sumif(B25:B129,B5,E25:E129) -> 17500003 | F5: =sumif(B25:B130,B5,F25:F130) -> 20278579 | G5: =D5+E5-F5 -> 321483 | L5: 미수금 | M5: 돌려 받을 예정인 금액 (ex. 부가세 환급금)
B6: 신한 #543 | C6: USD | D6: ='23.12월'!G6 -> 2.31 | E6: =sumif(B25:B129,B6,E25:E129) -> 0 | F6: =sumif(B25:B129,B6,F25:F129) -> 0 | G6: =D6+E6-F6 -> 2.31 | L6: 보증금 | M6: 보증금 (사무실 임대, 장비 리스 등)
B7: 하나 #304 | C7: KRW | D7: ='23.12월'!G7 -> 8568412 | E7: =sumif(B25:B129,B7,E25:E129) -> 58550000 | F7: =sumif(B25:B129,B7,F25:F129) -> 63362500 | G7: =D7+E7-F7 -> 3755912 | L7: 보통예금 | M7: 예금간 이체
B8: 하나 #138 | C8: USD | D8: ='23.12월'!G8 -> 3.35 | E8: =sumif(B25:B129,B8,E25:E129) -> 0 | F8: =sumif(B25:B129,B8,F25:F129) -> 0 | G8: =D8+E8-F8 -> 3.35 | L8: 복리후생비 | M8: 회식, 식대
B9: 기업 #019 | C9: KRW | D9: 0 | E9: =sumif(B25:B130,B9,E25:E130) -> 200001643 | F9: =sumif(B25:B131,B9,F25:F131) -> 115991877 | G9: =D9+E9-F9 -> 84009766 | H9: 일반계좌 | L9: 비품 | M9: 가구, 가전등 개당 단가 150만원이 넘는 용품
B10: 기업 #020 | C10: KRW | D10: 0 | E10: =sumif(B25:B131,B10,E25:E131) -> 400000000 | F10: =sumif(B25:B132,B10,F25:F132) -> 216000000 | G10: =D10+E10-F10 -> 184000000 | H10: 기보보증금 | L10: 사무용품비 | M10: 비품, 소모품비를 제외한 업무용 사무용품 구입
B11: 기업 #010 | C11: USD | D11: 0 | E11: =sumif(B25:B132,B11,E25:E132) -> 0 | F11: =sumif(B25:B132,B11,F25:F132) -> 0 | G11: =D11+E11-F11 -> 0 | L11: 서비스용역매출 | M11: 매출
B12: WISE USD | C12: USD | D12: ='23.12월'!G9 -> 517.21 | E12: =sumif(B25:B129,B12,E25:E129) -> 20743.68 | F12: =sumif(B25:B129,B12,F25:F129) -> 10386.37 | G12: =D12+E12-F12 -> 10874.52 | L12: 세금과공과 | M12: 세금 납부시
B13: WISE SGD | C13: SGD | D13: ='23.12월'!G10 -> 1100 | E13: =sumif(B25:B127,B13,E25:E127) -> 0 | F13: =sumif(B25:B129,B13,F25:F129) -> 994.6 | G13: =D13+E13-F13 -> 105.4 | L13: 소모품비 | M13: 비품(150만원)으로 잡기에는 금액이 작은 비품
B14: WISE KRW | C14: KRW | D14: ='23.12월'!G11 -> 0 | E14: =sumif(B25:B129,B14,E25:E129) -> 0 | F14: =sumif(B25:B69,B14,F25:F129) -> 0 | G14: =D14+E14-F14 -> 0 | L14: 여비교통비 | M14: 출장, 대중교통, 대리운전
B15: OCBC USD | C15: USD | D15: ='23.12월'!G12 -> 1160.62 | E15: =sumif(B25:B130,B15,E25:E72) -> 0 | F15: =sumif(B25:B130,B15,F25:F130) -> 0 | G15: =D15+E15-F15 -> 1160.62 | L15: 용역비 | M15: 외주용역비
B16: OCBC SGD | C16: SGD | D16: ='23.12월'!G13 -> 1165.59 | E16: =sumif(B25:B130,B16,E25:E130) -> 0 | F16: =sumif(B25:B130,B16,F25:F130) -> 10 | G16: =D16+E16-F16 -> 1155.59 | L16: 접대비 | M16: 외부 미팅
H17: 기준일 기준 잔액 | I17: 전월잔액 | L17: 지급수수료 | M17: sms 수수료, 송금 수수료, 일반적으로 발생되는 모든 비용
B18: KRW 합 계 | D18: =D5+D7+D14+D9+D10 -> 11668471 | E18: =E5+E7+E14+E9+E10 -> 676051646 | F18: =F5+F7+F14+F9+F10 -> 415632956 | G18: =G5+G7+G14+G9+G10 -> 272087161 | H18: =G18 -> 272087161 | I18: =D18 -> 11668471 | L18: 이자수익 | M18: 은행이자
B19: USD 합 계 | D19: =D6+D8+D12+D15+D11 -> 1683.49 | E19: =E6+E8+E12+E15+E11 -> 20743.68 | F19: =F6+F8+F12+F15+F11 -> 10386.37 | G19: =G6+G8+G12+G15+G11 -> 12040.8 | H19: =rounddown(G19*$J$3,0) -> 17732787 | I19: =rounddown(D19*$J$3,0) -> 2479317 | L19: 통신비 | M19: 등기, 퀵 사용비
B20: SGD 합 계 | D20: =D13+D16 -> 2265.59 | E20: =E13+E16 -> 0 | F20: =F13+F16 -> 1004.6 | G20: =G13+G16 -> 1260.99 | H20: =rounddown(G20*$J$4,0) -> 1442427 | I20: =rounddown(D20*$J$4,0) -> 2591574 | L20: 마케팅비 | M20: PR 기사등 마케팅 비용
H21: =SUM(H18:H20) -> 291262375 | I21: =SUM(I18:I20) -> 16739362 | L21: 대여금 | M21: 싱가폴 -> 한국 지사 송금
H22: =H21-I21 -> 274523013 | L22: 출장비 | M22: 출장여비
B23: ※ 세부내역 | L23: 투자자산 | M23: 투자
B24: 구 분 | C24: 날 짜 | D24: 은 행 적 요 | E24: 수입 | F24: 지출 | G24: 상세메모 | H24: 계정과목 | L24: 가수금 | M24: 가수금
B25: =B7 -> 하나 #304 | C25: 2024.01.03 | D25: 그림바우빌딩 | F25: 6219510 | G25: 12월 임대료,관리비,전기료 | H25: 지급수수료 | L25: 잡이익 | M25: 잡이익
B26: =B7 -> 하나 #304 | C26: 2024.01.03 | D26: 하나은행 | F26: 500 | G26: 송금 수수료 | H26: 지급수수료 | L26: 단기차입금 | M26: 기보 대출금
B27: =B5 -> 신한 #672 | C27: 2024.01.03 | D27: 비앤케이 | F27: 825000 | G27: 12월 법률자문료 | H27: 지급수수료
B28: =B7 -> 하나 #304 | C28: 2024.01.03 | D28: 전준영 | E28: 20000000 | G28: 가수금 입금 | H28: 가수금
B29: OCBC SGD | C29: 2024.01.03 | D29: OCBC | F29: 10 | G29: 송금 수수료 | H29: 지급수수료
B30: =B7 -> 하나 #304 | C30: 2024.01.09 | D30: 국세청 | F30: 6907710 | G30: 12월 근로 소득세 | H30: 세금과공과
B31: =B7 -> 하나 #304 | C31: 2024.01.09 | D31: 강남구청 | F31: 690690 | G31: 12월 지방 소득세 | H31: 세금과공과
B32: =B7 -> 하나 #304 | C32: 2024.01.09 | D32: 신한은행 | F32: 14000000 | G32: 계좌간 자금 이체 | H32: 보통예금
B33: =B7 -> 하나 #304 | C33: 2024.01.09 | D33: 하나은행 | F33: 500 | G33: 송금 수수료 지급 | H33: 지급수수료
B34: =B5 -> 신한 #672 | C34: 2024.01.09 | D34: 지식제산공제 | E34: 1 | G34: 인증번호 확인용 입금 | H34: 잡이익
B35: =B5 -> 신한 #672 | C35: 2024.01.09 | D35: 지식제산공제 | F35: 300000 | G35: 지식제산공제 상품 가입 | H35: 보통예금
B36: =B5 -> 신한 #672 | C36: 2024.01.09 | D36: 주식회사 제로 | E36: 14000000 | G36: 계좌간 자금 이체 | H36: 보통예금
B37: =B5 -> 신한 #672 | C37: 2024.01.10 | D37: 2312국민건강 | F37: 6911240 | G37: 2312국민건강 | H37: 세금과공과
B38: =B5 -> 신한 #672 | C38: 2024.01.10 | D38: 2312고용보험 | F38: 1511350 | G38: 2312고용보험 | H38: 세금과공과
B39: =B5 -> 신한 #672 | C39: 2024.01.10 | D39: 2312국민연금 | F39: 6934720 | G39: 2312국민연금 | H39: 세금과공과
B40: =B5 -> 신한 #672 | C40: 2024.01.10 | D40: 2312산재보험 | F40: 560140 | G40: 2312산재보험 | H40: 세금과공과
B41: =B5 -> 신한 #672 | C41: 2024.01.10 | D41: 청약용6168 | E41: 1 | G41: 인증번호 확인용 입금 | H41: 잡이익
B42: =B5 -> 신한 #672 | C42: 2024.01.10 | D42: 청약용8994 | E42: 1 | G42: 인증번호 확인용 입금 | H42: 잡이익
B43: =B7 -> 하나 #304 | C43: 2024.01.15 | D43: 신한은행 | F43: 500000 | G43: 계좌간 자금 이체 | H43: 보통예금
B44: =B7 -> 하나 #304 | C44: 2024.01.15 | D44: 하나은행 | F44: 500 | G44: 송금 수수료 지급 | H44: 지급수수료
B45: =B5 -> 신한 #672 | C45: 2024.01.15 | D45: 주식회사 제로 | E45: 500000 | G45: 계좌간 자금 이체 | H45: 보통예금
B46: =B12 -> WISE USD | C46: 2024.01.14 | D46: Postmarkapp.com | F46: 10 | G46: 서비스 이용료 지급 | H46: 지급수수료
B47: =B13 -> WISE SGD | C47: 2024.01.03 | D47: ATOZ ASIA PROFESSIONAL SERVICES | F47: 994.6 | G47: 자사주 매입 후 소각 대행 수수료 지급 | H47: 지급수수료
B48: =B5 -> 신한 #672 | C48: 2024.01.18 | D48: 주식회사 제로엑스앤드코리아 | F48: 550000 | G48: 계좌간 자금 이체 | H48: 보통예금
B49: =B5 -> 신한 #672 | C49: 2024.01.18 | D49: 신한은행 | F49: 500 | G49: 송금 수수료 지급 | H49: 보통예금
B50: =B7 -> 하나 #304 | C50: 2024.01.18 | D50: 주식회사 제로엑스앤드코리아 | E50: 550000 | G50: 계좌간 자금 이체 | H50: 지급수수료
B51: =B7 -> 하나 #304 | C51: 2024.01.18 | D51: 전준영 | E51: 3000000 | G51: 가수금 입금 | H51: 가수금
B52: =B7 -> 하나 #304 | C52: 2024.01.18 | D52: 기술보증기금 | F52: 2800000 | G52: 보증료 지급 | H52: 지급수수료
B53: =B7 -> 하나 #304 | C53: 2024.01.18 | D53: 하나은행 | F53: 500 | G53: 송금 수수료 지급 | H53: 지급수수료
B54: =B7 -> 하나 #304 | C54: 2024.01.18 | D54: 기술보증기금 | F54: 800000 | G54: 기술평가료 지급 | H54: 지급수수료
B55: =B7 -> 하나 #304 | C55: 2024.01.18 | D55: 하나은행 | F55: 500 | G55: 송금 수수료 지급 | H55: 지급수수료
B56: =B10 -> 기업 #020 | C56: 2024.01.18 | D56: 기보 기금 입금 | E56: 400000000 | G56: 기보 대출금 입금 | H56: 단기차입금
B57: =B56 -> 기업 #020 | C57: 2024.01.19 | D57: 주식회사 제로엑스앤드코리아 | F57: 200000000 | G57: 계좌간 자금 이체 | H57: 보통예금
B58: =B9 -> 기업 #019 | C58: 2024.01.19 | D58: 주식회사 제로엑스앤드코리아 | E58: 200000000 | G58: 계좌간 자금 이체 | H58: 보통예금
B59: =B10 -> 기업 #020 | C59: 2024.01.19 | D59: 주식회사 제로엑스앤드코리아 | F59: 15000000 | G59: 계좌간 자금 이체 | H59: 보통예금
B60: =B10 -> 기업 #020 | C60: 2024.01.19 | D60: 주식회사 제로엑스앤드코리아 | F60: 1000000 | G60: 계좌간 자금 이체 | H60: 보통예금
B61: =B5 -> 신한 #672 | C61: 2024.01.19 | D61: 주식회사 제로엑스앤드코리아 | E61: 1000000 | G61: 계좌간 자금 이체 | H61: 보통예금
B62: =B7 -> 하나 #304 | C62: 2024.01.19 | D62: 주식회사 제로엑스앤드코리아 | E62: 15000000 | G62: 계좌간 자금 이체 | H62: 보통예금
B63: =B7 -> 하나 #304 | C63: 2024.01.19 | D63: ZERO X AND PTE. LTD. | F63: 14006431 | G63: 마케팅비 지급 | H63: 마케팅비
B64: =B7 -> 하나 #304 | C64: 2024.01.19 | D64: 당발송금수수료 | F64: 55024 | G64: 송금 수수료 | H64: 지급수수료
B65: =B12 -> WISE USD | C65: 2024.01.19 | D65: ZERO X AND KOREA | E65: 10371.84 | G65: 마케팅비 입금 | H65: 마케팅비
B66: =B12 -> WISE USD | C66: 2024.01.20 | D66: Milestone Business Group | F66: 10375.98 | G66: Chris 1월 급여 | H66: 급여
B67: =B12 -> WISE USD | C67: 2024.01.20 | D67: Milestone Business Group | F67: 0.39 | G67: 송금 수수료 | H67: 지급수수료
B68: =B5 -> 신한 #672 | C68: 2024.01.22 | D68: 세콤(N5905012) | F68: 110000 | G68: 세콤(N5905012) | H68: 지급수수료
B69: =B9 -> 기업 #019 | C69: 2024.01.22 | D69: 기업은행 | E69: 1643 | G69: 예금이자 | H69: 이자수익
B70: =B9 -> 기업 #019 | C70: 2024.01.24 | D70: 주식회사 제로엑스앤드코리아 | F70: 2000000 | G70: 계좌간 자금 이체 | H70: 보통예금
B71: =B9 -> 기업 #019 | C71: 2024.01.24 | D71: 주식회사 제로엑스앤드코리아 | F71: 5000000 | G71: 계좌간 자금 이체 | H71: 보통예금
B72: =B5 -> 신한 #672 | C72: 2024.01.24 | D72: 주식회사 제로엑스앤드코리아 | E72: 2000000 | G72: 계좌간 자금 이체 | H72: 보통예금
B73: =B7 -> 하나 #304 | C73: 2024.01.24 | D73: 주식회사 제로엑스앤드코리아 | E73: 5000000 | G73: 계좌간 자금 이체 | H73: 보통예금
B74: =B7 -> 하나 #304 | C74: 2024.01.25 | D74: 하나카드기업 | F74: 3357541 | G74: 카드 대금 | H74: 지급수수료
B75: =B9 -> 기업 #019 | C75: 2024.01.25 | D75: 직원 | F75: 80736976 | G75: 급여 | H75: 급여
B76: =B9 -> 기업 #019 | C76: 2024.01.25 | D76: 문성화 | F76: 1030640 | G76: 현장실습 수당 지급(1/15~1/31) | H76: 급여
B77: =B9 -> 기업 #019 | C77: 2024.01.25 | D77: 메가존소프트(주) | F77: 3501989 | G77: Google Workspace Business Standard(연간/갱신) | H77: 지급수수료
B78: =B9 -> 기업 #019 | C78: 2024.01.25 | D78: 메가존소프트(주) | F78: 21052 | G78: Google Workspace Business Standard(일한계산) | H78: 지급수수료
B79: =B9 -> 기업 #019 | C79: 2024.01.25 | D79: 삼덕회계법인 | F79: 2750000 | G79: 평가 용역 수수료 | H79: 지급수수료
B80: =B9 -> 기업 #019 | C80: 2024.01.25 | D80: 주식회사 워크앤조이 | F80: 209220 | G80: 12월 그룹웨어 사용료 지급 | H80: 지급수수료
B81: =B9 -> 기업 #019 | C81: 2024.01.25 | D81: 주식회사 에스제이코어 | F81: 4950000 | G81: 2023년 종합검진 지급 | H81: 지급수수료
B82: =B9 -> 기업 #019 | C82: 2024.01.25 | D82: 노무법인도원 | F82: 792000 | G82: 청년일자리도약장려금 수임료 | H82: 지급수수료
B83: =B5 -> 신한 #672 | C83: 2024.01.25 | D83: 바디프랜드10 | F83: 98000 | G83: 안마의자 | H83: 복리후생비
B84: =B5 -> 신한 #672 | C84: 2024.01.25 | D84: 코웨이렌탈10 | F84: 37430 | G84: 공청기 | H84: 복리후생비
B85: =B5 -> 신한 #672 | C85: 2024.01.25 | D85: 코웨이렌탈10 | F85: 37430 | G85: 공청기 | H85: 복리후생비
B86: =B5 -> 신한 #672 | C86: 2024.01.25 | D86: 코웨이렌탈10 | F86: 20660 | G86: 비데 | H86: 복리후생비
B87: =B5 -> 신한 #672 | C87: 2024.01.25 | D87: 코웨이렌탈10 | F87: 50250 | G87: 정수기 | H87: 복리후생비
B88: =B5 -> 신한 #672 | C88: 2024.01.25 | D88: 코웨이렌탈10 | F88: 20660 | G88: 비데 | H88: 복리후생비
B89: =B5 -> 신한 #672 | C89: 2024.01.25 | D89: 삼덕회계법인 | F89: 330000 | G89: 회계 자문료 지급 | H89: 지급수수료
B90: =B5 -> 신한 #672 | C90: 2024.01.25 | D90: KT0540091110 | F90: 56990 | G90: 인터넷, 전화 요금 지급 | H90: 복리후생비
B91: =B5 -> 신한 #672 | C91: 2024.01.25 | D91: 현대카드 | F91: 1847209 | G91: 카드대금 지급 | H91: 지급수수료
B92: =B9 -> 기업 #019 | C92: 2024.01.31 | D92: 주식회사 제로엑스앤드코리아 | F92: 15000000 | G92: 계좌간 자금 이체 | H92: 보통예금
B93: =B7 -> 하나 #304 | C93: 2024.01.31 | D93: 주식회사 제로엑스앤드코리아 | E93: 15000000 | G93: 계좌간 자금 이체 | H93: 보통예금
B94: =B7 -> 하나 #304 | C94: 2024.01.31 | D94: ZERO X AND PTE. LTD. | F94: 13968144 | G94: 마케팅비 지급 | H94: 마케팅비
B95: =B7 -> 하나 #304 | C95: 2024.01.31 | D95: 당발송금수수료 | F95: 54950 | G95: 송금 수수료 | H95: 지급수수료
B96: =B12 -> WISE USD | C96: 2024.01.31 | D96: ZERO X AND KOREA | E96: 10371.84 | G96: 마케팅비 입금 | H96: 마케팅비
B97: =B5 -> 신한 #672 | C97: 2024.01.31 | D97: 안양신도판매 | F97: 77000 | G97: 복합기 사용료 지급 | H97: 지급수수료

Sheet 24.02월
B1: 자 금 일 보
I2: Currency | J2: KRW | L2: 계정과목 | M2: 설명
B3: ※ 자금현황 | G3: 기준일: 2024.02.29 | I3: USD | J3: =IFERROR(__xludf.DUMMYFUNCTION("GOOGLEFINANCE(""USDKRW"")"),1472.7250000000001) -> 1472.725 | L3: 광고매출 | M3: 타법인 매출
B4: 구 분 | C4: 단위 | D4: 전월잔액 | E4: 수 입 | F4: 지 출 | G4: 기준일 기준 잔액 | I4: SGD | J4: =IFERROR(__xludf.DUMMYFUNCTION("GOOGLEFINANCE(""SGDKRW"")"),1143.885) -> 1143.885 | L4: 급여 | M4: 직원 급여
B5: 신한 #672 | C5: KRW | D5: ='24.01월'!G5 -> 321483 | E5: =sumif(B25:B134,B5,E25:E134) -> 27518190 | F5: =sumif(B25:B135,B5,F25:F135) -> 21822397 | G5: =D5+E5-F5 -> 6017276 | L5: 미수금 | M5: 돌려 받을 예정인 금액 (ex. 부가세 환급금)
B6: 신한 #543 | C6: USD | D6: ='24.01월'!G6 -> 2.31 | E6: =sumif(B25:B134,B6,E25:E134) -> 0 | F6: =sumif(B25:B134,B6,F25:F134) -> 0 | G6: =D6+E6-F6 -> 2.31 | L6: 보증금 | M6: 보증금 (사무실 임대, 장비 리스 등)
B7: 하나 #304 | C7: KRW | D7: ='24.01월'!G7 -> 3755912 | E7: =sumif(B25:B134,B7,E25:E134) -> 40000000 | F7: =sumif(B25:B134,B7,F25:F134) -> 39849163 | G7: =D7+E7-F7 -> 3906749 | L7: 보통예금 | M7: 예금간 이체
B8: 하나 #138 | C8: USD | D8: ='24.01월'!G8 -> 3.35 | E8: =sumif(B25:B134,B8,E25:E134) -> 0 | F8: =sumif(B25:B134,B8,F25:F134) -> 0 | G8: =D8+E8-F8 -> 3.35 | L8: 복리후생비 | M8: 회식, 식대
B9: 기업 #019 | C9: KRW | D9: ='24.01월'!G9 -> 84009766 | E9: =sumif(B25:B135,B9,E25:E135) -> 184006638 | F9: =sumif(B25:B136,B9,F25:F136) -> 181345433 | G9: =D9+E9-F9 -> 86670971 | H9: 일반계좌 | L9: 비품 | M9: 가구, 가전등 개당 단가 150만원이 넘는 용품
B10: 기업 #020 | C10: KRW | D10: ='24.01월'!G10 -> 184000000 | E10: =sumif(B25:B136,B10,E25:E136) -> 0 | F10: =sumif(B25:B137,B10,F25:F137) -> 184000000 | G10: =D10+E10-F10 -> 0 | H10: 기보보증금 | L10: 사무용품비 | M10: 비품, 소모품비를 제외한 업무용 사무용품 구입
B11: 기업 #010 | C11: USD | D11: ='24.01월'!G11 -> 0 | E11: =sumif(B25:B137,B11,E25:E137) -> 0 | F11: =sumif(B25:B137,B11,F25:F137) -> 0 | G11: =D11+E11-F11 -> 0 | L11: 서비스용역매출 | M11: 매출
B12: WISE USD | C12: USD | D12: ='24.01월'!G12 -> 10874.52 | E12: =sumif(B25:B134,B12,E25:E134) -> 25995.86 | F12: =sumif(B25:B134,B12,F25:F134) -> 26026.41 | G12: =D12+E12-F12 -> 10843.97 | L12: 세금과공과 | M12: 세금 납부시
B13: WISE SGD | C13: SGD | D13: ='24.01월'!G13 -> 105.4 | E13: =sumif(B25:B132,B13,E25:E132) -> 0 | F13: =sumif(B25:B134,B13,F25:F134) -> 0 | G13: =D13+E13-F13 -> 105.4 | L13: 소모품비 | M13: 비품(150만원)으로 잡기에는 금액이 작은 비품
B14: WISE KRW | C14: KRW | D14: ='24.01월'!G14 -> 0 | E14: =sumif(B25:B134,B14,E25:E134) -> 0 | F14: =sumif(B25:B74,B14,F25:F134) -> 0 | G14: =D14+E14-F14 -> 0 | L14: 여비교통비 | M14: 출장, 대중교통, 대리운전
B15: OCBC USD | C15: USD | D15: ='24.01월'!G15 -> 1160.62 | E15: =sumif(B25:B135,B15,E25:E135) -> 350030.67 | F15: =sumif(B25:B135,B15,F25:F135) -> 0 | G15: =D15+E15-F15 -> 351191.29 | L15: 용역비 | M15: 외주용역비
B16: OCBC SGD | C16: SGD | D16: ='24.01월'!G16 -> 1155.59 | E16: =sumif(B25:B135,B16,E25:E135) -> 0 | F16: =sumif(B25:B135,B16,F25:F135) -> 896 | G16: =D16+E16-F16 -> 259.59 | L16: 접대비 | M16: 외부 미팅
H17: 기준일 기준 잔액 | I17: 전월잔액 | L17: 지급수수료 | M17: sms 수수료, 송금 수수료, 일반적으로 발생되는 모든 비용
B18: KRW 합 계 | D18: =D5+D7+D14+D9+D10 -> 272087161 | E18: =E5+E7+E14+E9+E10 -> 251524828 | F18: =F5+F7+F14+F9+F10 -> 427016993 | G18: =G5+G7+G14+G9+G10 -> 96594996 | H18: =G18 -> 96594996 | I18: =D18 -> 272087161 | L18: 이자수익 | M18: 은행이자
B19: USD 합 계 | D19: =D6+D8+D12+D15+D11 -> 12040.8 | E19: =E6+E8+E12+E15+E11 -> 376026.53 | F19: =F6+F8+F12+F15+F11 -> 26026.41 | G19: =G6+G8+G12+G15+G11 -> 362040.92 | H19: =rounddown(G19*$J$3,0) -> 533186713 | I19: =rounddown(D19*$J$3,0) -> 17732787 | L19: 통신비 | M19: 등기, 퀵 사용비
B20: SGD 합 계 | D20: =D13+D16 -> 1260.99 | E20: =E13+E16 -> 0 | F20: =F13+F16 -> 896 | G20: =G13+G16 -> 364.99 | H20: =rounddown(G20*$J$4,0) -> 417506 | I20: =rounddown(D20*$J$4,0) -> 1442427 | L20: 마케팅비 | M20: PR 기사등 마케팅 비용
H21: =SUM(H18:H20) -> 630199215 | I21: =SUM(I18:I20) -> 291262375 | L21: 대여금 | M21: 싱가폴 -> 한국 지사 송금
H22: =H21-I21 -> 338936840 | L22: 출장비 | M22: 출장여비
B23: ※ 세부내역 | L23: 투자자산 | M23: 투자
B24: 구 분 | C24: 날 짜 | D24: 은 행 적 요 | E24: 수입 | F24: 지출 | G24: 상세메모 | H24: 계정과목 | L24: 가수금 | M24: 가수금
B25: =B9 -> 기업 #019 | C25: 2024.02.01 | D25: 그림바우빌딩 | F25: 6392870 | G25: 1월 임대료,관리비,전기료 | H25: 지급수수료 | L25: 잡이익 | M25: 잡이익
B26: =B9 -> 기업 #019 | C26: 2024.02.01 | D26: 비앤케이 | F26: 825000 | G26: 1월 법률자문료 | H26: 지급수수료 | L26: 정기예적금 | M26: 정기예적금
B27: =B12 -> WISE USD | C27: 2024.02.01 | D27: Milestone Business Group | F27: 10375.98 | G27: Chris 2월 급여 | H27: 급여 | L27: 단기차입금 | M27: 기보 대출금
B28: =B12 -> WISE USD | C28: 2024.02.01 | D28: Milestone Business Group | F28: 0.39 | G28: 수수료 지급 | H28: 지급수수료 | L28: 이자비용 | M28: 기보 대출이자
B29: =B5 -> 신한 #672 | C29: 2024.02.02 | D29: 강남세무서 | E29: 7518190 | G29: 부가세 환급 | H29: 세금과공과
B30: =B5 -> 신한 #672 | C30: 2024.02.05 | D30: 특허공제02회 | F30: 300000 | G30: 특허공제02회 | H30: 정기예적금
B31: =B5 -> 신한 #672 | C31: 2024.02.13 | D31: 2401국민건강 | F31: 7001780 | G31: 2401국민건강 | H31: 세금과공과
B32: =B5 -> 신한 #672 | C32: 2024.02.13 | D32: 2401산재보험 | F32: 531240 | G32: 2401산재보험 | H32: 세금과공과
B33: =B5 -> 신한 #672 | C33: 2024.02.13 | D33: 주식회사 제로엑스앤드코리아 | E33: 20000000 | G33: 계좌간 자금 이체 | H33: 보통예금
B34: =B5 -> 신한 #672 | C34: 2024.02.13 | D34: 2401 국민연금 | F34: 6934720 | G34: 2401 국민연금 | H34: 세금과공과
B35: =B5 -> 신한 #672 | C35: 2024.02.13 | D35: 2401 고용보험 | F35: 1512970 | G35: 2401 고용보험 | H35: 세금과공과
B36: =B9 -> 기업 #019 | C36: 2024.02.13 | D36: 국세청 | F36: 6907710 | G36: 1월 근로 소득세 | H36: 세금과공과
B37: =B9 -> 기업 #019 | C37: 2024.02.13 | D37: 국세청 | F37: 90400 | G37: 1월 기타 소득세 | H37: 세금과공과
B38: =B9 -> 기업 #019 | C38: 2024.02.13 | D38: 강남구청 | F38: 699730 | G38: 1월 지방 소득세 | H38: 세금과공과
B39: =B9 -> 기업 #019 | C39: 2024.02.13 | D39: 주식회사 워크앤조이 | F39: 196200 | G39: 1월 그룹웨어 사용료 지급 | H39: 지급수수료
B40: =B9 -> 기업 #019 | C40: 2024.02.13 | D40: 전준영 | F40: 500000 | G40: 태국 출장여비 지급 | H40: 출장비
B41: =B9 -> 기업 #019 | C41: 2024.02.13 | D41: 주식회사 제로엑스앤드코리아 | F41: 20000000 | G41: 계좌간 자금 이체 | H41: 보통예금
B42: =B9 -> 기업 #019 | C42: 2024.02.13 | D42: 주식회사 제로엑스앤드코리아 | F42: 10000000 | G42: 계좌간 자금 이체 | H42: 보통예금
B43: =B7 -> 하나 #304 | C43: 2024.02.13 | D43: 주식회사 제로엑스앤드코리아 | E43: 10000000 | G43: 계좌간 자금 이체 | H43: 보통예금
B44: =B12 -> WISE USD | C44: 2024.02.14 | D44: Postmarkapp.com | F44: 10 | G44: 서비스 이용료 지급 | H44: 지급수수료
B45: =B15 -> OCBC USD | C45: 2024.02.14 | D45: Havah | E45: 100013.62 | G45: 투자금 입금 | H45: 투자자산
B46: =B9 -> 기업 #019 | C46: 2024.02.19 | D46: 이자 | F46: 1043158 | G46: 대출금 이자 지급 | H46: 이자비용
B47: =B9 -> 기업 #019 | C47: 2024.02.19 | D47: 2024 결산 | E47: 6638 | G47: 예금이자 | H47: 이자수익
B48: =B9 -> 기업 #019 | C48: 2024.02.22 | D48: 주식회사 제로엑스앤드코리아 | E48: 184000000 | G48: 계좌간 자금 이체 | H48: 보통예금
B49: =B10 -> 기업 #020 | C49: 2024.02.22 | D49: 주식회사 제로엑스앤드코리아 | F49: 184000000 | G49: 계좌간 자금 이체 | H49: 보통예금
B50: =B7 -> 하나 #304 | C50: 2024.02.26 | D50: 하나카드기업 | F50: 4866073 | G50: 카드 대금 | H50: 지급수수료
B51: =B7 -> 하나 #304 | C51: 2024.02.27 | D51: 주식회사 제로엑스앤드코리아 | E51: 30000000 | G51: 계좌간 자금 이체 | H51: 보통예금
B52: =B5 -> 신한 #672 | C52: 2024.02.21 | D52: 세콤(N5905012) | F52: 110000 | G52: 세콤(N5905012) | H52: 지급수수료
B53: =B5 -> 신한 #672 | C53: 2024.02.26 | D53: 바디프랜드10 | F53: 98000 | G53: 안마의자 | H53: 복리후생비
B54: =B5 -> 신한 #672 | C54: 2024.02.26 | D54: 코웨이렌탈10 | F54: 37430 | G54: 공청기 | H54: 복리후생비
B55: =B5 -> 신한 #672 | C55: 2024.02.26 | D55: 코웨이렌탈10 | F55: 37430 | G55: 공청기 | H55: 복리후생비
B56: =B5 -> 신한 #672 | C56: 2024.02.26 | D56: 코웨이렌탈10 | F56: 20660 | G56: 비데 | H56: 복리후생비
B57: =B5 -> 신한 #672 | C57: 2024.02.26 | D57: 코웨이렌탈10 | F57: 50250 | G57: 정수기 | H57: 복리후생비
B58: =B5 -> 신한 #672 | C58: 2024.02.26 | D58: 코웨이렌탈10 | F58: 20660 | G58: 비데 | H58: 복리후생비
B59: =B5 -> 신한 #672 | C59: 2024.02.26 | D59: 삼덕회계법인 | F59: 330000 | G59: 회계 자문료 지급 | H59: 지급수수료
B60: =B5 -> 신한 #672 | C60: 2024.02.26 | D60: KT0540091110 | F60: 55910 | G60: 인터넷, 전화 요금 지급 | H60: 복리후생비
B61: =B5 -> 신한 #672 | C61: 2024.02.26 | D61: 현대카드 | F61: 4704347 | G61: 카드대금 지급 | H61: 지급수수료
B62: =B9 -> 기업 #019 | C62: 2024.02.23 | D62: 직원 | F62: 102706626 | G62: 급여 | H62: 급여
B63: =B9 -> 기업 #019 | C63: 2024.02.23 | D63: 강진석 | F63: 51600 | G63: 개인경비 지급 | H63: 급여
B64: =B9 -> 기업 #019 | C64: 2024.02.23 | D64: 문성화 | F64: 1879396 | G64: 현장실습 수당 지급 | H64: 급여
B65: =B9 -> 기업 #019 | C65: 2024.02.23 | D65: 기업카드 | F65: 52743 | G65: 카드대금 지급 | H65: 지급수수료
B66: =B9 -> 기업 #019 | C66: 2024.02.27 | D66: 주식회사 제로엑스앤드코리아 | F66: 30000000 | G66: 계좌간 자금 이체 | H66: 보통예금
B67: =B7 -> 하나 #304 | C67: 2024.02.27 | D67: ZERO X AND PTE. LTD. | F67: 34923200 | G67: 마케팅비 지급 | H67: 마케팅비
B68: =B7 -> 하나 #304 | C68: 2024.02.27 | D68: 당발송금수수료 | F68: 59890 | G68: 송금 수수료 | H68: 지급수수료
B69: =B12 -> WISE USD | C69: 2024.02.26 | D69: IconScout | F69: 155.99 | G69: 서비스 이용료 지급 | H69: 지급수수료
B70: =B12 -> WISE USD | C70: 2024.02.27 | D70: Silas Yip Kwok Fei | F70: 60.57 | G70: 자사주 50주에 대한 대금 비용 | H70: 지급수수료
B71: =B12 -> WISE USD | C71: 2024.02.27 | D71: 주식회사 제로엑스앤드코리아 | E71: 25995.86 | G71: 마케팅비 입급 | H71: 마케팅비
B72: =B12 -> WISE USD | C72: 2024.02.28 | D72: Entra Law LLC | F72: 14953.69 | G72: 법무비용 | H72: 지급수수료
B73: =B12 -> WISE USD | C73: 2024.02.28 | D73: Wise | F73: 85.79 | G73: 송금 수수료 | H73: 지급수수료
B74: =B12 -> WISE USD | C74: 2024.02.28 | D74: Gitbook inc | F74: 384 | G74: 업무용 tool 사용 | H74: 지급수수료
B75: =B5 -> 신한 #672 | C75: 2024.02.29 | D75: 안양신도판매 | F75: 77000 | G75: 복합기 사용료 지급 | H75: 지급수수료
B76: OCBC SGD | C76: 2024.02.05 | D76: OCBC | F76: 10 | G76: 송금 수수료 | H76: 지급수수료
B77: OCBC SGD | C77: 2024.02.29 | D77: ATOZ | F77: 436 | G77: GST Report 1Q'24 GST 보고 | H77: 지급수수료
B78: OCBC SGD | C78: 2024.02.29 | D78: EBOS | F78: 450 | G78: Full XBRL | H78: 지급수수료
B79: OCBC USD | C79: 2024.02.29 | D79: SKY MAVIS | E79: 250017.05 | G79: 투자금 입금 | H79: 투자자산

Sheet 24.03월
B1: 자 금 일 보
I2: Currency | J2: KRW | L2: 계정과목 | M2: 설명
B3: ※ 자금현황 | G3: 기준일: 2024.03.29 | I3: USD | J3: =IFERROR(__xludf.DUMMYFUNCTION("GOOGLEFINANCE(""USDKRW"")"),1472.7250000000001) -> 1472.725 | L3: 광고매출 | M3: 타법인 매출
B4: 구 분 | C4: 단위 | D4: 전월잔액 | E4: 수 입 | F4: 지 출 | G4: 기준일 기준 잔액 | I4: SGD | J4: =IFERROR(__xludf.DUMMYFUNCTION("GOOGLEFINANCE(""SGDKRW"")"),1143.885) -> 1143.885 | L4: 급여 | M4: 직원 급여
B5: 신한 #672 | C5: KRW | D5: ='24.02월'!G5 -> 6017276 | E5: =sumif(B25:B142,B5,E25:E142) -> 15001387 | F5: =sumif(B25:B143,B5,F25:F143) -> 19743766 | G5: =D5+E5-F5 -> 1274897 | L5: 미수금 | M5: 돌려 받을 예정인 금액 (ex. 부가세 환급금)
B6: 신한 #543 | C6: USD | D6: ='24.02월'!G6 -> 2.31 | E6: =sumif(B25:B142,B6,E25:E142) -> 0 | F6: =sumif(B25:B142,B6,F25:F142) -> 0 | G6: =D6+E6-F6 -> 2.31 | L6: 보증금 | M6: 보증금 (사무실 임대, 장비 리스 등)
B7: 하나 #304 | C7: KRW | D7: ='24.02월'!G7 -> 3906749 | E7: =sumif(B25:B142,B7,E25:E142) -> 2802969 | F7: =sumif(B25:B142,B7,F25:F142) -> 6343628 | G7: =D7+E7-F7 -> 366090 | L7: 보통예금 | M7: 예금간 이체
B8: 하나 #138 | C8: USD | D8: ='24.02월'!G8 -> 3.35 | E8: =sumif(B25:B142,B8,E25:E142) -> 0 | F8: =sumif(B25:B142,B8,F25:F142) -> 0 | G8: =D8+E8-F8 -> 3.35 | L8: 복리후생비 | M8: 회식, 식대
B9: 기업 #019 | C9: KRW | D9: ='24.02월'!G9 -> 86670971 | E9: =sumif(B25:B143,B9,E25:E143) -> 32256370 | F9: =sumif(B25:B144,B9,F25:F144) -> 118215227 | G9: =D9+E9-F9 -> 712114 | H9: 일반계좌 | L9: 비품 | M9: 가구, 가전등 개당 단가 150만원이 넘는 용품
B10: 기업 #020 | C10: KRW | D10: ='24.02월'!G10 -> 0 | E10: =sumif(B25:B144,B10,E25:E144) -> 0 | F10: =sumif(B25:B145,B10,F25:F145) -> 0 | G10: =D10+E10-F10 -> 0 | H10: 기보보증금 | L10: 사무용품비 | M10: 비품, 소모품비를 제외한 업무용 사무용품 구입
B11: 기업 #010 | C11: USD | D11: ='24.02월'!G11 -> 0 | E11: =sumif(B25:B145,B11,E25:E145) -> 0 | F11: =sumif(B25:B145,B11,F25:F145) -> 0 | G11: =D11+E11-F11 -> 0 | L11: 서비스용역매출 | M11: 매출
B12: WISE USD | C12: USD | D12: ='24.02월'!G12 -> 10843.97 | E12: =sumif(B25:B142,B12,E25:E142) -> 0 | F12: =sumif(B25:B142,B12,F25:F142) -> 10613.17 | G12: =D12+E12-F12 -> 230.8 | L12: 세금과공과 | M12: 세금 납부시
B13: WISE SGD | C13: SGD | D13: ='24.02월'!G13 -> 105.4 | E13: =sumif(B25:B140,B13,E25:E140) -> 0 | F13: =sumif(B25:B142,B13,F25:F142) -> 80 | G13: =D13+E13-F13 -> 25.4 | L13: 소모품비 | M13: 비품(150만원)으로 잡기에는 금액이 작은 비품
B14: WISE KRW | C14: KRW | D14: ='24.02월'!G14 -> 0 | E14: =sumif(B25:B142,B14,E25:E142) -> 0 | F14: =sumif(B25:B82,B14,F25:F142) -> 0 | G14: =D14+E14-F14 -> 0 | L14: 여비교통비 | M14: 출장, 대중교통, 대리운전
B15: OCBC USD | C15: USD | D15: ='24.02월'!G15 -> 351191.29 | E15: =sumif(B25:B143,B15,E25:E85) -> 100003.62 | F15: =sumif(B25:B143,B15,F25:F143) -> 486.89 | G15: =D15+E15-F15 -> 450708.02 | L15: 용역비 | M15: 외주용역비
B16: OCBC SGD | C16: SGD | D16: ='24.02월'!G16 -> 259.59 | E16: =sumif(B25:B143,B16,E25:E143) -> 73.6 | F16: =sumif(B25:B143,B16,F25:F143) -> 25 | G16: =D16+E16-F16 -> 308.19 | L16: 접대비 | M16: 외부 미팅
H17: 기준일 기준 잔액 | I17: 전월잔액 | L17: 지급수수료 | M17: sms 수수료, 송금 수수료, 일반적으로 발생되는 모든 비용
B18: KRW 합 계 | D18: =D5+D7+D14+D9+D10 -> 96594996 | E18: =E5+E7+E14+E9+E10 -> 50060726 | F18: =F5+F7+F14+F9+F10 -> 144302621 | G18: =G5+G7+G14+G9+G10 -> 2353101 | H18: =G18 -> 2353101 | I18: =D18 -> 96594996 | L18: 이자수익 | M18: 은행이자
B19: USD 합 계 | D19: =D6+D8+D12+D15+D11 -> 362040.92 | E19: =E6+E8+E12+E15+E11 -> 100003.62 | F19: =F6+F8+F12+F15+F11 -> 11100.06 | G19: =G6+G8+G12+G15+G11 -> 450944.48 | H19: =rounddown(G19*$J$3,0) -> 664117209 | I19: =rounddown(D19*$J$3,0) -> 533186713 | L19: 통신비 | M19: 등기, 퀵 사용비
B20: SGD 합 계 | D20: =D13+D16 -> 364.99 | E20: =E13+E16 -> 73.6 | F20: =F13+F16 -> 105 | G20: =G13+G16 -> 333.59 | H20: =rounddown(G20*$J$4,0) -> 381588 | I20: =rounddown(D20*$J$4,0) -> 417506 | L20: 마케팅비 | M20: PR 기사등 마케팅 비용
H21: =SUM(H18:H20) -> 666851898 | I21: =SUM(I18:I20) -> 630199215 | L21: 대여금 | M21: 싱가폴 -> 한국 지사 송금
H22: =H21-I21 -> 36652683 | L22: 출장비 | M22: 출장여비
B23: ※ 세부내역 | L23: 투자자산 | M23: 투자
B24: 구 분 | C24: 날 짜 | D24: 은 행 적 요 | E24: 수입 | F24: 지출 | G24: 상세메모 | H24: 계정과목 | L24: 가수금 | M24: 가수금
B25: =B12 -> WISE USD | C25: 2024.03.01 | D25: Milestone Business Group | F25: 10375.98 | G25: Chris 3월 급여 | H25: 급여 | L25: 잡이익 | M25: 잡이익
B26: =B12 -> WISE USD | C26: 2024.03.01 | D26: Milestone Business Group | F26: 0.39 | G26: 수수료 지급 | H26: 지급수수료 | L26: 정기예적금 | M26: 정기예적금
B27: =B12 -> WISE USD | C27: 2024.03.01 | D27: Milestone Business Group | F27: 226.41 | G27: 개인 경비 지급 | H27: 복리후생비 | L27: 단기차입금 | M27: 기보 대출금
B28: =B12 -> WISE USD | C28: 2024.03.01 | D28: Milestone Business Group | F28: 0.39 | G28: 수수료 지급 | H28: 지급수수료 | L28: 이자비용 | M28: 기보 대출이자
B29: =B9 -> 기업 #019 | C29: 2023.03.04 | D29: 그림바우빌딩 | F29: 6332040 | G29: 2월 임대료,관리비,전기료 | H29: 지급수수료
B30: =B9 -> 기업 #019 | C30: 2023.03.04 | D30: 비앤케이 | F30: 825000 | G30: 2월 법률자문료 | H30: 지급수수료
B31: =B9 -> 기업 #019 | C31: 2023.03.04 | D31: 주식회사 워크앤조이 | F31: 196200 | G31: 2월 그룹웨어 사용료 지급 | H31: 지급수수료
B32: =B9 -> 기업 #019 | C32: 2023.03.05 | D32: 웹투어 | F32: 30000 | G32: 항공 취소 수수료 | H32: 지급수수료
B33: =B5 -> 신한 #672 | C33: 2023.03.05 | D33: 특허공제03회 | F33: 300000 | G33: 특허공제03회 | H33: 정기예적금
B34: =B9 -> 기업 #019 | C34: 2023.03.11 | D34: 주식회사 제로엑스앤드코리아 | F34: 15000000 | G34: 계좌간 자금 이체 | H34: 보통예금
B35: =B5 -> 신한 #672 | C35: 2023.03.11 | D35: 주식회사 제로엑스앤드코리아 | E35: 15000000 | G35: 계좌간 자금 이체 | H35: 보통예금
B36: =B5 -> 신한 #672 | C36: 2023.03.11 | D36: 2402고용보험 | F36: 1512970 | G36: 2402고용보험 | H36: 세금과공과
B37: =B5 -> 신한 #672 | C37: 2023.03.11 | D37: 2402산재보험 | F37: 544840 | G37: 2402산재보험 | H37: 세금과공과
B38: =B5 -> 신한 #672 | C38: 2023.03.11 | D38: 2402국민건강 | F38: 7001780 | G38: 2402국민건강 | H38: 세금과공과
B39: =B5 -> 신한 #672 | C39: 2023.03.11 | D39: 2402국민연금 | F39: 6934720 | G39: 2402국민연금 | H39: 세금과공과
B40: =B9 -> 기업 #019 | C40: 2024.03.18 | D40: 이자 | F40: 975857 | G40: 대출금 이자 지급 | H40: 이자비용
B41: =B9 -> 기업 #019 | C41: 2024.03.18 | D41: 2024 결산 | E41: 6370 | G41: 예금이자 | H41: 이자수익
B42: =B7 -> 하나 #304 | C42: 2024.03.18 | D42: 2024 결산 | E42: 2969 | G42: 예금이자 | H42: 이자수익
B43: =B12 -> WISE USD | C43: 2024.02.14 | D43: Postmarkapp.com | F43: 10 | G43: 서비스 이용료 지급 | H43: 지급수수료
B44: =B9 -> 기업 #019 | C44: 2024.03.20 | D44: 강진석 | E44: 10000000 | G44: 대여금 | H44: 대여금
B45: =B9 -> 기업 #019 | C45: 2024.03.20 | D45: 강진석 | E45: 10000000 | G45: 대여금 | H45: 대여금
B46: =B9 -> 기업 #019 | C46: 2024.03.20 | D46: 강진석 | E46: 10000000 | G46: 대여금 | H46: 대여금
B47: =B9 -> 기업 #019 | C47: 2024.03.20 | D47: 강진석 | E47: 250000 | G47: 대여금 | H47: 대여금
B48: =B9 -> 기업 #019 | C48: 2024.03.22 | D48: 주식회사 제로엑스앤드코리아 | F48: 1000000 | G48: 계좌간 자금 이체 | H48: 보통예금
B49: =B7 -> 하나 #304 | C49: 2024.03.22 | D49: 주식회사 제로엑스앤드코리아 | E49: 1000000 | G49: 계좌간 자금 이체 | H49: 보통예금
B50: =B5 -> 신한 #672 | C50: 2024.03.23 | D50: 이자 | E50: 1387 | G50: 이자 | H50: 이자수익
B51: =B9 -> 기업 #019 | C51: 2024.03.25 | D51: 직원 | F51: 86181201 | G51: 급여 | H51: 급여
B52: =B5 -> 신한 #672 | C52: 2024.03.25 | D52: 현대카드 | F52: 2612156 | G52: 현대카드 | H52: 지급수수료
B53: =B7 -> 하나 #304 | C53: 2024.03.25 | D53: 하나카드 | F53: 4343128 | G53: 하나카드 | H53: 지급수수료
B54: =B9 -> 기업 #019 | C54: 2024.03.25 | D54: 기업카드 | F54: 4367649 | G54: 기업카드 | H54: 지급수수료
B55: =B5 -> 신한 #672 | C55: 2024.03.25 | D55: 세콤(N5905012) | F55: 110000 | G55: 세콤(N5905012) | H55: 지급수수료
B56: =B5 -> 신한 #672 | C56: 2024.03.25 | D56: 바디프랜드10 | F56: 98000 | G56: 안마의자 | H56: 복리후생비
B57: =B5 -> 신한 #672 | C57: 2024.03.25 | D57: 코웨이렌탈10 | F57: 37430 | G57: 공청기 | H57: 복리후생비
B58: =B5 -> 신한 #672 | C58: 2024.03.25 | D58: 코웨이렌탈10 | F58: 37430 | G58: 공청기 | H58: 복리후생비
B59: =B5 -> 신한 #672 | C59: 2024.03.25 | D59: 코웨이렌탈10 | F59: 20660 | G59: 비데 | H59: 복리후생비
B60: =B5 -> 신한 #672 | C60: 2024.03.25 | D60: 코웨이렌탈10 | F60: 50250 | G60: 정수기 | H60: 복리후생비
B61: =B5 -> 신한 #672 | C61: 2024.03.25 | D61: 코웨이렌탈10 | F61: 20660 | G61: 비데 | H61: 복리후생비
B62: =B5 -> 신한 #672 | C62: 2024.03.25 | D62: 삼덕회계법인 | F62: 330000 | G62: 회계 자문료 지급 | H62: 지급수수료
B63: =B5 -> 신한 #672 | C63: 2024.03.25 | D63: KT0540091110 | F63: 55870 | G63: 인터넷, 전화 요금 지급 | H63: 복리후생비
B64: =B7 -> 하나 #304 | C64: 2024.03.26 | D64: 고용노동부 | E64: 1800000 | G64: 청년일자리도약장려금 (밀리) | H64: 잡이익
B65: OCBC USD | C65: 2024.03.15 | D65: WISEBRICK CO | E65: 100003.62 | G65: 투자금 입금 | H65: 투자자산
B66: OCBC USD | C66: 2024.03.15 | D66: OCBC | F66: 7.42 | G66: 송금 수수료 | H66: 지급수수료
B67: OCBC USD | C67: 2024.03.26 | D67: ATOZ | F67: 464.49 | G67: ATOZ SGD 620 (Pre-A Phase 2 투자 등기 신고) | H67: 지급수수료
B68: OCBC USD | C68: 2024.03.26 | D68: OCBC | F68: 14.98 | G68: 송금 수수료 | H68: 지급수수료
B69: OCBC SGD | C69: 2024.03.04 | D69: OCBC | F69: 10 | G69: 은행 수수료 | H69: 지급수수료
B70: OCBC SGD | C70: 2024.03.05 | D70: GST | E70: 73.6 | G70: GST 2024 1Q 환급 | H70: 세금과공과
B71: =B7 -> 하나 #304 | C71: 2024.03.29 | D71: 주식회사 제로엑스앤드코리아 | F71: 2000000 | G71: 계좌간 자금 이체 | H71: 보통예금
B72: =B7 -> 하나 #304 | C72: 2024.03.29 | D72: 하나은행 | F72: 500 | G72: 송금 수수료 | H72: 지급수수료
B73: =B9 -> 기업 #019 | C73: 2024.03.29 | D73: 주식회사 제로엑스앤드코리아 | E73: 2000000 | G73: 계좌간 자금 이체 | H73: 보통예금
B74: =B9 -> 기업 #019 | C74: 2024.03.29 | D74: 연 법무사합동사무소 | F74: 707280 | G74: 정관변경(상호),임원변경(각자대표) | H74: 지급수수료
B75: =B9 -> 기업 #019 | C75: 2024.03.29 | D75: 최지현 | F75: 2600000 | G75: 맥북 구입 대금 지급 | H75: 사무용품비
B76: =B13 -> WISE SGD | C76: 2024.03.25 | D76: Xero | F76: 80 | G76: 서비스 이용료 | H76: 지급수수료
B77: =B5 -> 신한 #672 | C77: 2024.03.29 | D77: 안양신도판매 | F77: 77000 | G77: 복합기 사용료 지급 | H77: 지급수수료
B78: OCBC SGD | C78: 2024.03.31 | D78: OCBC | F78: 15 | G78: 은행 수수료 | H78: 지급수수료

Sheet 24.04월
B1: 자 금 일 보
I2: Currency | J2: KRW | L2: 계정과목 | M2: 설명
B3: ※ 자금현황 | G3: 기준일: 2024.04.30 | I3: USD | J3: =IFERROR(__xludf.DUMMYFUNCTION("GOOGLEFINANCE(""USDKRW"")"),1472.7250000000001) -> 1472.725 | L3: 광고매출 | M3: 타법인 매출
B4: 구 분 | C4: 단위 | D4: 전월잔액 | E4: 수 입 | F4: 지 출 | G4: 기준일 기준 잔액 | I4: SGD | J4: =IFERROR(__xludf.DUMMYFUNCTION("GOOGLEFINANCE(""SGDKRW"")"),1143.885) -> 1143.885 | L4: 급여 | M4: 직원 급여
B5: 신한 #672 | C5: KRW | D5: ='24.03월'!G5 -> 1274897 | E5: =sumif($B$25:$B$131,B5,$E$25:$E$131) -> 53004360 | F5: =sumif($B$25:$B$131,B5,$F$25:$F$131) -> 29396307 | G5: =D5+E5-F5 -> 24882950 | L5: 미수금 | M5: 돌려 받을 예정인 금액 (ex. 부가세 환급금)
B6: 신한 #543 | C6: USD | D6: ='24.03월'!G6 -> 2.31 | E6: =sumif($B$25:$B$131,B6,$E$25:$E$131) -> 0 | F6: =sumif($B$25:$B$131,B6,$F$25:$F$131) -> 0 | G6: =D6+E6-F6 -> 2.31 | L6: 보증금 | M6: 보증금 (사무실 임대, 장비 리스 등)
B7: 하나 #304 | C7: KRW | D7: ='24.03월'!G7 -> 366090 | E7: =sumif($B$25:$B$131,B7,$E$25:$E$131) -> 270316965 | F7: =sumif($B$25:$B$131,B7,$F$25:$F$131) -> 269725890 | G7: =D7+E7-F7 -> 957165 | L7: 보통예금 | M7: 예금간 이체
B8: 하나 #138 | C8: USD | D8: ='24.03월'!G8 -> 3.35 | E8: =sumif($B$25:$B$131,B8,$E$25:$E$131) -> 199990 | F8: =sumif($B$25:$B$131,B8,$F$25:$F$131) -> 199993.35 | G8: =D8+E8-F8 -> 0 | L8: 복리후생비 | M8: 회식, 식대
B9: 기업 #019 | C9: KRW | D9: ='24.03월'!G9 -> 712114 | E9: =sumif($B$25:$B$131,B9,$E$25:$E$131) -> 244856555 | F9: =sumif($B$25:$B$131,B9,$F$25:$F$131) -> 216394638 | G9: =D9+E9-F9 -> 29174031 | H9: 일반계좌 | L9: 비품 | M9: 가구, 가전등 개당 단가 150만원이 넘는 용품
B10: 기업 #020 | C10: KRW | D10: ='24.03월'!G10 -> 0 | E10: =sumif($B$25:$B$131,B10,$E$25:$E$131) -> 0 | F10: =sumif($B$25:$B$131,B10,$F$25:$F$131) -> 0 | G10: =D10+E10-F10 -> 0 | H10: 기보보증금 | L10: 사무용품비 | M10: 비품, 소모품비를 제외한 업무용 사무용품 구입
B11: 기업 #010 | C11: USD | D11: ='24.03월'!G11 -> 0 | E11: =sumif($B$25:$B$131,B11,$E$25:$E$131) -> 0 | F11: =sumif($B$25:$B$131,B11,$F$25:$F$131) -> 0 | G11: =D11+E11-F11 -> 0 | L11: 서비스용역매출 | M11: 매출
B12: WISE USD | C12: USD | D12: ='24.03월'!G12 -> 230.8 | E12: =sumif($B$25:$B$131,B12,$E$25:$E$131) -> 99995.86 | F12: =sumif($B$25:$B$131,B12,$F$25:$F$131) -> 15198.98 | G12: =D12+E12-F12 -> 85027.68 | L12: 세금과공과 | M12: 세금 납부시
B13: WISE SGD | C13: SGD | D13: ='24.03월'!G13 -> 25.4 | E13: =sumif($B$25:$B$131,B13,$E$25:$E$131) -> 1000 | F13: =sumif($B$25:$B$131,B13,$F$25:$F$131) -> 1025.4 | G13: =D13+E13-F13 -> 0 | L13: 소모품비 | M13: 비품(150만원)으로 잡기에는 금액이 작은 비품
B14: WISE KRW | C14: KRW | D14: ='24.03월'!G14 -> 0 | E14: =sumif($B$25:$B$131,B14,$E$25:$E$131) -> 0 | F14: =sumif($B$25:$B$131,B14,$F$25:$F$131) -> 0 | G14: =D14+E14-F14 -> 0 | L14: 여비교통비 | M14: 출장, 대중교통, 대리운전
B15: OCBC USD | C15: USD | D15: ='24.03월'!G15 -> 450708.02 | E15: =sumif($B$25:$B$131,B15,$E$25:$E$131) -> 0 | F15: =sumif($B$25:$B$131,B15,$F$25:$F$131) -> 311212.9 | G15: =D15+E15-F15 -> 139495.12 | L15: 용역비 | M15: 외주용역비
B16: OCBC SGD | C16: SGD | D16: ='24.03월'!G16 -> 308.19 | E16: =sumif($B$25:$B$131,B16,$E$25:$E$131) -> 0 | F16: =sumif($B$25:$B$131,B16,$F$25:$F$131) -> 10 | G16: =D16+E16-F16 -> 298.19 | L16: 접대비 | M16: 외부 미팅
H17: 기준일 기준 잔액 | I17: 전월잔액 | L17: 지급수수료 | M17: sms 수수료, 송금 수수료, 일반적으로 발생되는 모든 비용
B18: KRW 합 계 | D18: =D5+D7+D14+D9+D10 -> 2353101 | E18: =E5+E7+E14+E9+E10 -> 568177880 | F18: =F5+F7+F14+F9+F10 -> 515516835 | G18: =G5+G7+G14+G9+G10 -> 55014146 | H18: =G18 -> 55014146 | I18: =D18 -> 2353101 | L18: 이자수익 | M18: 은행이자
B19: USD 합 계 | D19: =D6+D8+D12+D15+D11 -> 450944.48 | E19: =E6+E8+E12+E15+E11 -> 299985.86 | F19: =F6+F8+F12+F15+F11 -> 526405.23 | G19: =G6+G8+G12+G15+G11 -> 224525.11 | H19: =rounddown(G19*$J$3,0) -> 330663742 | I19: =rounddown(D19*$J$3,0) -> 664117209 | L19: 통신비 | M19: 등기, 퀵 사용비
B20: SGD 합 계 | D20: =D13+D16 -> 333.59 | E20: =E13+E16 -> 1000 | F20: =F13+F16 -> 1035.4 | G20: =G13+G16 -> 298.19 | H20: =rounddown(G20*$J$4,0) -> 341095 | I20: =rounddown(D20*$J$4,0) -> 381588 | L20: 마케팅비 | M20: PR 기사등 마케팅 비용
H21: =SUM(H18:H20) -> 386018983 | I21: =SUM(I18:I20) -> 666851898 | L21: 대여금 | M21: 싱가폴 -> 한국 지사 송금
H22: =H21-I21 -> -280832915 | L22: 출장비 | M22: 출장여비
B23: ※ 세부내역 | L23: 투자자산 | M23: 투자
B24: 구 분 | C24: 날 짜 | D24: 은 행 적 요 | E24: 수입 | F24: 지출 | G24: 상세메모 | H24: 계정과목 | L24: 가수금 | M24: 가수금
B25: =B15 -> OCBC USD | C25: 2024.04.01 | D25: Milestone Business Group | F25: 11063.45 | G25: Chris 4월 급여, 개인경비 | H25: 급여 | L25: 잡이익 | M25: 잡이익
B26: =B15 -> OCBC USD | C26: 2024.04.01 | D26: OCBD BANK | F26: =15+22.41 -> 37.41 | G26: 송금 수수료 | H26: 지급수수료 | L26: 정기예적금 | M26: 정기예적금
B27: =B15 -> OCBC USD | C27: 2024.04.01 | D27: ZERO X AND PTE | F27: 100000 | G27: 계좌간 자금 이체 | H27: 보통예금 | L27: 단기차입금 | M27: 기보 대출금
B28: =B15 -> OCBC USD | C28: 2024.04.01 | D28: OCBD BANK | F28: =15+22.41 -> 37.41 | G28: 송금 수수료 | H28: 지급수수료 | L28: 이자비용 | M28: 기보 대출이자
B29: =B15 -> OCBC USD | C29: 2024.04.01 | D29: ZERO X AND PTE | F29: 100000 | G29: 계좌간 자금 이체 | H29: 보통예금 | L29: 현금 | M29: 현금 인출
B30: =B15 -> OCBC USD | C30: 2024.04.01 | D30: OCBD BANK | F30: =15+22.41 -> 37.41 | G30: 송금 수수료 | H30: 지급수수료
B31: =B12 -> WISE USD | C31: 2024.04.01 | D31: ZERO X AND PTE | E31: 99995.86 | G31: 계좌간 자금 이체 | H31: 보통예금
B32: =B8 -> 하나 #138 | C32: 2024.04.02 | D32: ZERO X AND PTE | E32: 99995 | G32: 계좌간 자금 이체 | H32: 보통예금
B33: =B8 -> 하나 #138 | C33: 2024.04.03 | D33: 주식회사 제로엑스앤드코리아 | F33: 99998.35 | G33: 환전 | H33: 보통예금
B34: =B7 -> 하나 #304 | C34: 2024.04.03 | D34: 주식회사 제로엑스앤드코리아 | E34: 133789792 | G34: 환전 | H34: 보통예금
B35: =B7 -> 하나 #304 | C35: 2024.04.03 | D35: 주식회사 제로엑스앤드코리아 | F35: 124850000 | G35: 계좌간 자금 이체 | H35: 보통예금
B36: =B7 -> 하나 #304 | C36: 2024.04.03 | D36: 하나은행 | F36: 500 | G36: 송금수수료 지급 | H36: 지급수수료
B37: =B9 -> 기업 #019 | C37: 2024.04.03 | D37: 주식회사 제로엑스앤드코리아 | E37: 124850000 | G37: 계좌간 자금 이체 | H37: 보통예금
B38: =B5 -> 신한 #672 | C38: 2024.04.03 | D38: 주식회사 제로엑스앤드코리아 | E38: 5000000 | G38: 계좌간 자금 이체 | H38: 보통예금
B39: =B5 -> 신한 #672 | C39: 2024.04.03 | D39: 현대카드 | F39: 3689320 | G39: 법인카드 선지급 | H39: 지급수수료
B40: =B9 -> 기업 #019 | C40: 2024.04.03 | D40: 그림바우빌딩 | F40: 6229850 | G40: 3월 임대료,관리비,전기료 | H40: 지급수수료
B41: =B9 -> 기업 #019 | C41: 2024.04.03 | D41: 비앤케이 | F41: 825000 | G41: 3월 법률자문료 | H41: 지급수수료
B42: =B9 -> 기업 #019 | C42: 2024.04.03 | D42: 주식회사 워크앤조이 | F42: 196200 | G42: 3월 그룹웨어 사용료 지급 | H42: 지급수수료
B43: =B9 -> 기업 #019 | C43: 2024.04.03 | D43: 메가존소프트 주식회사 | F43: 419781 | G43: Google Workspace 3계정 추가 | H43: 지급수수료
B44: =B9 -> 기업 #019 | C44: 2024.04.03 | D44: 맥플러스 | F44: 6023000 | G44: 맥북 구입 (알마,알란) | H44: 비품
B45: =B9 -> 기업 #019 | C45: 2024.04.03 | D45: 노무법인 도원 | F45: 396000 | G45: 청년일자리도약장려금 (밀리 3차) | H45: 지급수수료
B46: =B9 -> 기업 #019 | C46: 2024.04.03 | D46: 주식회사 제로엑스앤드코리아 | F46: 5000000 | G46: 계좌간 자금 이체 | H46: 보통예금
B47: =B12 -> WISE USD | C47: 2024.04.05 | D47: Juneyoung Jeon | F47: 13592.62 | G47: 경비 정산 | H47: 복리후생비
B48: =B5 -> 신한 #672 | C48: 2023.04.05 | D48: 특허공제04회 | F48: 300000 | G48: 특허공제04회 | H48: 정기예적금
B49: =B5 -> 신한 #672 | C49: 2023.04.11 | D49: 2403고용보험 | F49: 1512970 | G49: 2403고용보험 | H49: 세금과공과
B50: =B5 -> 신한 #672 | C50: 2023.04.11 | D50: 2403산재보험 | F50: 544840 | G50: 2403산재보험 | H50: 세금과공과
B51: =B5 -> 신한 #672 | C51: 2023.04.11 | D51: 2403국민건강 | F51: 227760 | G51: 2403국민건강 | H51: 세금과공과
B52: =B5 -> 신한 #672 | C52: 2023.04.15 | D52: 주식회사제로엑스앤드코리아 | E52: 30000000 | F52: 0 | G52: 계좌간 자금 이체 | H52: 보통예금
B53: =B5 -> 신한 #672 | C53: 2023.04.15 | D53: 2403국민건강 | F53: 6792080 | G53: 2403국민건강 | H53: 세금과공과
B54: =B5 -> 신한 #672 | C54: 2023.04.15 | D54: 2403국민연금 | F54: 6953210 | G54: 2403국민연금 | H54: 세금과공과
B55: =B9 -> 기업 #019 | C55: 2023.04.15 | D55: 주식회사제로엑스앤드코리아 | F55: 30000000 | G55: 계좌간 자금 이체 | H55: 보통예금
B56: WISE USD | C56: 2024.04.14 | D56: Postmarkapp.com | F56: 10 | G56: 서비스 이용료 지급 | H56: 지급수수료
B57: WISE USD | C57: 2024.04.14 | D57: ZERO X AND PTE. LTD. | F57: 735.7 | G57: USD -> SGD 환전 | H57: 보통예금
B58: WISE SGD | C58: 2024.04.14 | D58: ZERO X AND PTE. LTD. | E58: 1000 | G58: USD -> SGD 환전 | H58: 보통예금
B59: WISE SGD | C59: 2024.04.14 | D59: Entra Law LLC | F59: 1000 | G59: 법무비용 | H59: 지급수수료
B60: =B5 -> 신한 #672 | C60: 2024.04.17 | D60: 신한은행 | F60: 2000 | G60: 통장발급수수료 | H60: 지급수수료
